Workbook

Sheet CAPA
A1: #VALUE! | C1: #VALUE! | E1: CONSÓRIO CONSTRUTOR BR-381 | I1: Nº MEDIÇÃO | K1: TIPO
I2: 3 | K2: FINAL
A4: CONTRATO: | B4: 381/188/2025 | D4: EMPRESA: | E4: CONSÓRCIO CONSTRUTOR BR-381 | H4: STATUS CONTRATUAL
A5: OBJETO: | B5: RECOMPOSIÇÃO DE TALUDES - SINISTRO 297+500 - OESTE | H5: R$ CONTRATUAL: | J5: =PQ!E140 -> 6891850.4 | L5: =SUM(L12:L13,L17,L22,L27:L28) -> 0.98371424
A6: TRECHO: | B6: GOV. VALADARES A CAETÉ
A7: RODOVIA: | B7: BR-381 | D7: EXTENSÃO: | H7: R$ MEDIÇÃO: | J7: =SUM(G12,G13,G17,G22,G27,G28) -> 2352439.6
A8: MEDIÇÃO: | B8: =I2 -> 3 | D8: PERÍODO: | E8: 24/09/2025 A 23/10/2025
A10: GRUPO DE SERVIÇOS | E10: ACUMULADO ANTERIOR | G10: =_xlfn.CONCAT(TEXT(I2,"00"),"ª MEDIÇÃO"," ",K2) -> 03ª MEDIÇÃO FINAL | I10: ACUMULADO ATUAL | K10: MEDIÇÃO ATUAL | L10: ACUMULADO
A12: =PQ!B13 -> A. | B12: =UPPER(VLOOKUP(A12,RESUMO!C:D,2,FALSE)) -> CUSTOS INDIRETOS | E12: =VLOOKUP($A12,PQ!$B:$R,9,FALSE)*1.182 -> 650700.05 | G12: =VLOOKUP($A12,PQ!$B:$R,11,FALSE)*1.182 -> 0 | I12: =VLOOKUP($A12,PQ!$B:$R,13,FALSE)*1.182 -> 650700.05 | K12: =IF(G12/$J$5=0,"",G12/$J$5) | L12: =IF(I12/$J$5=0,"",I12/$J$5) -> 0.09441587
A13: =PQ!B17 -> B. | B13: =UPPER(VLOOKUP(A13,RESUMO!C:D,2,FALSE)) -> ESTABILIZAÇÃO DE TALUDE | E13: =VLOOKUP($A13,PQ!$B:$R,9,FALSE)*1.182 -> 2361880.2 | G13: =VLOOKUP($A13,PQ!$B:$R,11,FALSE)*1.182 -> 2211056 | I13: =VLOOKUP($A13,PQ!$B:$R,13,FALSE)*1.182 -> 4572936.2 | K13: =IF(G13/$J$5=0,"",G13/$J$5) -> 0.32082182 | L13: =IF(I13/$J$5=0,"",I13/$J$5) -> 0.66352807
A14: =PQ!B18 -> B.1 | B14: =UPPER(VLOOKUP(A14,RESUMO!C:D,2,FALSE)) -> TERRAPLENAGEM | E14: =VLOOKUP($A14,PQ!$B:$R,9,FALSE)*1.182 -> 2085619.7 | G14: =VLOOKUP($A14,PQ!$B:$R,11,FALSE)*1.182 -> 1036960.7 | I14: =VLOOKUP($A14,PQ!$B:$R,13,FALSE)*1.182 -> 3122580.4 | K14: =IF(G14/$J$5=0,"",G14/$J$5) -> 0.15046187 | L14: =IF(I14/$J$5=0,"",I14/$J$5) -> 0.45308302
A15: =PQ!B28 -> B.2 | B15: =UPPER(VLOOKUP(A15,RESUMO!C:D,2,FALSE)) -> DRENAGEM E OACS | E15: =VLOOKUP($A15,PQ!$B:$R,9,FALSE)*1.182 -> 0 | G15: =VLOOKUP($A15,PQ!$B:$R,11,FALSE)*1.182 -> 439810.25 | I15: =VLOOKUP($A15,PQ!$B:$R,13,FALSE)*1.182 -> 439810.25 | K15: =IF(G15/$J$5=0,"",G15/$J$5) -> 0.063815989 | L15: =IF(I15/$J$5=0,"",I15/$J$5) -> 0.063815989
A16: =PQ!B38 -> B.3 | B16: =UPPER(VLOOKUP(A16,RESUMO!C:D,2,FALSE)) -> REVESTIMENTO VEGETAL | E16: =VLOOKUP($A16,PQ!$B:$R,9,FALSE)*1.182 -> 276260.49 | G16: =VLOOKUP($A16,PQ!$B:$R,11,FALSE)*1.182 -> 734285.08 | I16: =VLOOKUP($A16,PQ!$B:$R,13,FALSE)*1.182 -> 1010545.6 | K16: =IF(G16/$J$5=0,"",G16/$J$5) -> 0.10654397 | L16: =IF(I16/$J$5=0,"",I16/$J$5) -> 0.14662906
A17: =PQ!B41 -> C. | B17: =UPPER(VLOOKUP(A17,RESUMO!C:D,2,FALSE)) -> IMPLANTAÇÃO DE DESVIO 1 - KM 303+450 - LESTE | E17: =VLOOKUP($A17,PQ!$B:$R,9,FALSE)*1.182 -> 917970.25 | G17: =VLOOKUP($A17,PQ!$B:$R,11,FALSE)*1.182 -> 31336.711 | I17: =VLOOKUP($A17,PQ!$B:$R,13,FALSE)*1.182 -> 949306.97 | K17: =IF(G17/$J$5=0,"",G17/$J$5) -> 0.0045469227 | L17: =IF(I17/$J$5=0,"",I17/$J$5) -> 0.13774341
A18: =PQ!B42 -> C.1 | B18: =UPPER(VLOOKUP(A18,RESUMO!C:D,2,FALSE)) -> TERRAPLENAGEM | E18: =VLOOKUP($A18,PQ!$B:$R,9,FALSE)*1.182 -> 29257.461 | G18: =VLOOKUP($A18,PQ!$B:$R,11,FALSE)*1.182 -> 0 | I18: =VLOOKUP($A18,PQ!$B:$R,13,FALSE)*1.182 -> 29257.461 | K18: =IF(G18/$J$5=0,"",G18/$J$5) | L18: =IF(I18/$J$5=0,"",I18/$J$5) -> 0.0042452257
A19: =PQ!B48 -> C.2 | B19: =UPPER(VLOOKUP(A19,RESUMO!C:D,2,FALSE)) -> PAVIMENTAÇÃO | E19: =VLOOKUP($A19,PQ!$B:$R,9,FALSE)*1.182 -> 510414.79 | G19: =VLOOKUP($A19,PQ!$B:$R,11,FALSE)*1.182 -> 0 | I19: =VLOOKUP($A19,PQ!$B:$R,13,FALSE)*1.182 -> 510414.79 | K19: =IF(G19/$J$5=0,"",G19/$J$5) | L19: =IF(I19/$J$5=0,"",I19/$J$5) -> 0.074060631
A20: =PQ!B55 -> C.3 | B20: =UPPER(VLOOKUP(A20,RESUMO!C:D,2,FALSE)) -> MATERIAL BETUMINOSO E TRANSPORTES | E20: =VLOOKUP($A20,PQ!$B:$R,9,FALSE)*1.182 -> 378298 | G20: =VLOOKUP($A20,PQ!$B:$R,11,FALSE)*1.182 -> 0 | I20: =VLOOKUP($A20,PQ!$B:$R,13,FALSE)*1.182 -> 378298 | K20: =IF(G20/$J$5=0,"",G20/$J$5) | L20: =IF(I20/$J$5=0,"",I20/$J$5) -> 0.054890628
A21: =PQ!B62 -> C.4 | B21: =UPPER(VLOOKUP(A21,RESUMO!C:D,2,FALSE)) -> DRENAGEM E OACS | E21: =VLOOKUP($A21,PQ!$B:$R,9,FALSE)*1.182 -> 0 | G21: =VLOOKUP($A21,PQ!$B:$R,11,FALSE)*1.182 -> 31336.711 | I21: =VLOOKUP($A21,PQ!$B:$R,13,FALSE)*1.182 -> 31336.711 | K21: =IF(G21/$J$5=0,"",G21/$J$5) -> 0.0045469227 | L21: =IF(I21/$J$5=0,"",I21/$J$5) -> 0.0045469227
A22: =PQ!B68 -> D. | B22: =UPPER(VLOOKUP(A22,RESUMO!C:D,2,FALSE)) -> IMPLANTAÇÃO DE DESVIOS 2 E 3 | E22: =VLOOKUP($A22,PQ!$B:$R,9,FALSE)*1.182 -> 473829.21 | G22: =VLOOKUP($A22,PQ!$B:$R,11,FALSE)*1.182 -> -11511.412 | I22: =VLOOKUP($A22,PQ!$B:$R,13,FALSE)*1.182 -> 462317.8 | K22: =IF(G22/$J$5=0,"",G22/$J$5) -> -0.0016702934 | L22: =IF(I22/$J$5=0,"",I22/$J$5) -> 0.06708181
A23: =PQ!B69 -> D.1 | B23: =UPPER(VLOOKUP(A23,RESUMO!C:D,2,FALSE)) -> TERRAPLENAGEM | E23: =VLOOKUP($A23,PQ!$B:$R,9,FALSE)*1.182 -> 29346.462 | G23: =VLOOKUP($A23,PQ!$B:$R,11,FALSE)*1.182 -> -21369.765 | I23: =VLOOKUP($A23,PQ!$B:$R,13,FALSE)*1.182 -> 7976.6974 | K23: =IF(G23/$J$5=0,"",G23/$J$5) -> -0.0031007297 | L23: =IF(I23/$J$5=0,"",I23/$J$5) -> 0.0011574101
A24: =PQ!B75 -> D.2 | B24: =UPPER(VLOOKUP(A24,RESUMO!C:D,2,FALSE)) -> PAVIMENTO | E24: =VLOOKUP($A24,PQ!$B:$R,9,FALSE)*1.182 -> 254629.92 | G24: =VLOOKUP($A24,PQ!$B:$R,11,FALSE)*1.182 -> 0 | I24: =VLOOKUP($A24,PQ!$B:$R,13,FALSE)*1.182 -> 254629.92 | K24: =IF(G24/$J$5=0,"",G24/$J$5) | L24: =IF(I24/$J$5=0,"",I24/$J$5) -> 0.036946525
A25: =PQ!B83 -> D.3 | B25: =UPPER(VLOOKUP(A25,RESUMO!C:D,2,FALSE)) -> MATERIAL BETUMINOSO E TRANSPORTES | E25: =VLOOKUP($A25,PQ!$B:$R,9,FALSE)*1.182 -> 189852.83 | G25: =VLOOKUP($A25,PQ!$B:$R,11,FALSE)*1.182 -> 0 | I25: =VLOOKUP($A25,PQ!$B:$R,13,FALSE)*1.182 -> 189852.83 | K25: =IF(G25/$J$5=0,"",G25/$J$5) | L25: =IF(I25/$J$5=0,"",I25/$J$5) -> 0.027547439
A26: =PQ!B90 -> D.4 | B26: =UPPER(VLOOKUP(A26,RESUMO!C:D,2,FALSE)) -> DRENAGEM E OACS | E26: =VLOOKUP($A26,PQ!$B:$R,9,FALSE)*1.182 -> 0 | G26: =VLOOKUP($A26,PQ!$B:$R,11,FALSE)*1.182 -> 9858.3528 | I26: =VLOOKUP($A26,PQ!$B:$R,13,FALSE)*1.182 -> 9858.3528 | K26: =IF(G26/$J$5=0,"",G26/$J$5) -> 0.0014304363 | L26: =IF(I26/$J$5=0,"",I26/$J$5) -> 0.0014304363
A27: =PQ!B93 -> E. | B27: =UPPER(VLOOKUP(A27,RESUMO!C:D,2,FALSE)) -> SINALIZAÇÃO HORIZONTAL, VERTICAL E ELEMENTOS DE PROTEÇÃO E SEGURANÇA | E27: =VLOOKUP($A27,PQ!$B:$R,9,FALSE)*1.182 -> 22792.053 | G27: =VLOOKUP($A27,PQ!$B:$R,11,FALSE)*1.182 -> 0 | I27: =VLOOKUP($A27,PQ!$B:$R,13,FALSE)*1.182 -> 22792.053 | K27: =IF(G27/$J$5=0,"",G27/$J$5) | L27: =IF(I27/$J$5=0,"",I27/$J$5) -> 0.003307102
A28: =PQ!B95 -> F. | B28: =UPPER(VLOOKUP(A28,RESUMO!C:D,2,FALSE)) -> MÃO DE OBRA E EQUIPAMENTOS | E28: =VLOOKUP($A28,PQ!$B:$R,9,FALSE)*1.182 -> 0 | G28: =VLOOKUP($A28,PQ!$B:$R,11,FALSE)*1.182 -> 121558.3 | I28: =VLOOKUP($A28,PQ!$B:$R,13,FALSE)*1.182 -> 121558.3 | K28: =IF(G28/$J$5=0,"",G28/$J$5) -> 0.017637978 | L28: =IF(I28/$J$5=0,"",I28/$J$5) -> 0.017637978
A29: =PQ!B96 -> F.1 | B29: =UPPER(VLOOKUP(A29,RESUMO!C:D,2,FALSE)) -> MÃO DE OBRA | E29: =VLOOKUP($A29,PQ!$B:$R,9,FALSE)*1.182 -> 0 | G29: =VLOOKUP($A29,PQ!$B:$R,11,FALSE)*1.182 -> 15329.925 | I29: =VLOOKUP($A29,PQ!$B:$R,13,FALSE)*1.182 -> 15329.925 | K29: =IF(G29/$J$5=0,"",G29/$J$5) -> 0.0022243555 | L29: =IF(I29/$J$5=0,"",I29/$J$5) -> 0.0022243555
A30: =PQ!B100 -> F.2 | B30: =UPPER(VLOOKUP(A30,RESUMO!C:D,2,FALSE)) -> EQUIPAMENTOS | E30: =VLOOKUP($A30,PQ!$B:$R,9,FALSE)*1.182 -> 0 | G30: =VLOOKUP($A30,PQ!$B:$R,11,FALSE)*1.182 -> 106228.38 | I30: =VLOOKUP($A30,PQ!$B:$R,13,FALSE)*1.182 -> 106228.38 | K30: =IF(G30/$J$5=0,"",G30/$J$5) -> 0.015413622 | L30: =IF(I30/$J$5=0,"",I30/$J$5) -> 0.015413622

Sheet PQ
B2: BOLETIM DE MEDIÇÃO DE SERVIÇOS - BMS | I2: CONTRATO | L2: PERIODO MEDIÇÃO | N2: MEDIÇÃO | P2: Nº DO BMS | T2: Rev. 01
I3: 381/188/2025 | P3: MED. 03 - rev03 | T3: Base: Jan/25
I4: VIGÊNCIA | L4: INÍCIO: | M4: 45924 | P4: DATA DE EMISSÃO
L5: FINAL: | M5: 45953 | P5: 45978
B6: EMPRESA | C6: CONSÓRCIO CONSTRUTOR BR-381 | I6: OBJETO CONTRATUAL | P6: CENTRO DE CUSTO
B7: ENDEREÇO | C7: R PROJETADA 30, 386, PEDRA FURADA | I7: RECOMPOSIÇÃO DE TALUDES - SINISTRO 297+500 - OESTE
B8: CIDADE/UF: | C8: NOVA ERA/MG
B9: TELEFONE: | C9: (31) 9 9659-1026 | D9: E-MAIL: | E9: ygor.bastos@consorcio381.com.br
B10: ITEM | C10: DESCRIÇÃO | D10: CENTRO DE CUSTO | E10: BASES CONTRATUAIS - rev01 | I10: REALIZADO | P10: A REALIZAR | T10: BASES CONTRATUAIS
E11: UNID. | F11: P. UNITÁRIO (R$ / UNID.) | G11: QTDE | H11: VALOR TOTAL | I11: ACUMULADO ANTERIOR | K11: PERÍODO | M11: ACUMULADO ATUAL | P11: SALDO | T11: UNID. | U11: P. UNITÁRIO (R$ / UNID.) | V11: QTDE | W11: VALOR TOTAL
I12: QTDE | J12: VALOR | K12: QTDE | L12: VALOR | M12: QTDE | N12: VALOR | O12: % | P12: QTDE | Q12: VALOR | R12: %
B13: A. | C13: Custos Indiretos | H13: =SUM(H14:H16) -> 550507.66 | J13: =SUM(J14:J16) -> 550507.66 | L13: =SUM(L14:L16) -> 0 | N13: =SUM(N14:N16) -> 550507.66 | Q13: =SUM(Q14:Q16) -> 0 | W13: =SUM(W14:W16) -> 550507.67
B14: A.1 | C14: Mobilização e desmobilização | E14: vb. | F14: 22570.81 | G14: 1 | H14: =F14*G14 -> 22570.81 | I14: =RESUMO!H9 -> 1 | J14: =RESUMO!M9 -> 22570.81 | K14: =RESUMO!I9 -> 0 | L14: =RESUMO!N9 -> 0 | M14: =RESUMO!J9 -> 1 | N14: =RESUMO!O9 -> 22570.81 | O14: =RESUMO!R9 -> 1 | P14: =RESUMO!K9 -> 0 | Q14: =RESUMO!P9 -> 0 | R14: =1-O14 -> 0 | T14: vb. | U14: 22570.814 | V14: 1 | W14: =V14*U14 -> 22570.814
B15: A.2 | C15: Sinalização e desvio de tráfego | E15: vb. | F15: 45141.63 | G15: 1 | H15: =F15*G15 -> 45141.63 | I15: =RESUMO!H10 -> 1 | J15: =RESUMO!M10 -> 45141.63 | K15: =RESUMO!I10 -> 0 | L15: =RESUMO!N10 -> 0 | M15: =RESUMO!J10 -> 1 | N15: =RESUMO!O10 -> 45141.63 | O15: =RESUMO!R10 -> 1 | P15: =RESUMO!K10 -> 0 | Q15: =RESUMO!P10 -> 0 | R15: =1-O15 -> 0 | T15: vb. | U15: 45141.629 | V15: 1 | W15: =V15*U15 -> 45141.629
B16: A.3 | C16: Administração local | E16: vb. | F16: 482795.22 | G16: 1 | H16: =F16*G16 -> 482795.22 | I16: =RESUMO!H11 -> 1 | J16: =RESUMO!M11 -> 482795.22 | K16: =RESUMO!I11 -> 0 | L16: =RESUMO!N11 -> 0 | M16: =RESUMO!J11 -> 1 | N16: =RESUMO!O11 -> 482795.22 | O16: =RESUMO!R11 -> 1 | P16: =RESUMO!K11 -> 0 | Q16: =RESUMO!P11 -> 0 | R16: =1-O16 -> 0 | T16: vb. | U16: 482795.22 | V16: 1 | W16: =V16*U16 -> 482795.22
B17: B. | C17: Estabilização de Talude | H17: =SUBTOTAL(9,H18:H40) -> 3675277.4 | J17: =SUBTOTAL(9,J18:J40) -> 1998206.6 | L17: =SUBTOTAL(9,L18:L40) -> 1870605.8 | N17: =SUBTOTAL(9,N18:N40) -> 3868812.4 | Q17: =SUBTOTAL(9,Q18:Q40) -> -193535.02 | W17: =SUBTOTAL(9,W18:W39) -> 3578784
B18: B.1 | C18: Terraplenagem | H18: =SUBTOTAL(9,H19:H27) -> 2726353.3 | J18: =SUBTOTAL(9,J19:J27) -> 1764483.7 | L18: =SUBTOTAL(9,L19:L27) -> 877293.31 | N18: =SUBTOTAL(9,N19:N27) -> 2641777 | Q18: =SUBTOTAL(9,Q19:Q27) -> 84576.263 | W18: =SUBTOTAL(9,W19:W23) -> 2838512.9
B19: B.1.1 | C19: Escavação, carga e transporte de material de 1ª categoria - DMT de 800 a 1.000 m - caminho de serviço pavimentado - com escavadeira e caminhão basculante de 14 m³ | E19: m³ | F19: 0 | G19: 0 | H19: =F19*G19 -> 0 | I19: =RESUMO!H14 -> 0 | J19: =RESUMO!M14 -> 0 | K19: =RESUMO!I14 -> 0 | L19: =RESUMO!N14 -> 0 | M19: =RESUMO!J14 -> 0 | N19: =RESUMO!O14 -> 0 | O19: =RESUMO!R14 -> 0 | P19: =RESUMO!K14 -> 0 | Q19: =RESUMO!P14 -> 0 | R19: =1-O19 -> 1 | T19: m³ | U19: 10.09 | V19: 25000 | W19: =ROUND(V19*U19,2) -> 252250
B20: B.1.2 | C20: Escavação e carga de material de 1ª categoria - DMT acima de 3.000 m | E20: m³ | F20: 15.86326 | G20: 72616.71 | H20: =F20*G20 -> 1151937.7 | I20: =RESUMO!H15 -> 62616.71 | J20: =RESUMO!M15 -> 993305.14 | K20: =RESUMO!I15 -> 6145.816 | L20: =RESUMO!N15 -> 97492.676 | M20: =RESUMO!J15 -> 68762.526 | N20: =RESUMO!O15 -> 1090797.8 | O20: =RESUMO!R15 -> 0.94692428 | P20: =RESUMO!K15 -> 3854.184 | Q20: =RESUMO!P15 -> 61139.922 | R20: =1-O20 -> 0.053075718 | T20: m³ | U20: 15.86326 | V20: 94031.76 | W20: =ROUND(V20*U20,2) -> 1491650.2
B21: B.1.3 | C21: Transporte com caminhão basculante de 10 m³ - rodovia pavimentada (DMT 5 Km) | E21: T x Km | F21: 1.0278799 | G21: 543194.94 | H21: =F21*G21 -> 558339.16 | I21: =RESUMO!H16 -> 483457.86 | J21: =RESUMO!M16 -> 496936.61 | K21: =RESUMO!I16 -> 47451.28 | L21: =RESUMO!N16 -> 48774.217 | M21: =RESUMO!J16 -> 530909.14 | N21: =RESUMO!O16 -> 545710.83 | O21: =RESUMO!R16 -> 0.97738233 | P21: =RESUMO!K16 -> 12285.803 | Q21: =RESUMO!P16 -> 12628.33 | R21: =1-O21 -> 0.022617668 | T21: T x Km | U21: 1.0278799 | V21: 752254.08 | W21: =ROUND(V21*U21,2) -> 773226.85
B22: B.1.4 | C22: Regularização de bota-fora com espalhamento e execução de hidrossemeadura | E22: m³ | F22: 0 | G22: 0 | H22: =F22*G22 -> 0 | I22: =RESUMO!H17 -> 0 | J22: =RESUMO!M17 -> 0 | K22: =RESUMO!I17 -> 0 | L22: =RESUMO!N17 -> 0 | M22: =RESUMO!J17 -> 0 | N22: =RESUMO!O17 -> 0 | O22: =RESUMO!R17 -> 0 | P22: =RESUMO!K17 -> 0 | Q22: =RESUMO!P17 -> 0 | R22: =1-O22 -> 1 | T22: m³ | U22: 2.7 | V22: 119031.76 | W22: =ROUND(V22*U22,2) -> 321385.75
B23: B.1.5 | C23: Royaltie de bota-fora | E23: m³ | F23: 0 | G23: 0 | H23: =F23*G23 -> 0 | I23: =RESUMO!H18 -> 0 | J23: =RESUMO!M18 -> 0 | K23: =RESUMO!I18 -> 0 | L23: =RESUMO!N18 -> 0 | M23: =RESUMO!J18 -> 0 | N23: =RESUMO!O18 -> 0 | O23: =RESUMO!R18 -> 0 | P23: =RESUMO!K18 -> 0 | Q23: =RESUMO!P18 -> 0 | R23: =1-O23 -> 1
B24: B.1.6 | C24: Desmatamento, destocamento, limpeza de área e estocagem do material de limpeza com árvores de diâmetro até 0,15 m | E24: m² | F24: 0.85999993 | G24: 23377.56 | H24: =F24*G24 -> 20104.7 | I24: =RESUMO!H19 -> 0 | J24: =RESUMO!M19 -> 0 | K24: =RESUMO!I19 -> 21252.33 | L24: =RESUMO!N19 -> 18277.002 | M24: =RESUMO!J19 -> 21252.33 | N24: =RESUMO!O19 -> 18277.002 | O24: =RESUMO!R19 -> 0.90909103 | P24: =RESUMO!K19 -> 2125.23 | Q24: =RESUMO!P19 -> 1827.6977 | R24: =1-O24 -> 0.090908974
B25: B.1.7 | C25: Escavação, carga e transporte de material de 1ª categoria - DMT de 1.400 a 1.600 m - caminho de serviço pavimentado - com escavadeira e caminhão basculante de 14 m³ | E25: m³ | F25: 12.629999 | G25: 55083.7 | H25: =F25*G25 -> 695707.09 | I25: =RESUMO!H20 -> 0 | J25: =RESUMO!M20 -> 0 | K25: =RESUMO!I20 -> 55083.697 | L25: =RESUMO!N20 -> 695707.05 | M25: =RESUMO!J20 -> 55083.697 | N25: =RESUMO!O20 -> 695707.05 | O25: =RESUMO!R20 -> 0.99999995 | P25: =RESUMO!K20 -> 0.003 | Q25: =RESUMO!P20 -> 0.037889998 | R25: =1-O25 -> 5.4462572e-08
B26: B.1.8 | C26: Escavação e carga de material de 2ª categoria - DMT acima de 3.000 m | E26: m³ | F26: 19.519859 | G26: 139.48 | H26: =F26*G26 -> 2722.63 | I26: =RESUMO!H21 -> 0 | J26: =RESUMO!M21 -> 0 | K26: =RESUMO!I21 -> 139.479 | L26: =RESUMO!N21 -> 2722.6105 | M26: =RESUMO!J21 -> 139.479 | N26: =RESUMO!O21 -> 2722.6105 | O26: =RESUMO!R21 -> 0.99999283 | P26: =RESUMO!K21 -> 0.001 | Q26: =RESUMO!P21 -> 0.019519859 | R26: =1-O26 -> 7.1694867e-06
B27: B.1.9 | C27: Regularização de bota-fora | E27: m³ | F27: 2.33 | G27: 127700.41 | H27: =F27*G27 -> 297541.95 | I27: =RESUMO!H22 -> 117700.41 | J27: =RESUMO!M22 -> 274241.94 | K27: =RESUMO!I22 -> 6145.816 | L27: =RESUMO!N22 -> 14319.751 | M27: =RESUMO!J22 -> 123846.22 | N27: =RESUMO!O22 -> 288561.69 | O27: =RESUMO!R22 -> 0.96981852 | P27: =RESUMO!K22 -> 3854.187 | Q27: =RESUMO!P22 -> 8980.2556 | R27: =1-O27 -> 0.030181477
B28: B.2 | C28: Drenagem e OACs | H28: =SUBTOTAL(9,H29:H37) -> 549924.1 | J28: =SUBTOTAL(9,J29:J37) -> 0 | L28: =SUBTOTAL(9,L29:L37) -> 372089.89 | N28: =SUBTOTAL(9,N29:N37) -> 372089.89 | Q28: =SUBTOTAL(9,Q29:Q37) -> 177834.21 | W28: =SUBTOTAL(9,W29:W33) -> 335471.11
B29: B.2.1 | C29: Demolição de dispositivos de drenagem | E29: m³ | F29: 0 | G29: 0 | H29: =F29*G29 -> 0 | I29: =RESUMO!H24 -> 0 | J29: =RESUMO!M24 -> 0 | K29: =RESUMO!I24 -> 0 | L29: =RESUMO!N24 -> 0 | M29: =RESUMO!J24 -> 0 | N29: =RESUMO!O24 -> 0 | O29: =RESUMO!R24 -> 0 | P29: =RESUMO!K24 -> 0 | Q29: =RESUMO!P24 -> 0 | R29: =1-O29 -> 1 | T29: m³ | U29: 488.98472 | V29: 102 | W29: =ROUND(V29*U29,2) -> 49876.44
B30: B.2.2 | C30: Sarjeta triangular de concreto - STC 150-30 - escavação mecânica - areia e brita comerciais | E30: m | F30: 0 | G30: 0 | H30: =F30*G30 -> 0 | I30: =RESUMO!H25 -> 0 | J30: =RESUMO!M25 -> 0 | K30: =RESUMO!I25 -> 0 | L30: =RESUMO!N25 -> 0 | M30: =RESUMO!J25 -> 0 | N30: =RESUMO!O25 -> 0 | O30: =RESUMO!R25 -> 0 | P30: =RESUMO!K25 -> 0 | Q30: =RESUMO!P25 -> 0 | R30: =1-O30 -> 1 | T30: m | U30: 148.7 | V30: 633 | W30: =ROUND(V30*U30,2) -> 94127.1
B31: B.2.3 | C31: Valeta de proteção de cortes com revestimento de concreto - VPC 04 - areia e brita comerciais | E31: m | F31: 0 | G31: 0 | H31: =F31*G31 -> 0 | I31: =RESUMO!H26 -> 0 | J31: =RESUMO!M26 -> 0 | K31: =RESUMO!I26 -> 0 | L31: =RESUMO!N26 -> 0 | M31: =RESUMO!J26 -> 0 | N31: =RESUMO!O26 -> 0 | O31: =RESUMO!R26 -> 0 | P31: =RESUMO!K26 -> 0 | Q31: =RESUMO!P26 -> 0 | R31: =1-O31 -> 1 | T31: m | U31: 157.87 | V31: 142 | W31: =ROUND(V31*U31,2) -> 22417.54
B32: B.2.4 | C32: Caixa coletora A6 - CCS 200-60A | E32: und. | F32: 0 | G32: 0 | H32: =F32*G32 -> 0 | I32: =RESUMO!H27 -> 0 | J32: =RESUMO!M27 -> 0 | K32: =RESUMO!I27 -> 0 | L32: =RESUMO!N27 -> 0 | M32: =RESUMO!J27 -> 0 | N32: =RESUMO!O27 -> 0 | O32: =RESUMO!R27 -> 0 | P32: =RESUMO!K27 -> 0 | Q32: =RESUMO!P27 -> 0 | R32: =1-O32 -> 1 | T32: und. | U32: 5875.66 | V32: 4 | W32: =ROUND(V32*U32,2) -> 23502.64
B33: B.2.5 | C33: Descida d'água de cortes em degraus - DCD 02 - areia e brita comerciais | E33: m | F33: 0 | G33: 0 | H33: =F33*G33 -> 0 | I33: =RESUMO!H28 -> 0 | J33: =RESUMO!M28 -> 0 | K33: =RESUMO!I28 -> 0 | L33: =RESUMO!N28 -> 0 | M33: =RESUMO!J28 -> 0 | N33: =RESUMO!O28 -> 0 | O33: =RESUMO!R28 -> 0 | P33: =RESUMO!K28 -> 0 | Q33: =RESUMO!P28 -> 0 | R33: =1-O33 -> 1 | T33: m | U33: 963.89 | V33: 151 | W33: =ROUND(V33*U33,2) -> 145547.39
B34: B.2.6 | C34: Descida d'água de cortes em degraus - DCD 100-50 - areia e brita comerciais | E34: m | F34: 1034 | G34: 292.6 | H34: =F34*G34 -> 302548.4 | I34: =RESUMO!H29 -> 0 | J34: =RESUMO!M29 -> 0 | K34: =RESUMO!I29 -> 112.54 | L34: =RESUMO!N29 -> 116366.36 | M34: =RESUMO!J29 -> 112.54 | N34: =RESUMO!O29 -> 116366.36 | O34: =RESUMO!R29 -> 0.38462064 | P34: =RESUMO!K29 -> 180.06 | Q34: =RESUMO!P29 -> 186182.04 | R34: =1-O34 -> 0.61537936
B35: B.2.7 | C35: Valeta de proteção de cortes com revestimento de concreto - VPCC 120-30 - escavação mecânica - areia e brita comerciais | E35: m | F35: 141.79 | G35: 1111 | H35: =F35*G35 -> 157528.69 | I35: =RESUMO!H30 -> 0 | J35: =RESUMO!M30 -> 0 | K35: =RESUMO!I30 -> 1513.65 | L35: =RESUMO!N30 -> 214620.43 | M35: =RESUMO!J30 -> 1513.65 | N35: =RESUMO!O30 -> 214620.43 | O35: =RESUMO!R30 -> 1.3624212 | P35: =RESUMO!K30 -> -402.65 | Q35: =RESUMO!P30 -> -57091.743 | R35: =1-O35 -> -0.36242124
B36: B.2.8 | C36: Caixa coletora de sarjeta - CCS 250-120 A - com grelha de concreto - areia e brita comerciais | E36: und. | F36: 7471.91 | G36: 11 | H36: =F36*G36 -> 82191.01 | I36: =RESUMO!H31 -> 0 | J36: =RESUMO!M31 -> 0 | K36: =RESUMO!I31 -> 4 | L36: =RESUMO!N31 -> 29887.64 | M36: =RESUMO!J31 -> 4 | N36: =RESUMO!O31 -> 29887.64 | O36: =RESUMO!R31 -> 0.36363636 | P36: =RESUMO!K31 -> 7 | Q36: =RESUMO!P31 -> 52303.37 | R36: =1-O36 -> 0.63636364
B37: B.2.9 | C37: Sarjeta triangular de concreto - STC 88-20 - escavação mecânica - areia e brita comerciais | E37: m | F37: 58 | G37: 132 | H37: =F37*G37 -> 7656 | I37: =RESUMO!H32 -> 0 | J37: =RESUMO!M32 -> 0 | K37: =RESUMO!I32 -> 193.37 | L37: =RESUMO!N32 -> 11215.46 | M37: =RESUMO!J32 -> 193.37 | N37: =RESUMO!O32 -> 11215.46 | O37: =RESUMO!R32 -> 1.4649242 | P37: =RESUMO!K32 -> -61.37 | Q37: =RESUMO!P32 -> -3559.46 | R37: =1-O37 -> -0.46492424
B38: B.3 | C38: Revestimento Vegetal | H38: =SUBTOTAL(9,H39:H40) -> 399000 | J38: =SUBTOTAL(9,J39:J40) -> 233722.92 | L38: =SUBTOTAL(9,L39:L40) -> 621222.57 | N38: =SUBTOTAL(9,N39:N40) -> 854945.49 | Q38: =SUBTOTAL(9,Q39:Q40) -> -455945.49 | W38: =SUBTOTAL(9,W39) -> 404800
B39: B.3.1 | C39: Proteção Vegetal (Hidrossemeadura + Biomanta) | E39: m² | F39: 25.3 | G39: 15000 | H39: =F39*G39 -> 379500 | I39: =RESUMO!H34 -> 9238.06 | J39: =RESUMO!M34 -> 233722.92 | K39: =RESUMO!I34 -> 22721.098 | L39: =RESUMO!N34 -> 574843.77 | M39: =RESUMO!J34 -> 31959.158 | N39: =RESUMO!O34 -> 808566.69 | O39: =RESUMO!R34 -> 2.1306105 | P39: =RESUMO!K34 -> -16959.158 | Q39: =RESUMO!P34 -> -429066.69 | R39: =1-O39 -> -1.1306105 | T39: m² | U39: 25.3 | V39: 16000 | W39: =ROUND(V39*U39,2) -> 404800
B40: B.3.2 | C40: Cerca com 4 fios de arame farpado e mourão de concreto de seção quadrada de 11 cm a cada 2,5 m e esticador de 15 cm a cada 50 m - areia e brita comerciais | E40: m | F40: 65 | G40: 300 | H40: =F40*G40 -> 19500 | I40: =RESUMO!H35 -> 0 | J40: =RESUMO!M35 -> 0 | K40: =RESUMO!I35 -> 713.52 | L40: =RESUMO!N35 -> 46378.8 | M40: =RESUMO!J35 -> 713.52 | N40: =RESUMO!O35 -> 46378.8 | O40: =RESUMO!R35 -> 2.3784 | P40: =RESUMO!K35 -> -413.52 | Q40: =RESUMO!P35 -> -26878.8 | R40: =1-O40 -> -1.3784 | T40: m² | U40: 25.3 | V40: 16000 | W40: =ROUND(V40*U40,2) -> 404800
B41: C. | C41: Implantação de Desvio 1 - Km 303+450 - Leste | H41: =SUBTOTAL(9,H42:H67) -> 807697.37 | J41: =SUBTOTAL(9,J42:J67) -> 776624.58 | L41: =SUBTOTAL(9,L42:L67) -> 26511.6 | N41: =SUBTOTAL(9,N42:N67) -> 803136.18 | Q41: =SUBTOTAL(9,Q42:Q67) -> 4561.1893 | W41: =SUBTOTAL(9,W42:W61) -> 673298.87
B42: C.1 | C42: Terraplenagem | H42: =SUBTOTAL(9,H43:H47) -> 39565.81 | J42: =SUBTOTAL(9,J43:J47) -> 24752.505 | L42: =SUBTOTAL(9,L43:L47) -> 0 | N42: =SUBTOTAL(9,N43:N47) -> 24752.505 | Q42: =SUBTOTAL(9,Q43:Q47) -> 14813.305 | W42: =SUBTOTAL(9,W43:W46) -> 34802.9
B43: C.1.1 | C43: Desmatamento, destocamento, limpeza de área e estocagem do material de limpeza com árvores de diâmetro até 0,15 m | E43: m² | F43: 0.8599999 | G43: 7740.78 | H43: =F43*G43 -> 6657.07 | I43: =RESUMO!H38 -> 7740.779 | J43: =RESUMO!M38 -> 6657.0691 | K43: =RESUMO!I38 -> 0 | L43: =RESUMO!N38 -> 0 | M43: =RESUMO!J38 -> 7740.779 | N43: =RESUMO!O38 -> 6657.0691 | O43: =RESUMO!R38 -> 0.99999987 | P43: =RESUMO!K38 -> 0.001 | Q43: =RESUMO!P38 -> 0.0008599999 | R43: =1-O43 -> 1.2918595e-07 | T43: m² | U43: 0.86 | V43: 2153.736 | W43: =ROUND(V43*U43,2) -> 1852.21
B44: C.1.2 | C44: Transporte com caminhão basculante de 14 m³ - rodovia pavimentada | E44: T x Km | F44: 1.539998 | G44: 603.78 | H44: =F44*G44 -> 929.82 | I44: =RESUMO!H39 -> 603.78076 | J44: =RESUMO!M39 -> 929.82117 | K44: =RESUMO!I39 -> 0 | L44: =RESUMO!N39 -> 0 | M44: =RESUMO!J39 -> 603.78076 | N44: =RESUMO!O39 -> 929.82117 | O44: =RESUMO!R39 -> 1.0000013 | P44: =RESUMO!K39 -> -0.000762 | Q44: =RESUMO!P39 -> -0.0011734785 | R44: =1-O44 -> -1.2620491e-06 | T44: T x Km | U44: 1.54 | V44: 1679.9141 | W44: =ROUND(V44*U44,2) -> 2587.07
B45: C.1.3 | C45: Escavação, carga e transporte de material de 1ª categoria - DMT de 1.000 a 1.200 m - com escavadeira e caminhão basculante de 14 m³ | E45: m³ | F45: 0 | G45: 0 | H45: =F45*G45 -> 0 | I45: =RESUMO!H40 -> 6679.445 | J45: =RESUMO!M40 -> 0 | K45: =RESUMO!I40 -> 0 | L45: =RESUMO!N40 -> 0 | M45: =RESUMO!J40 -> 6679.445 | N45: =RESUMO!O40 -> 0 | O45: =RESUMO!R40 -> 0 | P45: =RESUMO!K40 -> -6679.445 | Q45: =RESUMO!P40 -> 0 | R45: =1-O45 -> 1 | T45: m³ | U45: 11.03 | V45: 2211.48 | W45: =ROUND(V45*U45,2) -> 24392.62
B46: C.1.4 | C46: Regularização de bota-fora com espalhamento e execução de hidrossemeadura | E46: m³ | F46: 2.6999987 | G46: 6357.64 | H46: =F46*G46 -> 17165.62 | I46: =RESUMO!H41 -> 6357.638 | J46: =RESUMO!M41 -> 17165.615 | K46: =RESUMO!I41 -> 0 | L46: =RESUMO!N41 -> 0 | M46: =RESUMO!J41 -> 6357.638 | N46: =RESUMO!O41 -> 17165.615 | O46: =RESUMO!R41 -> 0.99999969 | P46: =RESUMO!K41 -> 0.002 | Q46: =RESUMO!P41 -> 0.0053999975 | R46: =1-O46 -> 3.1458214e-07 | T46: m³ | U46: 2.7 | V46: 2211.48 | W46: =ROUND(V46*U46,2) -> 5971
B47: C.1.5 | C47: Regularização de bota-fora | E47: m³ | F47: 2.3299998 | G47: 6357.64 | H47: =F47*G47 -> 14813.3 | I47: =RESUMO!H42 -> 0 | J47: =RESUMO!M42 -> 0 | K47: =RESUMO!I42 -> 0 | L47: =RESUMO!N42 -> 0 | M47: =RESUMO!J42 -> 0 | N47: =RESUMO!O42 -> 0 | O47: =RESUMO!R42 -> 0 | P47: =RESUMO!K42 -> 6357.64 | Q47: =RESUMO!P42 -> 14813.3 | R47: =1-O47 -> 1
B48: C.2 | C48: Pavimentação | H48: =SUBTOTAL(9,H49:H54) -> 418780.26 | J48: =SUBTOTAL(9,J49:J54) -> 431823.01 | L48: =SUBTOTAL(9,L49:L54) -> 0 | N48: =SUBTOTAL(9,N49:N54) -> 431823.01 | Q48: =SUBTOTAL(9,Q49:Q54) -> -13042.746 | W48: =SUBTOTAL(9,W49:W54) -> 392963.58
B49: C.2.1 | C49: Preparo e melhoramento do subleito | E49: m² | F49: 4.2900002 | G49: 2405.24 | H49: =F49*G49 -> 10318.48 | I49: =RESUMO!H44 -> 2405.241 | J49: =RESUMO!M44 -> 10318.484 | K49: =RESUMO!I44 -> 0 | L49: =RESUMO!N44 -> 0 | M49: =RESUMO!J44 -> 2405.241 | N49: =RESUMO!O44 -> 10318.484 | O49: =RESUMO!R44 -> 1.0000004 | P49: =RESUMO!K44 -> -0.001 | Q49: =RESUMO!P44 -> -0.0042900002 | R49: =1-O49 -> -4.1575893e-07 | T49: m² | U49: 4.29 | V49: 2153.736 | W49: =ROUND(V49*U49,2) -> 9239.53
B50: C.2.2 | C50: Rachão ou pedra de mão | E50: m³ | F50: 153.92007 | G50: 1202.62 | H50: =F50*G50 -> 185107.35 | I50: =RESUMO!H45 -> 1202.6205 | J50: =RESUMO!M45 -> 185107.43 | K50: =RESUMO!I45 -> 0 | L50: =RESUMO!N45 -> 0 | M50: =RESUMO!J45 -> 1202.6205 | N50: =RESUMO!O45 -> 185107.43 | O50: =RESUMO!R45 -> 1.0000004 | P50: =RESUMO!K45 -> -0.0005 | Q50: =RESUMO!P45 -> -0.076960033 | R50: =1-O50 -> -4.1575893e-07 | T50: m³ | U50: 153.92 | V50: 1186.51 | W50: =ROUND(V50*U50,2) -> 182627.62
B51: C.2.3 | C51: Sub-base ou base de brita graduada simples (BGS) | E51: m³ | F51: 173.54936 | G51: 481.05 | H51: =F51*G51 -> 83485.92 | I51: =RESUMO!H46 -> 481.0482 | J51: =RESUMO!M46 -> 83485.608 | K51: =RESUMO!I46 -> 0 | L51: =RESUMO!N46 -> 0 | M51: =RESUMO!J46 -> 481.0482 | N51: =RESUMO!O46 -> 83485.608 | O51: =RESUMO!R46 -> 0.99999626 | P51: =RESUMO!K46 -> 0.0018 | Q51: =RESUMO!P46 -> 0.31238885 | R51: =1-O51 -> 3.7418148e-06 | T51: m³ | U51: 173.55 | V51: 430.7472 | W51: =ROUND(V51*U51,2) -> 74756.18
B52: C.2.4 | C52: Imprimadura betuminosa impermeabilizante | E52: m² | F52: 0.8700005 | G52: 2405.24 | H52: =F52*G52 -> 2092.56 | I52: =RESUMO!H47 -> 2405.241 | J52: =RESUMO!M47 -> 2092.5609 | K52: =RESUMO!I47 -> 0 | L52: =RESUMO!N47 -> 0 | M52: =RESUMO!J47 -> 2405.241 | N52: =RESUMO!O47 -> 2092.5609 | O52: =RESUMO!R47 -> 1.0000004 | P52: =RESUMO!K47 -> -0.001 | Q52: =RESUMO!P47 -> -0.0008700005 | R52: =1-O52 -> -4.1575893e-07 | T52: m² | U52: 0.87 | V52: 2153.736 | W52: =ROUND(V52*U52,2) -> 1873.75
B53: C.2.5 | C53: Imprimadura betuminosa ligante | E53: m² | F53: 0.53000116 | G53: 4810.48 | H53: =F53*G53 -> 2549.56 | I53: =RESUMO!H48 -> 4810.482 | J53: =RESUMO!M48 -> 2549.5611 | K53: =RESUMO!I48 -> 0 | L53: =RESUMO!N48 -> 0 | M53: =RESUMO!J48 -> 4810.482 | N53: =RESUMO!O48 -> 2549.5611 | O53: =RESUMO!R48 -> 1.0000004 | P53: =RESUMO!K48 -> -0.002 | Q53: =RESUMO!P48 -> -0.0010600023 | R53: =1-O53 -> -4.1575893e-07 | T53: m² | U53: 0.53 | V53: 4307.472 | W53: =ROUND(V53*U53,2) -> 2282.96
B54: C.2.6 | C54: CBUQ Faixa C/D c/ DOP ou polímero similar | E54: T | F54: 308.7431 | G54: 437.99 | H54: =F54*G54 -> 135226.39 | I54: =RESUMO!H49 -> 480.2354 | J54: =RESUMO!M49 -> 148269.36 | K54: =RESUMO!I49 -> 0 | L54: =RESUMO!N49 -> 0 | M54: =RESUMO!J49 -> 480.2354 | N54: =RESUMO!O49 -> 148269.36 | O54: =RESUMO!R49 -> 1.0964529 | P54: =RESUMO!K49 -> -42.245397 | Q54: =RESUMO!P49 -> -13042.975 | R54: =1-O54 -> -0.096452881 | T54: T | U54: 308.74 | V54: 395.74899 | W54: =ROUND(V54*U54,2) -> 122183.54
B55: C.3 | C55: Material Betuminoso e Transportes | H55: =SUBTOTAL(9,H56:H61) -> 305037 | J55: =SUBTOTAL(9,J56:J61) -> 320049.07 | L55: =SUBTOTAL(9,L56:L61) -> 0 | N55: =SUBTOTAL(9,N56:N61) -> 320049.07 | Q55: =SUBTOTAL(9,Q56:Q61) -> -15012.07 | W55: =SUBTOTAL(9,W56:W61) -> 245532.39
B56: C.3.1 | C56: Fornecimento de emulsão asfáltica Imprimer | E56: T | F56: 3055.8567 | G56: 3.28 | H56: =F56*G56 -> 10023.21 | I56: =RESUMO!H51 -> 3.7632974 | J56: =RESUMO!M51 -> 11500.097 | K56: =RESUMO!I51 -> 0 | L56: =RESUMO!N51 -> 0 | M56: =RESUMO!J51 -> 3.7632974 | N56: =RESUMO!O51 -> 11500.097 | O56: =RESUMO!R51 -> 1.1473468 | P56: =RESUMO!K51 -> -0.48329736 | Q56: =RESUMO!P51 -> -1476.8875 | R56: =1-O56 -> -0.14734676 | T56: T | U56: 3052.92 | V56: 2.7998568 | W56: =ROUND(V56*U56,2) -> 8547.74
B57: C.3.2 | C57: Fornecimento de emulsão asfáltica tipo RR-1C | E57: T | F57: 3461.7051 | G57: 2.34 | H57: =F57*G57 -> 8100.39 | I57: =RESUMO!H52 -> 2.6298571 | J57: =RESUMO!M52 -> 9103.7896 | K57: =RESUMO!I52 -> 0 | L57: =RESUMO!N52 -> 0 | M57: =RESUMO!J52 -> 2.6298571 | N57: =RESUMO!O52 -> 9103.7896 | O57: =RESUMO!R52 -> 1.1238705 | P57: =RESUMO!K52 -> -0.28985705 | Q57: =RESUMO!P52 -> -1003.3996 | R57: =1-O57 -> -0.12387053 | T57: T | U57: 3455.03 | V57: 2.0546641 | W57: =V57*U57 -> 7098.9263
B58: C.3.3 | C58: Fornecimento de CAP modificado com adição de polímero | E58: T | F58: 6076.7261 | G58: 22.34 | H58: =F58*G58 -> 135754.06 | I58: =RESUMO!H53 -> 24.395266 | J58: =RESUMO!M53 -> 148243.35 | K58: =RESUMO!I53 -> 0 | L58: =RESUMO!N53 -> 0 | M58: =RESUMO!J53 -> 24.395266 | N58: =RESUMO!O53 -> 148243.35 | O58: =RESUMO!R53 -> 1.0919994 | P58: =RESUMO!K53 -> -2.0552662 | Q58: =RESUMO!P53 -> -12489.29 | R58: =1-O58 -> -0.091999382 | T58: T | U58: 6077.35 | V58: 19.276933 | W58: =V58*U58 -> 117152.67
B59: C.3.4 | C59: Transporte com caminhão basculante de 14 m³ - rodovia pavimentada - Agregados | E59: T x Km | F59: 1.06 | G59: 119143.16 | H59: =F59*G59 -> 126291.75 | I59: =RESUMO!H54 -> 119183.25 | J59: =RESUMO!M54 -> 126334.25 | K59: =RESUMO!I54 -> 0 | L59: =RESUMO!N54 -> 0 | M59: =RESUMO!J54 -> 119183.25 | N59: =RESUMO!O54 -> 126334.25 | O59: =RESUMO!R54 -> 1.0003365 | P59: =RESUMO!K54 -> -40.089634 | Q59: =RESUMO!P54 -> -42.495012 | R59: =1-O59 -> -0.00033648288 | T59: T x Km | U59: 1.06 | V59: 88723.52 | W59: =V59*U59 -> 94046.931
B60: C.3.5 | C60: Transporte com caminhão basculante de 14 m³ - rodovia pavimentada - Massa Asfaltica | E60: T x Km | F60: 0.78999987 | G60: 24878.08 | H60: =F60*G60 -> 19653.68 | I60: =RESUMO!H55 -> 24878.081 | J60: =RESUMO!M55 -> 19653.681 | K60: =RESUMO!I55 -> 0 | L60: =RESUMO!N55 -> 0 | M60: =RESUMO!J55 -> 24878.081 | N60: =RESUMO!O55 -> 19653.681 | O60: =RESUMO!R55 -> 1 | P60: =RESUMO!K55 -> -0.001193528 | Q60: =RESUMO!P55 -> -0.00094288696 | R60: =1-O60 -> -4.7975085e-08 | T60: T x Km | U60: 0.79 | V60: 18995.952 | W60: =V60*U60 -> 15006.802
B61: C.3.6 | C61: Transporte com caminhão basculante de 14 m³ - rodovia pavimentada - Materiais Betuminosos | E61: T x Km | F61: 0.78999953 | G61: 6599.89 | H61: =F61*G61 -> 5213.91 | I61: =RESUMO!H56 -> 6599.8867 | J61: =RESUMO!M56 -> 5213.9074 | K61: =RESUMO!I56 -> 0 | L61: =RESUMO!N56 -> 0 | M61: =RESUMO!J56 -> 6599.8867 | N61: =RESUMO!O56 -> 5213.9074 | O61: =RESUMO!R56 -> 0.9999995 | P61: =RESUMO!K56 -> 0.0033303483 | Q61: =RESUMO!P56 -> 0.0026309736 | R61: =1-O61 -> 5.0460664e-07 | T61: T x Km | U61: 0.79 | V61: 4657.3707 | W61: =U61*V61 -> 3679.3228
B62: C.4 | C62: Drenagem e OACs | H62: =SUBTOTAL(9,H63:H67) -> 44314.3 | J62: =SUBTOTAL(9,J63:J67) -> 0 | L62: =SUBTOTAL(9,L63:L67) -> 26511.6 | N62: =SUBTOTAL(9,N63:N67) -> 26511.6 | Q62: =SUBTOTAL(9,Q63:Q67) -> 17802.7 | W62: =SUBTOTAL(9,W63:W69) -> 0
B63: C.4.1 | C63: Sarjeta triangular de concreto - STC 88-20 - escavação mecânica - areia e brita comerciais | E63: m | F63: 58 | G63: 456.5 | H63: =F63*G63 -> 26477 | I63: =RESUMO!H58 -> 0 | J63: =RESUMO!M58 -> 0 | K63: =RESUMO!I58 -> 285.4 | L63: =RESUMO!N58 -> 16553.2 | M63: =RESUMO!J58 -> 285.4 | N63: =RESUMO!O58 -> 16553.2 | O63: =RESUMO!R58 -> 0.62519168 | P63: =RESUMO!K58 -> 171.1 | Q63: =RESUMO!P58 -> 9923.8 | R63: =1-O63 -> 0.37480832
B64: C.4.2 | C64: Dissipador de energia - DES 88-264 - areia, brita e pedra de mão comerciais | E64: und. | F64: 959.24 | G64: 7 | H64: =F64*G64 -> 6714.68 | I64: =RESUMO!H59 -> 0 | J64: =RESUMO!M59 -> 0 | K64: =RESUMO!I59 -> 0 | L64: =RESUMO!N59 -> 0 | M64: =RESUMO!J59 -> 0 | N64: =RESUMO!O59 -> 0 | O64: =RESUMO!R59 -> 0 | P64: =RESUMO!K59 -> 7 | Q64: =RESUMO!P59 -> 6714.68 | R64: =1-O64 -> 1
B65: C.4.3 | C65: Dreno longitudinal profundo para corte em solo - DPS 01 - tubo PEAD e areia comercial | E65: m | F65: 166.25 | G65: 15.4 | H65: =F65*G65 -> 2560.25 | I65: =RESUMO!H60 -> 0 | J65: =RESUMO!M60 -> 0 | K65: =RESUMO!I60 -> 14 | L65: =RESUMO!N60 -> 2327.5 | M65: =RESUMO!J60 -> 14 | N65: =RESUMO!O60 -> 2327.5 | O65: =RESUMO!R60 -> 0.90909091 | P65: =RESUMO!K60 -> 1.4 | Q65: =RESUMO!P60 -> 232.75 | R65: =1-O65 -> 0.090909091
B66: C.4.4 | C66: Concreto fck = 20 MPa - confecção em central dosadora de 30 m³/h - areia e brita comerciais | E66: m³ | F66: 729.31429 | G66: 2.8 | H66: =F66*G66 -> 2042.08 | I66: =RESUMO!H61 -> 0 | J66: =RESUMO!M61 -> 0 | K66: =RESUMO!I61 -> 2.8 | L66: =RESUMO!N61 -> 2042.08 | M66: =RESUMO!J61 -> 2.8 | N66: =RESUMO!O61 -> 2042.08 | O66: =RESUMO!R61 -> 1 | P66: =RESUMO!K61 -> 0 | Q66: =RESUMO!P61 -> 0 | R66: =1-O66 -> 0
B67: C.4.5 | C67: Tubo PEAD para drenagem - D = 800 mm - fornecimento e instalação | E67: m | F67: 931.47 | G67: 7 | H67: =F67*G67 -> 6520.29 | I67: =RESUMO!H62 -> 0 | J67: =RESUMO!M62 -> 0 | K67: =RESUMO!I62 -> 6 | L67: =RESUMO!N62 -> 5588.82 | M67: =RESUMO!J62 -> 6 | N67: =RESUMO!O62 -> 5588.82 | O67: =RESUMO!R62 -> 0.85714286 | P67: =RESUMO!K62 -> 1 | Q67: =RESUMO!P62 -> 931.47 | R67: =1-O67 -> 0.14285714
B68: D. | C68: Implantação de Desvios 2 e 3 | H68: =SUBTOTAL(9,H69:H92) -> 429102.81 | J68: =SUBTOTAL(9,J69:J92) -> 400870.74 | L68: =SUBTOTAL(9,L69:L92) -> -9738.9274 | N68: =SUBTOTAL(9,N69:N92) -> 391131.81 | Q68: =SUBTOTAL(9,Q69:Q92) -> 37971.001 | W68: =SUBTOTAL(9,W69:W89) -> 799354.84
B69: D.1 | C69: Terraplenagem | H69: =SUBTOTAL(9,H70:H74) -> 30111.77 | J69: =SUBTOTAL(9,J70:J74) -> 24827.802 | L69: =SUBTOTAL(9,L70:L74) -> -18079.327 | N69: =SUBTOTAL(9,N70:N74) -> 6748.4749 | Q69: =SUBTOTAL(9,Q70:Q74) -> 23363.295 | W69: =SUBTOTAL(9,W70:W73) -> 23802.3
B70: D.1.1 | C70: Desmatamento, destocamento, limpeza de área e estocagem do material de limpeza com árvores de diâmetro até 0,15 m | E70: m² | F70: 0.85999792 | G70: 2400.25 | H70: =F70*G70 -> 2064.21 | I70: =RESUMO!H65 -> 1887.389 | J70: =RESUMO!M65 -> 1623.1506 | K70: =RESUMO!I65 -> 0 | L70: =RESUMO!N65 -> 0 | M70: =RESUMO!J65 -> 1887.389 | N70: =RESUMO!O65 -> 1623.1506 | O70: =RESUMO!R65 -> 0.78633017 | P70: =RESUMO!K65 -> 512.861 | Q70: =RESUMO!P65 -> 441.05939 | R70: =1-O70 -> 0.21366983 | T70: m² | U70: 0.86 | V70: 2000 | W70: =ROUND(V70*U70,2) -> 1720
B71: D.1.2 | C71: Transporte com caminhão basculante de 14 m³ - rodovia pavimentada | E71: T x Km | F71: 1.5399903 | G71: 184.67 | H71: =F71*G71 -> 284.39 | I71: =RESUMO!H66 -> 184.02043 | J71: =RESUMO!M66 -> 283.38966 | K71: =RESUMO!I66 -> 0 | L71: =RESUMO!N66 -> 0 | M71: =RESUMO!J66 -> 184.02043 | N71: =RESUMO!O66 -> 283.38966 | O71: =RESUMO!R66 -> 0.99648252 | P71: =RESUMO!K66 -> 0.6495725 | Q71: =RESUMO!P66 -> 1.0003353 | R71: =1-O71 -> 0.0035174771 | T71: T x Km | U71: 1.54 | V71: 520 | W71: =ROUND(V71*U71,2) -> 800.8
B72: D.1.3 | C72: Escavação, carga e transporte de material de 1ª categoria - DMT de 1.000 a 1.200 m - com escavadeira e caminhão basculante de 14 m³ | E72: m³ | F72: 11.030008 | G72: 2078.08 | H72: =F72*G72 -> 22921.24 | I72: =RESUMO!H67 -> 2078.082 | J72: =RESUMO!M67 -> 22921.262 | K72: =RESUMO!I67 -> -2078.082 | L72: =RESUMO!N67 -> -22921.262 | M72: =RESUMO!J67 -> 0 | N72: =RESUMO!O67 -> 0 | O72: =RESUMO!R67 -> 0 | P72: =RESUMO!K67 -> 2078.08 | Q72: =RESUMO!P67 -> 22921.24 | R72: =1-O72 -> 1 | T72: m³ | U72: 11.03 | V72: 1550 | W72: =ROUND(V72*U72,2) -> 17096.5
B73: D.1.4 | C73: Regularização de bota-fora com espalhamento e execução de hidrossemeadura | E73: m³ | F73: 0 | G73: 0 | H73: =F73*G73 -> 0 | I73: =RESUMO!H68 -> 0 | J73: =RESUMO!M68 -> 0 | K73: =RESUMO!I68 -> 0 | L73: =RESUMO!N68 -> 0 | M73: =RESUMO!J68 -> 0 | N73: =RESUMO!O68 -> 0 | O73: =RESUMO!R68 -> 0 | P73: =RESUMO!K68 -> 0 | Q73: =RESUMO!P68 -> 0 | R73: =1-O73 -> 1 | T73: m³ | U73: 2.7 | V73: 1550 | W73: =ROUND(V73*U73,2) -> 4185
B74: D.1.5 | C74: Regularização de bota-fora | E74: m³ | F74: 2.3300017 | G74: 2078.08 | H74: =F74*G74 -> 4841.93 | I74: =RESUMO!H69 -> 0 | J74: =RESUMO!M69 -> 0 | K74: =RESUMO!I69 -> 2078.082 | L74: =RESUMO!N69 -> 4841.9347 | M74: =RESUMO!J69 -> 2078.082 | N74: =RESUMO!O69 -> 4841.9347 | O74: =RESUMO!R69 -> 1.000001 | P74: =RESUMO!K69 -> -0.002 | Q74: =RESUMO!P69 -> -0.0046600035 | R74: =1-O74 -> -9.6242686e-07 | T74: m³ | U74: 2.7 | V74: 1550 | W74: =ROUND(V74*U74,2) -> 4185
B75: D.2 | C75: Pavimento | H75: =SUBTOTAL(9,H76:H82) -> 215423.15 | J75: =SUBTOTAL(9,J76:J82) -> 215422.95 | L75: =SUBTOTAL(9,L76:L82) -> 0 | N75: =SUBTOTAL(9,N76:N82) -> 215422.95 | Q75: =SUBTOTAL(9,Q76:Q82) -> 0.20445337 | W75: =SUBTOTAL(9,W76:W82) -> 419437.6
B76: D.2.1 | C76: Fresagem contínua de revestimento betuminoso | E76: m³ | F76: 225.86635 | G76: 38.46 | H76: =F76*G76 -> 8686.82 | I76: =RESUMO!H71 -> 38.4645 | J76: =RESUMO!M71 -> 8687.8364 | K76: =RESUMO!I71 -> 0 | L76: =RESUMO!N71 -> 0 | M76: =RESUMO!J71 -> 38.4645 | N76: =RESUMO!O71 -> 8687.8364 | O76: =RESUMO!R71 -> 1.000117 | P76: =RESUMO!K71 -> -0.0045 | Q76: =RESUMO!P71 -> -1.0163986 | R76: =1-O76 -> -0.00011700468 | T76: m³ | U76: 225.84 | V76: 75 | W76: =ROUND(V76*U76,2) -> 16938
B77: D.2.2 | C77: Preparo e melhoramento do subleito | E77: m² | F77: 4.2900015 | G77: 1018.65 | H77: =F77*G77 -> 4370.01 | I77: =RESUMO!H72 -> 1018.651 | J77: =RESUMO!M72 -> 4370.0143 | K77: =RESUMO!I72 -> 0 | L77: =RESUMO!N72 -> 0 | M77: =RESUMO!J72 -> 1018.651 | N77: =RESUMO!O72 -> 4370.0143 | O77: =RESUMO!R72 -> 1.000001 | P77: =RESUMO!K72 -> -0.001 | Q77: =RESUMO!P72 -> -0.0042900015 | R77: =1-O77 -> -9.8169145e-07 | T77: m² | U77: 4.29 | V77: 2000 | W77: =ROUND(V77*U77,2) -> 8580
B78: D.2.3 | C78: Rachão ou pedra de mão | E78: m³ | F78: 153.91864 | G78: 509.33 | H78: =F78*G78 -> 78395.38 | I78: =RESUMO!H73 -> 509.3255 | J78: =RESUMO!M73 -> 78394.687 | K78: =RESUMO!I73 -> 0 | L78: =RESUMO!N73 -> 0 | M78: =RESUMO!J73 -> 509.3255 | N78: =RESUMO!O73 -> 78394.687 | O78: =RESUMO!R73 -> 0.99999116 | P78: =RESUMO!K73 -> 0.0045 | Q78: =RESUMO!P73 -> 0.69263387 | R78: =1-O78 -> 8.8351364e-06 | T78: m³ | U78: 153.92 | V78: 1000 | W78: =ROUND(V78*U78,2) -> 153920
B79: D.2.4 | C79: Sub-base ou base de brita graduada simples (BGS) | E79: m³ | F79: 173.55019 | G79: 203.73 | H79: =F79*G79 -> 35357.38 | I79: =RESUMO!H74 -> 203.7302 | J79: =RESUMO!M74 -> 35357.415 | K79: =RESUMO!I74 -> 0 | L79: =RESUMO!N74 -> 0 | M79: =RESUMO!J74 -> 203.7302 | N79: =RESUMO!O74 -> 35357.415 | O79: =RESUMO!R74 -> 1.000001 | P79: =RESUMO!K74 -> -0.0002 | Q79: =RESUMO!P74 -> -0.034710038 | R79: =1-O79 -> -9.8169145e-07 | T79: m³ | U79: 173.55 | V79: 400 | W79: =ROUND(V79*U79,2) -> 69420
B80: D.2.5 | C80: Imprimadura betuminosa impermeabilizante | E80: m² | F80: 0.87000442 | G80: 1018.65 | H80: =F80*G80 -> 886.23 | I80: =RESUMO!H75 -> 1018.651 | J80: =RESUMO!M75 -> 886.23087 | K80: =RESUMO!I75 -> 0 | L80: =RESUMO!N75 -> 0 | M80: =RESUMO!J75 -> 1018.651 | N80: =RESUMO!O75 -> 886.23087 | O80: =RESUMO!R75 -> 1.000001 | P80: =RESUMO!K75 -> -0.001 | Q80: =RESUMO!P75 -> -0.00087000442 | R80: =1-O80 -> -9.8169145e-07 | T80: m² | U80: 0.87 | V80: 2000 | W80: =ROUND(V80*U80,2) -> 1740
B81: D.2.6 | C81: Imprimadura betuminosa ligante | E81: m² | F81: 0.5299998 | G81: 3063.02 | H81: =F81*G81 -> 1623.4 | I81: =RESUMO!H76 -> 3063.024 | J81: =RESUMO!M76 -> 1623.4021 | K81: =RESUMO!I76 -> 0 | L81: =RESUMO!N76 -> 0 | M81: =RESUMO!J76 -> 3063.024 | N81: =RESUMO!O76 -> 1623.4021 | O81: =RESUMO!R76 -> 1.0000013 | P81: =RESUMO!K76 -> -0.004 | Q81: =RESUMO!P76 -> -0.0021199992 | R81: =1-O81 -> -1.3059007e-06 | T81: m² | U81: 0.53 | V81: 4000 | W81: =ROUND(V81*U81,2) -> 2120
B82: D.2.7 | C82: CBUQ Faixa C/D c/ DOP ou polímero similar | E82: T | F82: 308.73796 | G82: 278.89 | H82: =F82*G82 -> 86103.93 | I82: =RESUMO!H77 -> 278.88815 | J82: =RESUMO!M77 -> 86103.36 | K82: =RESUMO!I77 -> 0 | L82: =RESUMO!N77 -> 0 | M82: =RESUMO!J77 -> 278.88815 | N82: =RESUMO!O77 -> 86103.36 | O82: =RESUMO!R77 -> 0.99999338 | P82: =RESUMO!K77 -> 0.0018469 | Q82: =RESUMO!P77 -> 0.57020814 | R82: =1-O82 -> 6.6223242e-06 | T82: T | U82: 308.74 | V82: 540 | W82: =ROUND(V82*U82,2) -> 166719.6
B83: D.3 | C83: Material Betuminoso e Transportes | H83: =SUBTOTAL(9,H84:H89) -> 160588.69 | J83: =SUBTOTAL(9,J84:J89) -> 160619.99 | L83: =SUBTOTAL(9,L84:L89) -> 0 | N83: =SUBTOTAL(9,N84:N89) -> 160619.99 | Q83: =SUBTOTAL(9,Q84:Q89) -> -31.298022 | W83: =SUBTOTAL(9,W84:W89) -> 351929.94
B84: D.3.1 | C84: Fornecimento de CAP modificado com adição de polímero | E84: T | F84: 6078.7588 | G84: 14.22 | H84: =F84*G84 -> 86439.95 | I84: =RESUMO!H79 -> 14.223296 | J84: =RESUMO!M79 -> 86459.984 | K84: =RESUMO!I79 -> 0 | L84: =RESUMO!N79 -> 0 | M84: =RESUMO!J79 -> 14.223296 | N84: =RESUMO!O79 -> 86459.984 | O84: =RESUMO!R79 -> 1.0002318 | P84: =RESUMO!K79 -> -0.0032958081 | Q84: =RESUMO!P79 -> -20.034422 | R84: =1-O84 -> -0.00023177272 | T84: T | U84: 6077.35 | V84: 26.46 | W84: =ROUND(V84*U84,2) -> 160806.68
B85: D.3.2 | C85: Fornecimento de emulsão asfáltica tipo RR-1C | E85: T | F85: 3461.6376 | G85: 1.49 | H85: =F85*G85 -> 5157.84 | I85: =RESUMO!H80 -> 1.492849 | J85: =RESUMO!M80 -> 5167.7022 | K85: =RESUMO!I80 -> 0 | L85: =RESUMO!N80 -> 0 | M85: =RESUMO!J80 -> 1.492849 | N85: =RESUMO!O80 -> 5167.7022 | O85: =RESUMO!R80 -> 1.0019121 | P85: =RESUMO!K80 -> -0.0028490102 | Q85: =RESUMO!P80 -> -9.8622408 | R85: =1-O85 -> -0.0019120874 | T85: T | U85: 3455.03 | V85: 1.8 | W85: =V85*U85 -> 6219.054
B86: D.3.3 | C86: Fornecimento de emulsão asfáltica Imprimer | E86: T | F86: 3053.9281 | G86: 1.39 | H86: =F86*G86 -> 4244.96 | I86: =RESUMO!H81 -> 1.3904586 | J86: =RESUMO!M81 -> 4246.3606 | K86: =RESUMO!I81 -> 0 | L86: =RESUMO!N81 -> 0 | M86: =RESUMO!J81 -> 1.3904586 | N86: =RESUMO!O81 -> 4246.3606 | O86: =RESUMO!R81 -> 1.0003299 | P86: =RESUMO!K81 -> -0.000458615 | Q86: =RESUMO!P81 -> -1.4005772 | R86: =1-O86 -> -0.00032993885 | T86: T | U86: 3052.92 | V86: 2.6 | W86: =V86*U86 -> 7937.592
B87: D.3.4 | C87: Transporte com caminhão basculante de 14 m³ - rodovia pavimentada - Agregados | E87: T x Km | F87: 1.0600001 | G87: 45369.07 | H87: =F87*G87 -> 48091.22 | I87: =RESUMO!H82 -> 45369.073 | J87: =RESUMO!M82 -> 48091.223 | K87: =RESUMO!I82 -> 0 | L87: =RESUMO!N82 -> 0 | M87: =RESUMO!J82 -> 45369.073 | N87: =RESUMO!O82 -> 48091.223 | O87: =RESUMO!R82 -> 1.0000001 | P87: =RESUMO!K82 -> -0.0031563751 | Q87: =RESUMO!P82 -> -0.0033457581 | R87: =1-O87 -> -6.9571079e-08 | T87: T x Km | U87: 1.06 | V87: 133718.06 | W87: =V87*U87 -> 141741.14
B88: D.3.5 | C88: Transporte com caminhão basculante de 14 m³ - rodovia pavimentada - Massa Asfaltica | E88: T x Km | F88: 0.78999998 | G88: 17044.76 | H88: =F88*G88 -> 13465.36 | I88: =RESUMO!H83 -> 17044.758 | J88: =RESUMO!M83 -> 13465.359 | K88: =RESUMO!I83 -> 0 | L88: =RESUMO!N83 -> 0 | M88: =RESUMO!J83 -> 17044.758 | N88: =RESUMO!O83 -> 13465.359 | O88: =RESUMO!R83 -> 0.9999999 | P88: =RESUMO!K83 -> 0.00165668 | Q88: =RESUMO!P83 -> 0.0013087772 | R88: =1-O88 -> 9.7195854e-08 | T88: T x Km | U88: 0.79 | V88: 37800 | W88: =V88*U88 -> 29862
B89: D.3.6 | C89: Transporte com caminhão basculante de 14 m³ - rodovia pavimentada - Materiais Betuminosos | E89: T x Km | F89: 0.79000089 | G89: 4037.16 | H89: =F89*G89 -> 3189.36 | I89: =RESUMO!H84 -> 4037.1584 | J89: =RESUMO!M84 -> 3189.3587 | K89: =RESUMO!I84 -> 0 | L89: =RESUMO!N84 -> 0 | M89: =RESUMO!J84 -> 4037.1584 | N89: =RESUMO!O84 -> 3189.3587 | O89: =RESUMO!R84 -> 0.99999961 | P89: =RESUMO!K84 -> 0.0015897435 | Q89: =RESUMO!P84 -> 0.0012558988 | R89: =1-O89 -> 3.9377768e-07 | T89: T x Km | U89: 0.79 | V89: 6789.2 | W89: =U89*V89 -> 5363.468
B90: D.4 | C90: Drenagem e OACs | H90: =SUBTOTAL(9,H91:H92) -> 22979.2 | J90: =SUBTOTAL(9,J91:J92) -> 0 | L90: =SUBTOTAL(9,L91:L92) -> 8340.4 | N90: =SUBTOTAL(9,N91:N92) -> 8340.4 | Q90: =SUBTOTAL(9,Q91:Q92) -> 14638.8 | W90: =SUBTOTAL(9,W91:W107) -> 1146379.5
B91: D.4.1 | C91: Sarjeta triangular de concreto - STC 88-20 - escavação mecânica - areia e brita comerciais | E91: m | F91: 58 | G91: 313.5 | H91: =F91*G91 -> 18183 | I91: =RESUMO!H86 -> 0 | J91: =RESUMO!M86 -> 0 | K91: =RESUMO!I86 -> 143.8 | L91: =RESUMO!N86 -> 8340.4 | M91: =RESUMO!J86 -> 143.8 | N91: =RESUMO!O86 -> 8340.4 | O91: =RESUMO!R86 -> 0.45869219 | P91: =RESUMO!K86 -> 169.7 | Q91: =RESUMO!P86 -> 9842.6 | R91: =1-O91 -> 0.54130781 | T91: T | U91: 6077.35 | V91: 26.46 | W91: =ROUND(V91*U91,2) -> 160806.68
B92: D.4.2 | C92: Dissipador de energia - DES 88-264 - areia, brita e pedra de mão comerciais | E92: und. | F92: 959.24 | G92: 5 | H92: =F92*G92 -> 4796.2 | I92: =RESUMO!H87 -> 0 | J92: =RESUMO!M87 -> 0 | K92: =RESUMO!I87 -> 0 | L92: =RESUMO!N87 -> 0 | M92: =RESUMO!J87 -> 0 | N92: =RESUMO!O87 -> 0 | O92: =RESUMO!R87 -> 0 | P92: =RESUMO!K87 -> 5 | Q92: =RESUMO!P87 -> 4796.2 | R92: =1-O92 -> 1 | T92: T | U92: 3455.03 | V92: 1.8 | W92: =V92*U92 -> 6219.054
B93: E. | C93: Sinalização Horizontal, Vertical e Elementos de Proteção e Segurança | H93: =SUBTOTAL(9,H94:H94) -> 138991.07 | J93: =SUBTOTAL(9,J94:J94) -> 19282.616 | L93: =SUBTOTAL(9,L94:L94) -> 0 | N93: =SUBTOTAL(9,N94:N94) -> 19282.616 | Q93: =SUBTOTAL(9,Q94:Q94) -> 119708.45 | W93: =SUBTOTAL(9,W94:W94) -> 457824
B94: E.1 | C94: Manutenção/recomposição de sinalização - pintura de faixa com tinta acrílica emulsionada em água - espessura de 0,3 / 0,5 mm | E94: m² | F94: 47.689999 | G94: 2914.47 | H94: =F94*G94 -> 138991.07 | I94: =RESUMO!H89 -> 404.3325 | J94: =RESUMO!M89 -> 19282.616 | K94: =RESUMO!I89 -> 0 | L94: =RESUMO!N89 -> 0 | M94: =RESUMO!J89 -> 404.3325 | N94: =RESUMO!O89 -> 19282.616 | O94: =RESUMO!R89 -> 0.13873277 | P94: =RESUMO!K89 -> 2510.1375 | Q94: =RESUMO!P89 -> 119708.45 | R94: =1-O94 -> 0.86126723 | T94: m² | U94: 47.69 | V94: 9600 | W94: =V94*U94 -> 457824
B95: F. | C95: Mão de Obra e Equipamentos | H95: =SUBTOTAL(9,H96:H105) -> 229092.44 | J95: =SUBTOTAL(9,J96:J105) -> 0 | L95: =SUBTOTAL(9,L96:L105) -> 102841.21 | N95: =SUBTOTAL(9,N96:N105) -> 102841.21 | Q95: =SUBTOTAL(9,Q96:Q105) -> 126251.23 | W95: =SUBTOTAL(9,W106:W106) -> 0
B96: F.1 | C96: Mão de Obra | H96: =SUBTOTAL(9,H97:H99) -> 19454.22 | J96: =SUBTOTAL(9,J97:J99) -> 0 | L96: =SUBTOTAL(9,L97:L99) -> 12969.48 | N96: =SUBTOTAL(9,N97:N99) -> 12969.48 | Q96: =SUBTOTAL(9,Q97:Q99) -> 6484.74 | W96: =SUBTOTAL(9,W106:W113) -> 0
B97: F.1.1 | C97: Encarregado | E97: h | F97: 70.817037 | G97: 54 | H97: =F97*G97 -> 3824.12 | I97: =RESUMO!H92 -> 0 | J97: =RESUMO!M92 -> 0 | K97: =RESUMO!I92 -> 36 | L97: =RESUMO!N92 -> 2549.4133 | M97: =RESUMO!J92 -> 36 | N97: =RESUMO!O92 -> 2549.4133 | O97: =RESUMO!R92 -> 0.66666667 | P97: =RESUMO!K92 -> 18 | Q97: =RESUMO!P92 -> 1274.7067 | R97: =1-O97 -> 0.33333333 | T97: T | U97: 6077.35 | V97: 26.46 | W97: =ROUND(V97*U97,2) -> 160806.68
B98: F.1.2 | C98: Oficial | E98: h | F98: 40.88321 | G98: 162 | H98: =F98*G98 -> 6623.08 | I98: =RESUMO!H93 -> 0 | J98: =RESUMO!M93 -> 0 | K98: =RESUMO!I93 -> 108 | L98: =RESUMO!N93 -> 4415.3867 | M98: =RESUMO!J93 -> 108 | N98: =RESUMO!O93 -> 4415.3867 | O98: =RESUMO!R93 -> 0.66666667 | P98: =RESUMO!K93 -> 54 | Q98: =RESUMO!P93 -> 2207.6933 | R98: =1-O98 -> 0.33333333 | T98: T | U98: 3455.03 | V98: 1.8 | W98: =V98*U98 -> 6219.054
B99: F.1.3 | C99: Servente | E99: h | F99: 33.359333 | G99: 270 | H99: =F99*G99 -> 9007.02 | I99: =RESUMO!H94 -> 0 | J99: =RESUMO!M94 -> 0 | K99: =RESUMO!I94 -> 180 | L99: =RESUMO!N94 -> 6004.68 | M99: =RESUMO!J94 -> 180 | N99: =RESUMO!O94 -> 6004.68 | O99: =RESUMO!R94 -> 0.66666667 | P99: =RESUMO!K94 -> 90 | Q99: =RESUMO!P94 -> 3002.34 | R99: =1-O99 -> 0.33333333 | T99: T | U99: 3052.92 | V99: 2.6 | W99: =V99*U99 -> 7937.592
B100: F.2 | C100: Equipamentos | H100: =SUBTOTAL(9,H101:H105) -> 209638.22 | J100: =SUBTOTAL(9,J101:J105) -> 0 | L100: =SUBTOTAL(9,L101:L105) -> 89871.725 | N100: =SUBTOTAL(9,N101:N105) -> 89871.725 | Q100: =SUBTOTAL(9,Q101:Q105) -> 119766.49 | W100: =SUBTOTAL(9,W106:W117) -> 0
B101: F.2.1 | C101: Trator sobre Esteiras com Lâmina - 127 Kw | E101: h | F101: 272.35346 | G101: 81 | H101: =F101*G101 -> 22060.63 | I101: =RESUMO!H96 -> 0 | J101: =RESUMO!M96 -> 0 | K101: =RESUMO!I96 -> 21.705353 | L101: =RESUMO!N96 -> 5911.528 | M101: =RESUMO!J96 -> 21.705353 | N101: =RESUMO!O96 -> 5911.528 | O101: =RESUMO!R96 -> 0.26796733 | P101: =RESUMO!K96 -> 59.294647 | Q101: =RESUMO!P96 -> 16149.102 | R101: =1-O101 -> 0.73203267 | T101: T | U101: 6077.35 | V101: 26.46 | W101: =ROUND(V101*U101,2) -> 160806.68
...

Sheet RESUMO
B1: STATUS | C1: ="CONTRATO: "&CAPA!B4 -> CONTRATO: 381/188/2025 | G1: =CAPA!B5 -> RECOMPOSIÇÃO DE TALUDES - SINISTRO 297+500 - OESTE | N1: R$ MEDIÇÃO ATUAL (PI) | P1: R$ REAJUSTE (BDI - 18,20%) | R1: R$ MEDIÇÃO (PI+BDI)
N2: =SUBTOTAL(9,N8:N100) -> 1990219.7 | P2: =N2*(18.2/100) -> 362219.98 | R2: =SUM(L2:Q2) -> 2352439.6
B4: LINK | C4: =UPPER(IF(PQ!B10="","",PQ!B10)) -> ITEM | D4: =UPPER(IF(PQ!C10="","",PQ!C10)) -> DESCRIÇÃO | E4: =UPPER(IF(PQ!E11="","",PQ!E11)) -> UNID. | F4: =UPPER(IF(PQ!F11="","",PQ!F11)) -> P. UNITÁRIO (R$ / UNID.) | G4: QUANTIDADES | M4: FINANCEIRO | R4: AVANÇO % | S4: DESVIO
G5: PROJETO | H5: ACUMULADO ANTERIOR | I5: MEDIÇÃO ATUAL | J5: ACUMULADO | K5: SALDO | L5: NÃO MEDIDO | M5: ACUMULADO ANTERIOR | N5: MEDIÇÃO ATUAL | O5: ACUMULADO | P5: SALDO | Q5: NÃO MEDIDO
M7: =SUM(M8,M12,M36,M63,M88,M90) -> 3745492.2 | N7: =SUM(N8,N12,N36,N63,N88,N90) -> 1990219.7 | O7: =SUM(O8,O12,O36,O63,O88,O90) -> 5735711.9 | P7: =SUM(P8,P12,P36,P63,P88,P90) -> 94956.86 | Q7: =SUM(Q8,Q12,Q36,Q63,Q88,Q90) -> 217212.11
C8: =IF(PQ!B13="","",PQ!B13) -> A. | D8: =IF(PQ!C13="","",PQ!C13) -> Custos Indiretos | E8: =IF(PQ!E13="","",PQ!E13) | F8: =IF(PQ!F13="","",PQ!F13) | G8: =IF(PQ!G13="","",PQ!G13) | M8: =SUBTOTAL(9,M9:M11) -> 550507.66 | N8: =SUBTOTAL(9,N9:N11) -> 0 | O8: =SUBTOTAL(9,O9:O11) -> 550507.66 | P8: =SUBTOTAL(9,P9:P11) -> 0 | Q8: =SUBTOTAL(9,Q9:Q11) -> 0
B9: =HYPERLINK("#"&"'"&C9&"'"&"!A1","LINK") -> LINK | C9: =IF(PQ!B14="","",PQ!B14) -> A.1 | D9: =IF(PQ!C14="","",PQ!C14) -> Mobilização e desmobilização | E9: =IF(PQ!E14="","",PQ!E14) -> vb. | F9: =IF(PQ!F14="","",PQ!F14) -> 22570.81 | G9: =IF(PQ!G14="","",PQ!G14) -> 1 | H9: {=INDIRECT($C9&"!E6")} -> 1 | I9: {=INDIRECT($C9&"!E9")} -> 0 | J9: {=INDIRECT($C9&"!E5")} -> 1 | K9: {=INDIRECT($C9&"!E7")} -> 0 | L9: {=INDIRECT($C9&"!E8")} -> 0 | M9: {=INDIRECT($C9&"!G6")} -> 22570.81 | N9: {=INDIRECT($C9&"!G9")} -> 0 | O9: {=INDIRECT($C9&"!G5")} -> 22570.81 | P9: {=INDIRECT($C9&"!G7")} -> 0 | Q9: {=INDIRECT($C9&"!G8")} -> 0 | R9: =IF(ISERROR(J9/G9),0,J9/G9) -> 1 | S9: =IF(R9>1,R9-1,0) -> 0
B10: =HYPERLINK("#"&"'"&C10&"'"&"!A1","LINK") -> LINK | C10: =IF(PQ!B15="","",PQ!B15) -> A.2 | D10: =IF(PQ!C15="","",PQ!C15) -> Sinalização e desvio de tráfego | E10: =IF(PQ!E15="","",PQ!E15) -> vb. | F10: =IF(PQ!F15="","",PQ!F15) -> 45141.63 | G10: =IF(PQ!G15="","",PQ!G15) -> 1 | H10: {=INDIRECT($C10&"!E6")} -> 1 | I10: {=INDIRECT($C10&"!E9")} -> 0 | J10: {=INDIRECT($C10&"!E5")} -> 1 | K10: {=INDIRECT($C10&"!E7")} -> 0 | L10: {=INDIRECT($C10&"!E8")} -> 0 | M10: {=INDIRECT($C10&"!G6")} -> 45141.63 | N10: {=INDIRECT($C10&"!G9")} -> 0 | O10: {=INDIRECT($C10&"!G5")} -> 45141.63 | P10: {=INDIRECT($C10&"!G7")} -> 0 | Q10: {=INDIRECT($C10&"!G8")} -> 0 | R10: =IF(ISERROR(J10/G10),0,J10/G10) -> 1 | S10: =IF(R10>1,R10-1,0) -> 0
B11: =HYPERLINK("#"&"'"&C11&"'"&"!A1","LINK") -> LINK | C11: =IF(PQ!B16="","",PQ!B16) -> A.3 | D11: =IF(PQ!C16="","",PQ!C16) -> Administração local | E11: =IF(PQ!E16="","",PQ!E16) -> vb. | F11: =IF(PQ!F16="","",PQ!F16) -> 482795.22 | G11: =IF(PQ!G16="","",PQ!G16) -> 1 | H11: {=INDIRECT($C11&"!E6")} -> 1 | I11: {=INDIRECT($C11&"!E9")} -> 0 | J11: {=INDIRECT($C11&"!E5")} -> 1 | K11: {=INDIRECT($C11&"!E7")} -> 0 | L11: {=INDIRECT($C11&"!E8")} -> 0 | M11: {=INDIRECT($C11&"!G6")} -> 482795.22 | N11: {=INDIRECT($C11&"!G9")} -> 0 | O11: {=INDIRECT($C11&"!G5")} -> 482795.22 | P11: {=INDIRECT($C11&"!G7")} -> 0 | Q11: {=INDIRECT($C11&"!G8")} -> 0 | R11: =IF(ISERROR(J11/G11),0,J11/G11) -> 1 | S11: =IF(R11>1,R11-1,0) -> 0
C12: =IF(PQ!B17="","",PQ!B17) -> B. | D12: =IF(PQ!C17="","",PQ!C17) -> Estabilização de Talude | E12: =IF(PQ!E17="","",PQ!E17) | F12: =IF(PQ!F17="","",PQ!F17) | G12: =IF(PQ!G17="","",PQ!G17) | M12: =SUBTOTAL(9,M13:M35) -> 1998206.6 | N12: =SUBTOTAL(9,N13:N35) -> 1870605.8 | O12: =SUBTOTAL(9,O13:O35) -> 3868812.4 | P12: =SUBTOTAL(9,P13:P35) -> -193535.02 | Q12: =SUBTOTAL(9,Q13:Q35) -> 171481.92
C13: =IF(PQ!B18="","",PQ!B18) -> B.1 | D13: =IF(PQ!C18="","",PQ!C18) -> Terraplenagem | E13: =IF(PQ!E18="","",PQ!E18) | F13: =IF(PQ!F18="","",PQ!F18) | G13: =IF(PQ!G18="","",PQ!G18) | M13: =SUBTOTAL(9,M14:M22) -> 1764483.7 | N13: =SUBTOTAL(9,N14:N22) -> 877293.31 | O13: =SUBTOTAL(9,O14:O22) -> 2641777 | P13: =SUBTOTAL(9,P14:P22) -> 84576.263 | Q13: =SUBTOTAL(9,Q14:Q22) -> 0
B14: =HYPERLINK("#"&"'"&C14&"'"&"!A1","LINK") -> LINK | C14: =IF(PQ!B19="","",PQ!B19) -> B.1.1 | D14: =IF(PQ!C19="","",PQ!C19) -> Escavação, carga e transporte de material de 1ª categoria - DMT de 800 a 1.000 m - caminho de serviço pavimentado - com escavadeira e caminhão basculante de 14 m³ | E14: =IF(PQ!E19="","",PQ!E19) -> m³ | F14: =IF(PQ!F19="","",PQ!F19) -> 0 | G14: =IF(PQ!G19="","",PQ!G19) -> 0 | H14: {=INDIRECT($C14&"!E6")} -> 0 | I14: {=INDIRECT($C14&"!E9")} -> 0 | J14: {=INDIRECT($C14&"!E5")} -> 0 | K14: {=INDIRECT($C14&"!E7")} -> 0 | L14: {=INDIRECT($C14&"!E8")} -> 0 | M14: {=INDIRECT($C14&"!G6")} -> 0 | N14: {=INDIRECT($C14&"!G9")} -> 0 | O14: {=INDIRECT($C14&"!G5")} -> 0 | P14: {=INDIRECT($C14&"!G7")} -> 0 | Q14: {=INDIRECT($C14&"!G8")} -> 0 | R14: =IF(ISERROR(J14/G14),0,J14/G14) -> 0 | S14: =IF(R14>1,R14-1,0) -> 0
B15: =HYPERLINK("#"&"'"&C15&"'"&"!A1","LINK") -> LINK | C15: =IF(PQ!B20="","",PQ!B20) -> B.1.2 | D15: =IF(PQ!C20="","",PQ!C20) -> Escavação e carga de material de 1ª categoria - DMT acima de 3.000 m | E15: =IF(PQ!E20="","",PQ!E20) -> m³ | F15: =IF(PQ!F20="","",PQ!F20) -> 15.86326 | G15: =IF(PQ!G20="","",PQ!G20) -> 72616.71 | H15: {=INDIRECT($C15&"!E6")} -> 62616.71 | I15: {=INDIRECT($C15&"!E9")} -> 6145.816 | J15: {=INDIRECT($C15&"!E5")} -> 68762.526 | K15: {=INDIRECT($C15&"!E7")} -> 3854.184 | L15: {=INDIRECT($C15&"!E8")} -> 0 | M15: {=INDIRECT($C15&"!G6")} -> 993305.14 | N15: {=INDIRECT($C15&"!G9")} -> 97492.676 | O15: {=INDIRECT($C15&"!G5")} -> 1090797.8 | P15: {=INDIRECT($C15&"!G7")} -> 61139.922 | Q15: {=INDIRECT($C15&"!G8")} -> 0 | R15: =IF(ISERROR(J15/G15),0,J15/G15) -> 0.94692428 | S15: =IF(R15>1,R15-1,0) -> 0
B16: =HYPERLINK("#"&"'"&C16&"'"&"!A1","LINK") -> LINK | C16: =IF(PQ!B21="","",PQ!B21) -> B.1.3 | D16: =IF(PQ!C21="","",PQ!C21) -> Transporte com caminhão basculante de 10 m³ - rodovia pavimentada (DMT 5 Km) | E16: =IF(PQ!E21="","",PQ!E21) -> T x Km | F16: =IF(PQ!F21="","",PQ!F21) -> 1.0278799 | G16: =IF(PQ!G21="","",PQ!G21) -> 543194.94 | H16: {=INDIRECT($C16&"!E6")} -> 483457.86 | I16: {=INDIRECT($C16&"!E9")} -> 47451.28 | J16: {=INDIRECT($C16&"!E5")} -> 530909.14 | K16: {=INDIRECT($C16&"!E7")} -> 12285.803 | L16: {=INDIRECT($C16&"!E8")} -> 0 | M16: {=INDIRECT($C16&"!G6")} -> 496936.61 | N16: {=INDIRECT($C16&"!G9")} -> 48774.217 | O16: {=INDIRECT($C16&"!G5")} -> 545710.83 | P16: {=INDIRECT($C16&"!G7")} -> 12628.33 | Q16: {=INDIRECT($C16&"!G8")} -> 0 | R16: =IF(ISERROR(J16/G16),0,J16/G16) -> 0.97738233 | S16: =IF(R16>1,R16-1,0) -> 0
B17: =HYPERLINK("#"&"'"&C17&"'"&"!A1","LINK") -> LINK | C17: =IF(PQ!B22="","",PQ!B22) -> B.1.4 | D17: =IF(PQ!C22="","",PQ!C22) -> Regularização de bota-fora com espalhamento e execução de hidrossemeadura | E17: =IF(PQ!E22="","",PQ!E22) -> m³ | F17: =IF(PQ!F22="","",PQ!F22) -> 0 | G17: =IF(PQ!G22="","",PQ!G22) -> 0 | H17: {=INDIRECT($C17&"!E6")} -> 0 | I17: {=INDIRECT($C17&"!E9")} -> 0 | J17: {=INDIRECT($C17&"!E5")} -> 0 | K17: {=INDIRECT($C17&"!E7")} -> 0 | L17: {=INDIRECT($C17&"!E8")} -> 0 | M17: {=INDIRECT($C17&"!G6")} -> 0 | N17: {=INDIRECT($C17&"!G9")} -> 0 | O17: {=INDIRECT($C17&"!G5")} -> 0 | P17: {=INDIRECT($C17&"!G7")} -> 0 | Q17: {=INDIRECT($C17&"!G8")} -> 0 | R17: =IF(ISERROR(J17/G17),0,J17/G17) -> 0 | S17: =IF(R17>1,R17-1,0) -> 0
B18: =HYPERLINK("#"&"'"&C18&"'"&"!A1","LINK") -> LINK | C18: =IF(PQ!B23="","",PQ!B23) -> B.1.5 | D18: =IF(PQ!C23="","",PQ!C23) -> Royaltie de bota-fora | E18: =IF(PQ!E23="","",PQ!E23) -> m³ | F18: =IF(PQ!F23="","",PQ!F23) -> 0 | G18: =IF(PQ!G23="","",PQ!G23) -> 0 | H18: {=INDIRECT($C18&"!E6")} -> 0 | I18: {=INDIRECT($C18&"!E9")} -> 0 | J18: {=INDIRECT($C18&"!E5")} -> 0 | K18: {=INDIRECT($C18&"!E7")} -> 0 | L18: {=INDIRECT($C18&"!E8")} -> 0 | M18: {=INDIRECT($C18&"!G6")} -> 0 | N18: {=INDIRECT($C18&"!G9")} -> 0 | O18: {=INDIRECT($C18&"!G5")} -> 0 | P18: {=INDIRECT($C18&"!G7")} -> 0 | Q18: {=INDIRECT($C18&"!G8")} -> 0 | R18: =IF(ISERROR(J18/G18),0,J18/G18) -> 0 | S18: =IF(R18>1,R18-1,0) -> 0
B19: =HYPERLINK("#"&"'"&C19&"'"&"!A1","LINK") -> LINK | C19: =IF(PQ!B24="","",PQ!B24) -> B.1.6 | D19: =IF(PQ!C24="","",PQ!C24) -> Desmatamento, destocamento, limpeza de área e estocagem do material de limpeza com árvores de diâmetro até 0,15 m | E19: =IF(PQ!E24="","",PQ!E24) -> m² | F19: =IF(PQ!F24="","",PQ!F24) -> 0.85999993 | G19: =IF(PQ!G24="","",PQ!G24) -> 23377.56 | H19: {=INDIRECT($C19&"!E6")} -> 0 | I19: {=INDIRECT($C19&"!E9")} -> 21252.33 | J19: {=INDIRECT($C19&"!E5")} -> 21252.33 | K19: {=INDIRECT($C19&"!E7")} -> 2125.23 | L19: {=INDIRECT($C19&"!E8")} -> 0 | M19: {=INDIRECT($C19&"!G6")} -> 0 | N19: {=INDIRECT($C19&"!G9")} -> 18277.002 | O19: {=INDIRECT($C19&"!G5")} -> 18277.002 | P19: {=INDIRECT($C19&"!G7")} -> 1827.6977 | Q19: {=INDIRECT($C19&"!G8")} -> 0 | R19: =IF(ISERROR(J19/G19),0,J19/G19) -> 0.90909103 | S19: =IF(R19>1,R19-1,0) -> 0
B20: =HYPERLINK("#"&"'"&C20&"'"&"!A1","LINK") -> LINK | C20: =IF(PQ!B25="","",PQ!B25) -> B.1.7 | D20: =IF(PQ!C25="","",PQ!C25) -> Escavação, carga e transporte de material de 1ª categoria - DMT de 1.400 a 1.600 m - caminho de serviço pavimentado - com escavadeira e caminhão basculante de 14 m³ | E20: =IF(PQ!E25="","",PQ!E25) -> m³ | F20: =IF(PQ!F25="","",PQ!F25) -> 12.629999 | G20: =IF(PQ!G25="","",PQ!G25) -> 55083.7 | H20: {=INDIRECT($C20&"!E6")} -> 0 | I20: {=INDIRECT($C20&"!E9")} -> 55083.697 | J20: {=INDIRECT($C20&"!E5")} -> 55083.697 | K20: {=INDIRECT($C20&"!E7")} -> 0.003 | L20: {=INDIRECT($C20&"!E8")} -> 0 | M20: {=INDIRECT($C20&"!G6")} -> 0 | N20: {=INDIRECT($C20&"!G9")} -> 695707.05 | O20: {=INDIRECT($C20&"!G5")} -> 695707.05 | P20: {=INDIRECT($C20&"!G7")} -> 0.037889998 | Q20: {=INDIRECT($C20&"!G8")} -> 0 | R20: =IF(ISERROR(J20/G20),0,J20/G20) -> 0.99999995 | S20: =IF(R20>1,R20-1,0) -> 0
B21: =HYPERLINK("#"&"'"&C21&"'"&"!A1","LINK") -> LINK | C21: =IF(PQ!B26="","",PQ!B26) -> B.1.8 | D21: =IF(PQ!C26="","",PQ!C26) -> Escavação e carga de material de 2ª categoria - DMT acima de 3.000 m | E21: =IF(PQ!E26="","",PQ!E26) -> m³ | F21: =IF(PQ!F26="","",PQ!F26) -> 19.519859 | G21: =IF(PQ!G26="","",PQ!G26) -> 139.48 | H21: {=INDIRECT($C21&"!E6")} -> 0 | I21: {=INDIRECT($C21&"!E9")} -> 139.479 | J21: {=INDIRECT($C21&"!E5")} -> 139.479 | K21: {=INDIRECT($C21&"!E7")} -> 0.001 | L21: {=INDIRECT($C21&"!E8")} -> 0 | M21: {=INDIRECT($C21&"!G6")} -> 0 | N21: {=INDIRECT($C21&"!G9")} -> 2722.6105 | O21: {=INDIRECT($C21&"!G5")} -> 2722.6105 | P21: {=INDIRECT($C21&"!G7")} -> 0.019519859 | Q21: {=INDIRECT($C21&"!G8")} -> 0 | R21: =IF(ISERROR(J21/G21),0,J21/G21) -> 0.99999283 | S21: =IF(R21>1,R21-1,0) -> 0
B22: =HYPERLINK("#"&"'"&C22&"'"&"!A1","LINK") -> LINK | C22: =IF(PQ!B27="","",PQ!B27) -> B.1.9 | D22: =IF(PQ!C27="","",PQ!C27) -> Regularização de bota-fora | E22: =IF(PQ!E27="","",PQ!E27) -> m³ | F22: =IF(PQ!F27="","",PQ!F27) -> 2.33 | G22: =IF(PQ!G27="","",PQ!G27) -> 127700.41 | H22: {=INDIRECT($C22&"!E6")} -> 117700.41 | I22: {=INDIRECT($C22&"!E9")} -> 6145.816 | J22: {=INDIRECT($C22&"!E5")} -> 123846.22 | K22: {=INDIRECT($C22&"!E7")} -> 3854.187 | L22: {=INDIRECT($C22&"!E8")} -> 0 | M22: {=INDIRECT($C22&"!G6")} -> 274241.94 | N22: {=INDIRECT($C22&"!G9")} -> 14319.751 | O22: {=INDIRECT($C22&"!G5")} -> 288561.69 | P22: {=INDIRECT($C22&"!G7")} -> 8980.2556 | Q22: {=INDIRECT($C22&"!G8")} -> 0 | R22: =IF(ISERROR(J22/G22),0,J22/G22) -> 0.96981852 | S22: =IF(R22>1,R22-1,0) -> 0
C23: =IF(PQ!B28="","",PQ!B28) -> B.2 | D23: =IF(PQ!C28="","",PQ!C28) -> Drenagem e OACs | E23: =IF(PQ!E28="","",PQ!E28) | F23: =IF(PQ!F28="","",PQ!F28) | G23: =IF(PQ!G28="","",PQ!G28) | M23: =SUBTOTAL(9,M24:M32) -> 0 | N23: =SUBTOTAL(9,N24:N32) -> 372089.89 | O23: =SUBTOTAL(9,O24:O32) -> 372089.89 | P23: =SUBTOTAL(9,P24:P32) -> 177834.21 | Q23: =SUBTOTAL(9,Q24:Q32) -> 0
B24: =HYPERLINK("#"&"'"&C24&"'"&"!A1","LINK") -> LINK | C24: =IF(PQ!B29="","",PQ!B29) -> B.2.1 | D24: =IF(PQ!C29="","",PQ!C29) -> Demolição de dispositivos de drenagem | E24: =IF(PQ!E29="","",PQ!E29) -> m³ | F24: =IF(PQ!F29="","",PQ!F29) -> 0 | G24: =IF(PQ!G29="","",PQ!G29) -> 0 | H24: {=INDIRECT($C24&"!E6")} -> 0 | I24: {=INDIRECT($C24&"!E9")} -> 0 | J24: {=INDIRECT($C24&"!E5")} -> 0 | K24: {=INDIRECT($C24&"!E7")} -> 0 | L24: {=INDIRECT($C24&"!E8")} -> 0 | M24: {=INDIRECT($C24&"!G6")} -> 0 | N24: {=INDIRECT($C24&"!G9")} -> 0 | O24: {=INDIRECT($C24&"!G5")} -> 0 | P24: {=INDIRECT($C24&"!G7")} -> 0 | Q24: {=INDIRECT($C24&"!G8")} -> 0 | R24: =IF(ISERROR(J24/G24),0,J24/G24) -> 0 | S24: =IF(R24>1,R24-1,0) -> 0
B25: =HYPERLINK("#"&"'"&C25&"'"&"!A1","LINK") -> LINK | C25: =IF(PQ!B30="","",PQ!B30) -> B.2.2 | D25: =IF(PQ!C30="","",PQ!C30) -> Sarjeta triangular de concreto - STC 150-30 - escavação mecânica - areia e brita comerciais | E25: =IF(PQ!E30="","",PQ!E30) -> m | F25: =IF(PQ!F30="","",PQ!F30) -> 0 | G25: =IF(PQ!G30="","",PQ!G30) -> 0 | H25: {=INDIRECT($C25&"!E6")} -> 0 | I25: {=INDIRECT($C25&"!E9")} -> 0 | J25: {=INDIRECT($C25&"!E5")} -> 0 | K25: {=INDIRECT($C25&"!E7")} -> 0 | L25: {=INDIRECT($C25&"!E8")} -> 0 | M25: {=INDIRECT($C25&"!G6")} -> 0 | N25: {=INDIRECT($C25&"!G9")} -> 0 | O25: {=INDIRECT($C25&"!G5")} -> 0 | P25: {=INDIRECT($C25&"!G7")} -> 0 | Q25: {=INDIRECT($C25&"!G8")} -> 0 | R25: =IF(ISERROR(J25/G25),0,J25/G25) -> 0 | S25: =IF(R25>1,R25-1,0) -> 0
B26: =HYPERLINK("#"&"'"&C26&"'"&"!A1","LINK") -> LINK | C26: =IF(PQ!B31="","",PQ!B31) -> B.2.3 | D26: =IF(PQ!C31="","",PQ!C31) -> Valeta de proteção de cortes com revestimento de concreto - VPC 04 - areia e brita comerciais | E26: =IF(PQ!E31="","",PQ!E31) -> m | F26: =IF(PQ!F31="","",PQ!F31) -> 0 | G26: =IF(PQ!G31="","",PQ!G31) -> 0 | H26: {=INDIRECT($C26&"!E6")} -> 0 | I26: {=INDIRECT($C26&"!E9")} -> 0 | J26: {=INDIRECT($C26&"!E5")} -> 0 | K26: {=INDIRECT($C26&"!E7")} -> 0 | L26: {=INDIRECT($C26&"!E8")} -> 0 | M26: {=INDIRECT($C26&"!G6")} -> 0 | N26: {=INDIRECT($C26&"!G9")} -> 0 | O26: {=INDIRECT($C26&"!G5")} -> 0 | P26: {=INDIRECT($C26&"!G7")} -> 0 | Q26: {=INDIRECT($C26&"!G8")} -> 0 | R26: =IF(ISERROR(J26/G26),0,J26/G26) -> 0 | S26: =IF(R26>1,R26-1,0) -> 0
B27: =HYPERLINK("#"&"'"&C27&"'"&"!A1","LINK") -> LINK | C27: =IF(PQ!B32="","",PQ!B32) -> B.2.4 | D27: =IF(PQ!C32="","",PQ!C32) -> Caixa coletora A6 - CCS 200-60A | E27: =IF(PQ!E32="","",PQ!E32) -> und. | F27: =IF(PQ!F32="","",PQ!F32) -> 0 | G27: =IF(PQ!G32="","",PQ!G32) -> 0 | H27: {=INDIRECT($C27&"!E6")} -> 0 | I27: {=INDIRECT($C27&"!E9")} -> 0 | J27: {=INDIRECT($C27&"!E5")} -> 0 | K27: {=INDIRECT($C27&"!E7")} -> 0 | L27: {=INDIRECT($C27&"!E8")} -> 0 | M27: {=INDIRECT($C27&"!G6")} -> 0 | N27: {=INDIRECT($C27&"!G9")} -> 0 | O27: {=INDIRECT($C27&"!G5")} -> 0 | P27: {=INDIRECT($C27&"!G7")} -> 0 | Q27: {=INDIRECT($C27&"!G8")} -> 0 | R27: =IF(ISERROR(J27/G27),0,J27/G27) -> 0 | S27: =IF(R27>1,R27-1,0) -> 0
B28: =HYPERLINK("#"&"'"&C28&"'"&"!A1","LINK") -> LINK | C28: =IF(PQ!B33="","",PQ!B33) -> B.2.5 | D28: =IF(PQ!C33="","",PQ!C33) -> Descida d'água de cortes em degraus - DCD 02 - areia e brita comerciais | E28: =IF(PQ!E33="","",PQ!E33) -> m | F28: =IF(PQ!F33="","",PQ!F33) -> 0 | G28: =IF(PQ!G33="","",PQ!G33) -> 0 | H28: {=INDIRECT($C28&"!E6")} -> 0 | I28: {=INDIRECT($C28&"!E9")} -> 0 | J28: {=INDIRECT($C28&"!E5")} -> 0 | K28: {=INDIRECT($C28&"!E7")} -> 0 | L28: {=INDIRECT($C28&"!E8")} -> 0 | M28: {=INDIRECT($C28&"!G6")} -> 0 | N28: {=INDIRECT($C28&"!G9")} -> 0 | O28: {=INDIRECT($C28&"!G5")} -> 0 | P28: {=INDIRECT($C28&"!G7")} -> 0 | Q28: {=INDIRECT($C28&"!G8")} -> 0 | R28: =IF(ISERROR(J28/G28),0,J28/G28) -> 0 | S28: =IF(R28>1,R28-1,0) -> 0
B29: =HYPERLINK("#"&"'"&C29&"'"&"!A1","LINK") -> LINK | C29: =IF(PQ!B34="","",PQ!B34) -> B.2.6 | D29: =IF(PQ!C34="","",PQ!C34) -> Descida d'água de cortes em degraus - DCD 100-50 - areia e brita comerciais | E29: =IF(PQ!E34="","",PQ!E34) -> m | F29: =IF(PQ!F34="","",PQ!F34) -> 1034 | G29: =IF(PQ!G34="","",PQ!G34) -> 292.6 | H29: {=INDIRECT($C29&"!E6")} -> 0 | I29: {=INDIRECT($C29&"!E9")} -> 112.54 | J29: {=INDIRECT($C29&"!E5")} -> 112.54 | K29: {=INDIRECT($C29&"!E7")} -> 180.06 | L29: {=INDIRECT($C29&"!E8")} -> 0 | M29: {=INDIRECT($C29&"!G6")} -> 0 | N29: {=INDIRECT($C29&"!G9")} -> 116366.36 | O29: {=INDIRECT($C29&"!G5")} -> 116366.36 | P29: {=INDIRECT($C29&"!G7")} -> 186182.04 | Q29: {=INDIRECT($C29&"!G8")} -> 0 | R29: =IF(ISERROR(J29/G29),0,J29/G29) -> 0.38462064 | S29: =IF(R29>1,R29-1,0) -> 0
B30: =HYPERLINK("#"&"'"&C30&"'"&"!A1","LINK") -> LINK | C30: =IF(PQ!B35="","",PQ!B35) -> B.2.7 | D30: =IF(PQ!C35="","",PQ!C35) -> Valeta de proteção de cortes com revestimento de concreto - VPCC 120-30 - escavação mecânica - areia e brita comerciais | E30: =IF(PQ!E35="","",PQ!E35) -> m | F30: =IF(PQ!F35="","",PQ!F35) -> 141.79 | G30: =IF(PQ!G35="","",PQ!G35) -> 1111 | H30: {=INDIRECT($C30&"!E6")} -> 0 | I30: {=INDIRECT($C30&"!E9")} -> 1513.65 | J30: {=INDIRECT($C30&"!E5")} -> 1513.65 | K30: {=INDIRECT($C30&"!E7")} -> -402.65 | L30: {=INDIRECT($C30&"!E8")} -> 0 | M30: {=INDIRECT($C30&"!G6")} -> 0 | N30: {=INDIRECT($C30&"!G9")} -> 214620.43 | O30: {=INDIRECT($C30&"!G5")} -> 214620.43 | P30: {=INDIRECT($C30&"!G7")} -> -57091.743 | Q30: {=INDIRECT($C30&"!G8")} -> 0 | R30: =IF(ISERROR(J30/G30),0,J30/G30) -> 1.3624212 | S30: =IF(R30>1,R30-1,0) -> 0.36242124
B31: =HYPERLINK("#"&"'"&C31&"'"&"!A1","LINK") -> LINK | C31: =IF(PQ!B36="","",PQ!B36) -> B.2.8 | D31: =IF(PQ!C36="","",PQ!C36) -> Caixa coletora de sarjeta - CCS 250-120 A - com grelha de concreto - areia e brita comerciais | E31: =IF(PQ!E36="","",PQ!E36) -> und. | F31: =IF(PQ!F36="","",PQ!F36) -> 7471.91 | G31: =IF(PQ!G36="","",PQ!G36) -> 11 | H31: {=INDIRECT($C31&"!E6")} -> 0 | I31: {=INDIRECT($C31&"!E9")} -> 4 | J31: {=INDIRECT($C31&"!E5")} -> 4 | K31: {=INDIRECT($C31&"!E7")} -> 7 | L31: {=INDIRECT($C31&"!E8")} -> 0 | M31: {=INDIRECT($C31&"!G6")} -> 0 | N31: {=INDIRECT($C31&"!G9")} -> 29887.64 | O31: {=INDIRECT($C31&"!G5")} -> 29887.64 | P31: {=INDIRECT($C31&"!G7")} -> 52303.37 | Q31: {=INDIRECT($C31&"!G8")} -> 0 | R31: =IF(ISERROR(J31/G31),0,J31/G31) -> 0.36363636 | S31: =IF(R31>1,R31-1,0) -> 0
B32: =HYPERLINK("#"&"'"&C32&"'"&"!A1","LINK") -> LINK | C32: =IF(PQ!B37="","",PQ!B37) -> B.2.9 | D32: =IF(PQ!C37="","",PQ!C37) -> Sarjeta triangular de concreto - STC 88-20 - escavação mecânica - areia e brita comerciais | E32: =IF(PQ!E37="","",PQ!E37) -> m | F32: =IF(PQ!F37="","",PQ!F37) -> 58 | G32: =IF(PQ!G37="","",PQ!G37) -> 132 | H32: {=INDIRECT($C32&"!E6")} -> 0 | I32: {=INDIRECT($C32&"!E9")} -> 193.37 | J32: {=INDIRECT($C32&"!E5")} -> 193.37 | K32: {=INDIRECT($C32&"!E7")} -> -61.37 | L32: {=INDIRECT($C32&"!E8")} -> 0 | M32: {=INDIRECT($C32&"!G6")} -> 0 | N32: {=INDIRECT($C32&"!G9")} -> 11215.46 | O32: {=INDIRECT($C32&"!G5")} -> 11215.46 | P32: {=INDIRECT($C32&"!G7")} -> -3559.46 | Q32: {=INDIRECT($C32&"!G8")} -> 0 | R32: =IF(ISERROR(J32/G32),0,J32/G32) -> 1.4649242 | S32: =IF(R32>1,R32-1,0) -> 0.46492424
C33: =IF(PQ!B38="","",PQ!B38) -> B.3 | D33: =IF(PQ!C38="","",PQ!C38) -> Revestimento Vegetal | E33: =IF(PQ!E38="","",PQ!E38) | F33: =IF(PQ!F38="","",PQ!F38) | G33: =IF(PQ!G38="","",PQ!G38) | M33: =SUBTOTAL(9,M34:M35) -> 233722.92 | N33: =SUBTOTAL(9,N34:N35) -> 621222.57 | O33: =SUBTOTAL(9,O34:O35) -> 854945.49 | P33: =SUBTOTAL(9,P34:P35) -> -455945.49 | Q33: =SUBTOTAL(9,Q34:Q35) -> 171481.92
B34: =HYPERLINK("#"&"'"&C34&"'"&"!A1","LINK") -> LINK | C34: =IF(PQ!B39="","",PQ!B39) -> B.3.1 | D34: =IF(PQ!C39="","",PQ!C39) -> Proteção Vegetal (Hidrossemeadura + Biomanta) | E34: =IF(PQ!E39="","",PQ!E39) -> m² | F34: =IF(PQ!F39="","",PQ!F39) -> 25.3 | G34: =IF(PQ!G39="","",PQ!G39) -> 15000 | H34: {=INDIRECT($C34&"!E6")} -> 9238.06 | I34: {=INDIRECT($C34&"!E9")} -> 22721.098 | J34: {=INDIRECT($C34&"!E5")} -> 31959.158 | K34: {=INDIRECT($C34&"!E7")} -> -16959.158 | L34: {=INDIRECT($C34&"!E8")} -> 6777.9414 | M34: {=INDIRECT($C34&"!G6")} -> 233722.92 | N34: {=INDIRECT($C34&"!G9")} -> 574843.77 | O34: {=INDIRECT($C34&"!G5")} -> 808566.69 | P34: {=INDIRECT($C34&"!G7")} -> -429066.69 | Q34: {=INDIRECT($C34&"!G8")} -> 171481.92 | R34: =IF(ISERROR(J34/G34),0,J34/G34) -> 2.1306105 | S34: =IF(R34>1,R34-1,0) -> 1.1306105
B35: =HYPERLINK("#"&"'"&C35&"'"&"!A1","LINK") -> LINK | C35: =IF(PQ!B40="","",PQ!B40) -> B.3.2 | D35: =IF(PQ!C40="","",PQ!C40) -> Cerca com 4 fios de arame farpado e mourão de concreto de seção quadrada de 11 cm a cada 2,5 m e esticador de 15 cm a cada 50 m - areia e brita comerciais | E35: =IF(PQ!E40="","",PQ!E40) -> m | F35: =IF(PQ!F40="","",PQ!F40) -> 65 | G35: =IF(PQ!G40="","",PQ!G40) -> 300 | H35: {=INDIRECT($C35&"!E6")} -> 0 | I35: {=INDIRECT($C35&"!E9")} -> 713.52 | J35: {=INDIRECT($C35&"!E5")} -> 713.52 | K35: {=INDIRECT($C35&"!E7")} -> -413.52 | L35: {=INDIRECT($C35&"!E8")} -> 0 | M35: {=INDIRECT($C35&"!G6")} -> 0 | N35: {=INDIRECT($C35&"!G9")} -> 46378.8 | O35: {=INDIRECT($C35&"!G5")} -> 46378.8 | P35: {=INDIRECT($C35&"!G7")} -> -26878.8 | Q35: {=INDIRECT($C35&"!G8")} -> 0 | R35: =IF(ISERROR(J35/G35),0,J35/G35) -> 2.3784 | S35: =IF(R35>1,R35-1,0) -> 1.3784
C36: =IF(PQ!B41="","",PQ!B41) -> C. | D36: =IF(PQ!C41="","",PQ!C41) -> Implantação de Desvio 1 - Km 303+450 - Leste | E36: =IF(PQ!E41="","",PQ!E41) | F36: =IF(PQ!F41="","",PQ!F41) | G36: =IF(PQ!G41="","",PQ!G41) | M36: =SUBTOTAL(9,M37:M62) -> 776624.58 | N36: =SUBTOTAL(9,N37:N62) -> 26511.6 | O36: =SUBTOTAL(9,O37:O62) -> 803136.18 | P36: =SUBTOTAL(9,P37:P62) -> 4561.1893 | Q36: =SUBTOTAL(9,Q37:Q62) -> 0
C37: =IF(PQ!B42="","",PQ!B42) -> C.1 | D37: =IF(PQ!C42="","",PQ!C42) -> Terraplenagem | E37: =IF(PQ!E42="","",PQ!E42) | F37: =IF(PQ!F42="","",PQ!F42) | G37: =IF(PQ!G42="","",PQ!G42) | M37: =SUBTOTAL(9,M38:M42) -> 24752.505 | N37: =SUBTOTAL(9,N38:N42) -> 0 | O37: =SUBTOTAL(9,O38:O42) -> 24752.505 | P37: =SUBTOTAL(9,P38:P42) -> 14813.305 | Q37: =SUBTOTAL(9,Q38:Q42) -> 0
B38: =HYPERLINK("#"&"'"&C38&"'"&"!A1","LINK") -> LINK | C38: =IF(PQ!B43="","",PQ!B43) -> C.1.1 | D38: =IF(PQ!C43="","",PQ!C43) -> Desmatamento, destocamento, limpeza de área e estocagem do material de limpeza com árvores de diâmetro até 0,15 m | E38: =IF(PQ!E43="","",PQ!E43) -> m² | F38: =IF(PQ!F43="","",PQ!F43) -> 0.8599999 | G38: =IF(PQ!G43="","",PQ!G43) -> 7740.78 | H38: {=INDIRECT($C38&"!E6")} -> 7740.779 | I38: {=INDIRECT($C38&"!E9")} -> 0 | J38: {=INDIRECT($C38&"!E5")} -> 7740.779 | K38: {=INDIRECT($C38&"!E7")} -> 0.001 | L38: {=INDIRECT($C38&"!E8")} -> 0 | M38: {=INDIRECT($C38&"!G6")} -> 6657.0691 | N38: {=INDIRECT($C38&"!G9")} -> 0 | O38: {=INDIRECT($C38&"!G5")} -> 6657.0691 | P38: {=INDIRECT($C38&"!G7")} -> 0.0008599999 | Q38: {=INDIRECT($C38&"!G8")} -> 0 | R38: =IF(ISERROR(J38/G38),0,J38/G38) -> 0.99999987 | S38: =IF(R38>1,R38-1,0) -> 0
B39: =HYPERLINK("#"&"'"&C39&"'"&"!A1","LINK") -> LINK | C39: =IF(PQ!B44="","",PQ!B44) -> C.1.2 | D39: =IF(PQ!C44="","",PQ!C44) -> Transporte com caminhão basculante de 14 m³ - rodovia pavimentada | E39: =IF(PQ!E44="","",PQ!E44) -> T x Km | F39: =IF(PQ!F44="","",PQ!F44) -> 1.539998 | G39: =IF(PQ!G44="","",PQ!G44) -> 603.78 | H39: {=INDIRECT($C39&"!E6")} -> 603.78076 | I39: {=INDIRECT($C39&"!E9")} -> 0 | J39: {=INDIRECT($C39&"!E5")} -> 603.78076 | K39: {=INDIRECT($C39&"!E7")} -> -0.000762 | L39: {=INDIRECT($C39&"!E8")} -> 0 | M39: {=INDIRECT($C39&"!G6")} -> 929.82117 | N39: {=INDIRECT($C39&"!G9")} -> 0 | O39: {=INDIRECT($C39&"!G5")} -> 929.82117 | P39: {=INDIRECT($C39&"!G7")} -> -0.0011734785 | Q39: {=INDIRECT($C39&"!G8")} -> 0 | R39: =IF(ISERROR(J39/G39),0,J39/G39) -> 1.0000013 | S39: =IF(R39>1,R39-1,0) -> 1.2620491e-06
B40: =HYPERLINK("#"&"'"&C40&"'"&"!A1","LINK") -> LINK | C40: =IF(PQ!B45="","",PQ!B45) -> C.1.3 | D40: =IF(PQ!C45="","",PQ!C45) -> Escavação, carga e transporte de material de 1ª categoria - DMT de 1.000 a 1.200 m - com escavadeira e caminhão basculante de 14 m³ | E40: =IF(PQ!E45="","",PQ!E45) -> m³ | F40: =IF(PQ!F45="","",PQ!F45) -> 0 | G40: =IF(PQ!G45="","",PQ!G45) -> 0 | H40: {=INDIRECT($C40&"!E6")} -> 6679.445 | I40: {=INDIRECT($C40&"!E9")} -> 0 | J40: {=INDIRECT($C40&"!E5")} -> 6679.445 | K40: {=INDIRECT($C40&"!E7")} -> -6679.445 | L40: {=INDIRECT($C40&"!E8")} -> 0 | M40: {=INDIRECT($C40&"!G6")} -> 0 | N40: {=INDIRECT($C40&"!G9")} -> 0 | O40: {=INDIRECT($C40&"!G5")} -> 0 | P40: {=INDIRECT($C40&"!G7")} -> 0 | Q40: {=INDIRECT($C40&"!G8")} -> 0 | R40: =IF(ISERROR(J40/G40),0,J40/G40) -> 0 | S40: =IF(R40>1,R40-1,0) -> 0
B41: =HYPERLINK("#"&"'"&C41&"'"&"!A1","LINK") -> LINK | C41: =IF(PQ!B46="","",PQ!B46) -> C.1.4 | D41: =IF(PQ!C46="","",PQ!C46) -> Regularização de bota-fora com espalhamento e execução de hidrossemeadura | E41: =IF(PQ!E46="","",PQ!E46) -> m³ | F41: =IF(PQ!F46="","",PQ!F46) -> 2.6999987 | G41: =IF(PQ!G46="","",PQ!G46) -> 6357.64 | H41: {=INDIRECT($C41&"!E6")} -> 6357.638 | I41: {=INDIRECT($C41&"!E9")} -> 0 | J41: {=INDIRECT($C41&"!E5")} -> 6357.638 | K41: {=INDIRECT($C41&"!E7")} -> 0.002 | L41: {=INDIRECT($C41&"!E8")} -> 0 | M41: {=INDIRECT($C41&"!G6")} -> 17165.615 | N41: {=INDIRECT($C41&"!G9")} -> 0 | O41: {=INDIRECT($C41&"!G5")} -> 17165.615 | P41: {=INDIRECT($C41&"!G7")} -> 0.0053999975 | Q41: {=INDIRECT($C41&"!G8")} -> 0 | R41: =IF(ISERROR(J41/G41),0,J41/G41) -> 0.99999969 | S41: =IF(R41>1,R41-1,0) -> 0
B42: =HYPERLINK("#"&"'"&C42&"'"&"!A1","LINK") -> LINK | C42: =IF(PQ!B47="","",PQ!B47) -> C.1.5 | D42: =IF(PQ!C47="","",PQ!C47) -> Regularização de bota-fora | E42: =IF(PQ!E47="","",PQ!E47) -> m³ | F42: =IF(PQ!F47="","",PQ!F47) -> 2.3299998 | G42: =IF(PQ!G47="","",PQ!G47) -> 6357.64 | H42: {=INDIRECT($C42&"!E6")} -> 0 | I42: {=INDIRECT($C42&"!E9")} -> 0 | J42: {=INDIRECT($C42&"!E5")} -> 0 | K42: {=INDIRECT($C42&"!E7")} -> 6357.64 | L42: {=INDIRECT($C42&"!E8")} -> 0 | M42: {=INDIRECT($C42&"!G6")} -> 0 | N42: {=INDIRECT($C42&"!G9")} -> 0 | O42: {=INDIRECT($C42&"!G5")} -> 0 | P42: {=INDIRECT($C42&"!G7")} -> 14813.3 | Q42: {=INDIRECT($C42&"!G8")} -> 0 | R42: =IF(ISERROR(J42/G42),0,J42/G42) -> 0 | S42: =IF(R42>1,R42-1,0) -> 0
C43: =IF(PQ!B48="","",PQ!B48) -> C.2 | D43: =IF(PQ!C48="","",PQ!C48) -> Pavimentação | E43: =IF(PQ!E48="","",PQ!E48) | F43: =IF(PQ!F48="","",PQ!F48) | G43: =IF(PQ!G48="","",PQ!G48) | M43: =SUBTOTAL(9,M44:M49) -> 431823.01 | N43: =SUBTOTAL(9,N44:N49) -> 0 | O43: =SUBTOTAL(9,O44:O49) -> 431823.01 | P43: =SUBTOTAL(9,P44:P49) -> -13042.746 | Q43: =SUBTOTAL(9,Q44:Q49) -> 0
B44: =HYPERLINK("#"&"'"&C44&"'"&"!A1","LINK") -> LINK | C44: =IF(PQ!B49="","",PQ!B49) -> C.2.1 | D44: =IF(PQ!C49="","",PQ!C49) -> Preparo e melhoramento do subleito | E44: =IF(PQ!E49="","",PQ!E49) -> m² | F44: =IF(PQ!F49="","",PQ!F49) -> 4.2900002 | G44: =IF(PQ!G49="","",PQ!G49) -> 2405.24 | H44: {=INDIRECT($C44&"!E6")} -> 2405.241 | I44: {=INDIRECT($C44&"!E9")} -> 0 | J44: {=INDIRECT($C44&"!E5")} -> 2405.241 | K44: {=INDIRECT($C44&"!E7")} -> -0.001 | L44: {=INDIRECT($C44&"!E8")} -> 0 | M44: {=INDIRECT($C44&"!G6")} -> 10318.484 | N44: {=INDIRECT($C44&"!G9")} -> 0 | O44: {=INDIRECT($C44&"!G5")} -> 10318.484 | P44: {=INDIRECT($C44&"!G7")} -> -0.0042900002 | Q44: {=INDIRECT($C44&"!G8")} -> 0 | R44: =IF(ISERROR(J44/G44),0,J44/G44) -> 1.0000004 | S44: =IF(R44>1,R44-1,0) -> 4.1575893e-07
B45: =HYPERLINK("#"&"'"&C45&"'"&"!A1","LINK") -> LINK | C45: =IF(PQ!B50="","",PQ!B50) -> C.2.2 | D45: =IF(PQ!C50="","",PQ!C50) -> Rachão ou pedra de mão | E45: =IF(PQ!E50="","",PQ!E50) -> m³ | F45: =IF(PQ!F50="","",PQ!F50) -> 153.92007 | G45: =IF(PQ!G50="","",PQ!G50) -> 1202.62 | H45: {=INDIRECT($C45&"!E6")} -> 1202.6205 | I45: {=INDIRECT($C45&"!E9")} -> 0 | J45: {=INDIRECT($C45&"!E5")} -> 1202.6205 | K45: {=INDIRECT($C45&"!E7")} -> -0.0005 | L45: {=INDIRECT($C45&"!E8")} -> 0 | M45: {=INDIRECT($C45&"!G6")} -> 185107.43 | N45: {=INDIRECT($C45&"!G9")} -> 0 | O45: {=INDIRECT($C45&"!G5")} -> 185107.43 | P45: {=INDIRECT($C45&"!G7")} -> -0.076960033 | Q45: {=INDIRECT($C45&"!G8")} -> 0 | R45: =IF(ISERROR(J45/G45),0,J45/G45) -> 1.0000004 | S45: =IF(R45>1,R45-1,0) -> 4.1575893e-07
B46: =HYPERLINK("#"&"'"&C46&"'"&"!A1","LINK") -> LINK | C46: =IF(PQ!B51="","",PQ!B51) -> C.2.3 | D46: =IF(PQ!C51="","",PQ!C51) -> Sub-base ou base de brita graduada simples (BGS) | E46: =IF(PQ!E51="","",PQ!E51) -> m³ | F46: =IF(PQ!F51="","",PQ!F51) -> 173.54936 | G46: =IF(PQ!G51="","",PQ!G51) -> 481.05 | H46: {=INDIRECT($C46&"!E6")} -> 481.0482 | I46: {=INDIRECT($C46&"!E9")} -> 0 | J46: {=INDIRECT($C46&"!E5")} -> 481.0482 | K46: {=INDIRECT($C46&"!E7")} -> 0.0018 | L46: {=INDIRECT($C46&"!E8")} -> 0 | M46: {=INDIRECT($C46&"!G6")} -> 83485.608 | N46: {=INDIRECT($C46&"!G9")} -> 0 | O46: {=INDIRECT($C46&"!G5")} -> 83485.608 | P46: {=INDIRECT($C46&"!G7")} -> 0.31238885 | Q46: {=INDIRECT($C46&"!G8")} -> 0 | R46: =IF(ISERROR(J46/G46),0,J46/G46) -> 0.99999626 | S46: =IF(R46>1,R46-1,0) -> 0
B47: =HYPERLINK("#"&"'"&C47&"'"&"!A1","LINK") -> LINK | C47: =IF(PQ!B52="","",PQ!B52) -> C.2.4 | D47: =IF(PQ!C52="","",PQ!C52) -> Imprimadura betuminosa impermeabilizante | E47: =IF(PQ!E52="","",PQ!E52) -> m² | F47: =IF(PQ!F52="","",PQ!F52) -> 0.8700005 | G47: =IF(PQ!G52="","",PQ!G52) -> 2405.24 | H47: {=INDIRECT($C47&"!E6")} -> 2405.241 | I47: {=INDIRECT($C47&"!E9")} -> 0 | J47: {=INDIRECT($C47&"!E5")} -> 2405.241 | K47: {=INDIRECT($C47&"!E7")} -> -0.001 | L47: {=INDIRECT($C47&"!E8")} -> 0 | M47: {=INDIRECT($C47&"!G6")} -> 2092.5609 | N47: {=INDIRECT($C47&"!G9")} -> 0 | O47: {=INDIRECT($C47&"!G5")} -> 2092.5609 | P47: {=INDIRECT($C47&"!G7")} -> -0.0008700005 | Q47: {=INDIRECT($C47&"!G8")} -> 0 | R47: =IF(ISERROR(J47/G47),0,J47/G47) -> 1.0000004 | S47: =IF(R47>1,R47-1,0) -> 4.1575893e-07
B48: =HYPERLINK("#"&"'"&C48&"'"&"!A1","LINK") -> LINK | C48: =IF(PQ!B53="","",PQ!B53) -> C.2.5 | D48: =IF(PQ!C53="","",PQ!C53) -> Imprimadura betuminosa ligante | E48: =IF(PQ!E53="","",PQ!E53) -> m² | F48: =IF(PQ!F53="","",PQ!F53) -> 0.53000116 | G48: =IF(PQ!G53="","",PQ!G53) -> 4810.48 | H48: {=INDIRECT($C48&"!E6")} -> 4810.482 | I48: {=INDIRECT($C48&"!E9")} -> 0 | J48: {=INDIRECT($C48&"!E5")} -> 4810.482 | K48: {=INDIRECT($C48&"!E7")} -> -0.002 | L48: {=INDIRECT($C48&"!E8")} -> 0 | M48: {=INDIRECT($C48&"!G6")} -> 2549.5611 | N48: {=INDIRECT($C48&"!G9")} -> 0 | O48: {=INDIRECT($C48&"!G5")} -> 2549.5611 | P48: {=INDIRECT($C48&"!G7")} -> -0.0010600023 | Q48: {=INDIRECT($C48&"!G8")} -> 0 | R48: =IF(ISERROR(J48/G48),0,J48/G48) -> 1.0000004 | S48: =IF(R48>1,R48-1,0) -> 4.1575893e-07
B49: =HYPERLINK("#"&"'"&C49&"'"&"!A1","LINK") -> LINK | C49: =IF(PQ!B54="","",PQ!B54) -> C.2.6 | D49: =IF(PQ!C54="","",PQ!C54) -> CBUQ Faixa C/D c/ DOP ou polímero similar | E49: =IF(PQ!E54="","",PQ!E54) -> T | F49: =IF(PQ!F54="","",PQ!F54) -> 308.7431 | G49: =IF(PQ!G54="","",PQ!G54) -> 437.99 | H49: {=INDIRECT($C49&"!E6")} -> 480.2354 | I49: {=INDIRECT($C49&"!E9")} -> 0 | J49: {=INDIRECT($C49&"!E5")} -> 480.2354 | K49: {=INDIRECT($C49&"!E7")} -> -42.245397 | L49: {=INDIRECT($C49&"!E8")} -> 0 | M49: {=INDIRECT($C49&"!G6")} -> 148269.36 | N49: {=INDIRECT($C49&"!G9")} -> 0 | O49: {=INDIRECT($C49&"!G5")} -> 148269.36 | P49: {=INDIRECT($C49&"!G7")} -> -13042.975 | Q49: {=INDIRECT($C49&"!G8")} -> 0 | R49: =IF(ISERROR(J49/G49),0,J49/G49) -> 1.0964529 | S49: =IF(R49>1,R49-1,0) -> 0.096452881
C50: =IF(PQ!B55="","",PQ!B55) -> C.3 | D50: =IF(PQ!C55="","",PQ!C55) -> Material Betuminoso e Transportes | E50: =IF(PQ!E55="","",PQ!E55) | F50: =IF(PQ!F55="","",PQ!F55) | G50: =IF(PQ!G55="","",PQ!G55) | M50: =SUBTOTAL(9,M51:M56) -> 320049.07 | N50: =SUBTOTAL(9,N51:N56) -> 0 | O50: =SUBTOTAL(9,O51:O56) -> 320049.07 | P50: =SUBTOTAL(9,P51:P56) -> -15012.07 | Q50: =SUBTOTAL(9,Q51:Q56) -> 0
B51: =HYPERLINK("#"&"'"&C51&"'"&"!A1","LINK") -> LINK | C51: =IF(PQ!B56="","",PQ!B56) -> C.3.1 | D51: =IF(PQ!C56="","",PQ!C56) -> Fornecimento de emulsão asfáltica Imprimer | E51: =IF(PQ!E56="","",PQ!E56) -> T | F51: =IF(PQ!F56="","",PQ!F56) -> 3055.8567 | G51: =IF(PQ!G56="","",PQ!G56) -> 3.28 | H51: {=INDIRECT($C51&"!E6")} -> 3.7632974 | I51: {=INDIRECT($C51&"!E9")} -> 0 | J51: {=INDIRECT($C51&"!E5")} -> 3.7632974 | K51: {=INDIRECT($C51&"!E7")} -> -0.48329736 | L51: {=INDIRECT($C51&"!E8")} -> 0 | M51: {=INDIRECT($C51&"!G6")} -> 11500.097 | N51: {=INDIRECT($C51&"!G9")} -> 0 | O51: {=INDIRECT($C51&"!G5")} -> 11500.097 | P51: {=INDIRECT($C51&"!G7")} -> -1476.8875 | Q51: {=INDIRECT($C51&"!G8")} -> 0 | R51: =IF(ISERROR(J51/G51),0,J51/G51) -> 1.1473468 | S51: =IF(R51>1,R51-1,0) -> 0.14734676
B52: =HYPERLINK("#"&"'"&C52&"'"&"!A1","LINK") -> LINK | C52: =IF(PQ!B57="","",PQ!B57) -> C.3.2 | D52: =IF(PQ!C57="","",PQ!C57) -> Fornecimento de emulsão asfáltica tipo RR-1C | E52: =IF(PQ!E57="","",PQ!E57) -> T | F52: =IF(PQ!F57="","",PQ!F57) -> 3461.7051 | G52: =IF(PQ!G57="","",PQ!G57) -> 2.34 | H52: {=INDIRECT($C52&"!E6")} -> 2.6298571 | I52: {=INDIRECT($C52&"!E9")} -> 0 | J52: {=INDIRECT($C52&"!E5")} -> 2.6298571 | K52: {=INDIRECT($C52&"!E7")} -> -0.28985705 | L52: {=INDIRECT($C52&"!E8")} -> 0 | M52: {=INDIRECT($C52&"!G6")} -> 9103.7896 | N52: {=INDIRECT($C52&"!G9")} -> 0 | O52: {=INDIRECT($C52&"!G5")} -> 9103.7896 | P52: {=INDIRECT($C52&"!G7")} -> -1003.3996 | Q52: {=INDIRECT($C52&"!G8")} -> 0 | R52: =IF(ISERROR(J52/G52),0,J52/G52) -> 1.1238705 | S52: =IF(R52>1,R52-1,0) -> 0.12387053
B53: =HYPERLINK("#"&"'"&C53&"'"&"!A1","LINK") -> LINK | C53: =IF(PQ!B58="","",PQ!B58) -> C.3.3 | D53: =IF(PQ!C58="","",PQ!C58) -> Fornecimento de CAP modificado com adição de polímero | E53: =IF(PQ!E58="","",PQ!E58) -> T | F53: =IF(PQ!F58="","",PQ!F58) -> 6076.7261 | G53: =IF(PQ!G58="","",PQ!G58) -> 22.34 | H53: {=INDIRECT($C53&"!E6")} -> 24.395266 | I53: {=INDIRECT($C53&"!E9")} -> 0 | J53: {=INDIRECT($C53&"!E5")} -> 24.395266 | K53: {=INDIRECT($C53&"!E7")} -> -2.0552662 | L53: {=INDIRECT($C53&"!E8")} -> 0 | M53: {=INDIRECT($C53&"!G6")} -> 148243.35 | N53: {=INDIRECT($C53&"!G9")} -> 0 | O53: {=INDIRECT($C53&"!G5")} -> 148243.35 | P53: {=INDIRECT($C53&"!G7")} -> -12489.29 | Q53: {=INDIRECT($C53&"!G8")} -> 0 | R53: =IF(ISERROR(J53/G53),0,J53/G53) -> 1.0919994 | S53: =IF(R53>1,R53-1,0) -> 0.091999382
B54: =HYPERLINK("#"&"'"&C54&"'"&"!A1","LINK") -> LINK | C54: =IF(PQ!B59="","",PQ!B59) -> C.3.4 | D54: =IF(PQ!C59="","",PQ!C59) -> Transporte com caminhão basculante de 14 m³ - rodovia pavimentada - Agregados | E54: =IF(PQ!E59="","",PQ!E59) -> T x Km | F54: =IF(PQ!F59="","",PQ!F59) -> 1.06 | G54: =IF(PQ!G59="","",PQ!G59) -> 119143.16 | H54: {=INDIRECT($C54&"!E6")} -> 119183.25 | I54: {=INDIRECT($C54&"!E9")} -> 0 | J54: {=INDIRECT($C54&"!E5")} -> 119183.25 | K54: {=INDIRECT($C54&"!E7")} -> -40.089634 | L54: {=INDIRECT($C54&"!E8")} -> 0 | M54: {=INDIRECT($C54&"!G6")} -> 126334.25 | N54: {=INDIRECT($C54&"!G9")} -> 0 | O54: {=INDIRECT($C54&"!G5")} -> 126334.25 | P54: {=INDIRECT($C54&"!G7")} -> -42.495012 | Q54: {=INDIRECT($C54&"!G8")} -> 0 | R54: =IF(ISERROR(J54/G54),0,J54/G54) -> 1.0003365 | S54: =IF(R54>1,R54-1,0) -> 0.00033648288
B55: =HYPERLINK("#"&"'"&C55&"'"&"!A1","LINK") -> LINK | C55: =IF(PQ!B60="","",PQ!B60) -> C.3.5 | D55: =IF(PQ!C60="","",PQ!C60) -> Transporte com caminhão basculante de 14 m³ - rodovia pavimentada - Massa Asfaltica | E55: =IF(PQ!E60="","",PQ!E60) -> T x Km | F55: =IF(PQ!F60="","",PQ!F60) -> 0.78999987 | G55: =IF(PQ!G60="","",PQ!G60) -> 24878.08 | H55: {=INDIRECT($C55&"!E6")} -> 24878.081 | I55: {=INDIRECT($C55&"!E9")} -> 0 | J55: {=INDIRECT($C55&"!E5")} -> 24878.081 | K55: {=INDIRECT($C55&"!E7")} -> -0.001193528 | L55: {=INDIRECT($C55&"!E8")} -> 0 | M55: {=INDIRECT($C55&"!G6")} -> 19653.681 | N55: {=INDIRECT($C55&"!G9")} -> 0 | O55: {=INDIRECT($C55&"!G5")} -> 19653.681 | P55: {=INDIRECT($C55&"!G7")} -> -0.00094288696 | Q55: {=INDIRECT($C55&"!G8")} -> 0 | R55: =IF(ISERROR(J55/G55),0,J55/G55) -> 1 | S55: =IF(R55>1,R55-1,0) -> 4.7975085e-08
B56: =HYPERLINK("#"&"'"&C56&"'"&"!A1","LINK") -> LINK | C56: =IF(PQ!B61="","",PQ!B61) -> C.3.6 | D56: =IF(PQ!C61="","",PQ!C61) -> Transporte com caminhão basculante de 14 m³ - rodovia pavimentada - Materiais Betuminosos | E56: =IF(PQ!E61="","",PQ!E61) -> T x Km | F56: =IF(PQ!F61="","",PQ!F61) -> 0.78999953 | G56: =IF(PQ!G61="","",PQ!G61) -> 6599.89 | H56: {=INDIRECT($C56&"!E6")} -> 6599.8867 | I56: {=INDIRECT($C56&"!E9")} -> 0 | J56: {=INDIRECT($C56&"!E5")} -> 6599.8867 | K56: {=INDIRECT($C56&"!E7")} -> 0.0033303483 | L56: {=INDIRECT($C56&"!E8")} -> 0 | M56: {=INDIRECT($C56&"!G6")} -> 5213.9074 | N56: {=INDIRECT($C56&"!G9")} -> 0 | O56: {=INDIRECT($C56&"!G5")} -> 5213.9074 | P56: {=INDIRECT($C56&"!G7")} -> 0.0026309736 | Q56: {=INDIRECT($C56&"!G8")} -> 0 | R56: =IF(ISERROR(J56/G56),0,J56/G56) -> 0.9999995 | S56: =IF(R56>1,R56-1,0) -> 0
C57: =IF(PQ!B62="","",PQ!B62) -> C.4 | D57: =IF(PQ!C62="","",PQ!C62) -> Drenagem e OACs | E57: =IF(PQ!E62="","",PQ!E62) | F57: =IF(PQ!F62="","",PQ!F62) | G57: =IF(PQ!G62="","",PQ!G62) | M57: =SUBTOTAL(9,M58:M62) -> 0 | N57: =SUBTOTAL(9,N58:N62) -> 26511.6 | O57: =SUBTOTAL(9,O58:O62) -> 26511.6 | P57: =SUBTOTAL(9,P58:P62) -> 17802.7 | Q57: =SUBTOTAL(9,Q58:Q62) -> 0
B58: =HYPERLINK("#"&"'"&C58&"'"&"!A1","LINK") -> LINK | C58: =IF(PQ!B63="","",PQ!B63) -> C.4.1 | D58: =IF(PQ!C63="","",PQ!C63) -> Sarjeta triangular de concreto - STC 88-20 - escavação mecânica - areia e brita comerciais | E58: =IF(PQ!E63="","",PQ!E63) -> m | F58: =IF(PQ!F63="","",PQ!F63) -> 58 | G58: =IF(PQ!G63="","",PQ!G63) -> 456.5 | H58: {=INDIRECT($C58&"!E6")} -> 0 | I58: {=INDIRECT($C58&"!E9")} -> 285.4 | J58: {=INDIRECT($C58&"!E5")} -> 285.4 | K58: {=INDIRECT($C58&"!E7")} -> 171.1 | L58: {=INDIRECT($C58&"!E8")} -> 0 | M58: {=INDIRECT($C58&"!G6")} -> 0 | N58: {=INDIRECT($C58&"!G9")} -> 16553.2 | O58: {=INDIRECT($C58&"!G5")} -> 16553.2 | P58: {=INDIRECT($C58&"!G7")} -> 9923.8 | Q58: {=INDIRECT($C58&"!G8")} -> 0 | R58: =IF(ISERROR(J58/G58),0,J58/G58) -> 0.62519168 | S58: =IF(R58>1,R58-1,0) -> 0
B59: =HYPERLINK("#"&"'"&C59&"'"&"!A1","LINK") -> LINK | C59: =IF(PQ!B64="","",PQ!B64) -> C.4.2 | D59: =IF(PQ!C64="","",PQ!C64) -> Dissipador de energia - DES 88-264 - areia, brita e pedra de mão comerciais | E59: =IF(PQ!E64="","",PQ!E64) -> und. | F59: =IF(PQ!F64="","",PQ!F64) -> 959.24 | G59: =IF(PQ!G64="","",PQ!G64) -> 7 | H59: {=INDIRECT($C59&"!E6")} -> 0 | I59: {=INDIRECT($C59&"!E9")} -> 0 | J59: {=INDIRECT($C59&"!E5")} -> 0 | K59: {=INDIRECT($C59&"!E7")} -> 7 | L59: {=INDIRECT($C59&"!E8")} -> 0 | M59: {=INDIRECT($C59&"!G6")} -> 0 | N59: {=INDIRECT($C59&"!G9")} -> 0 | O59: {=INDIRECT($C59&"!G5")} -> 0 | P59: {=INDIRECT($C59&"!G7")} -> 6714.68 | Q59: {=INDIRECT($C59&"!G8")} -> 0 | R59: =IF(ISERROR(J59/G59),0,J59/G59) -> 0 | S59: =IF(R59>1,R59-1,0) -> 0
B60: =HYPERLINK("#"&"'"&C60&"'"&"!A1","LINK") -> LINK | C60: =IF(PQ!B65="","",PQ!B65) -> C.4.3 | D60: =IF(PQ!C65="","",PQ!C65) -> Dreno longitudinal profundo para corte em solo - DPS 01 - tubo PEAD e areia comercial | E60: =IF(PQ!E65="","",PQ!E65) -> m | F60: =IF(PQ!F65="","",PQ!F65) -> 166.25 | G60: =IF(PQ!G65="","",PQ!G65) -> 15.4 | H60: {=INDIRECT($C60&"!E6")} -> 0 | I60: {=INDIRECT($C60&"!E9")} -> 14 | J60: {=INDIRECT($C60&"!E5")} -> 14 | K60: {=INDIRECT($C60&"!E7")} -> 1.4 | L60: {=INDIRECT($C60&"!E8")} -> 0 | M60: {=INDIRECT($C60&"!G6")} -> 0 | N60: {=INDIRECT($C60&"!G9")} -> 2327.5 | O60: {=INDIRECT($C60&"!G5")} -> 2327.5 | P60: {=INDIRECT($C60&"!G7")} -> 232.75 | Q60: {=INDIRECT($C60&"!G8")} -> 0 | R60: =IF(ISERROR(J60/G60),0,J60/G60) -> 0.90909091 | S60: =IF(R60>1,R60-1,0) -> 0
B61: =HYPERLINK("#"&"'"&C61&"'"&"!A1","LINK") -> LINK | C61: =IF(PQ!B66="","",PQ!B66) -> C.4.4 | D61: =IF(PQ!C66="","",PQ!C66) -> Concreto fck = 20 MPa - confecção em central dosadora de 30 m³/h - areia e brita comerciais | E61: =IF(PQ!E66="","",PQ!E66) -> m³ | F61: =IF(PQ!F66="","",PQ!F66) -> 729.31429 | G61: =IF(PQ!G66="","",PQ!G66) -> 2.8 | H61: {=INDIRECT($C61&"!E6")} -> 0 | I61: {=INDIRECT($C61&"!E9")} -> 2.8 | J61: {=INDIRECT($C61&"!E5")} -> 2.8 | K61: {=INDIRECT($C61&"!E7")} -> 0 | L61: {=INDIRECT($C61&"!E8")} -> 0 | M61: {=INDIRECT($C61&"!G6")} -> 0 | N61: {=INDIRECT($C61&"!G9")} -> 2042.08 | O61: {=INDIRECT($C61&"!G5")} -> 2042.08 | P61: {=INDIRECT($C61&"!G7")} -> 0 | Q61: {=INDIRECT($C61&"!G8")} -> 0 | R61: =IF(ISERROR(J61/G61),0,J61/G61) -> 1 | S61: =IF(R61>1,R61-1,0) -> 0
B62: =HYPERLINK("#"&"'"&C62&"'"&"!A1","LINK") -> LINK | C62: =IF(PQ!B67="","",PQ!B67) -> C.4.5 | D62: =IF(PQ!C67="","",PQ!C67) -> Tubo PEAD para drenagem - D = 800 mm - fornecimento e instalação | E62: =IF(PQ!E67="","",PQ!E67) -> m | F62: =IF(PQ!F67="","",PQ!F67) -> 931.47 | G62: =IF(PQ!G67="","",PQ!G67) -> 7 | H62: {=INDIRECT($C62&"!E6")} -> 0 | I62: {=INDIRECT($C62&"!E9")} -> 6 | J62: {=INDIRECT($C62&"!E5")} -> 6 | K62: {=INDIRECT($C62&"!E7")} -> 1 | L62: {=INDIRECT($C62&"!E8")} -> 0 | M62: {=INDIRECT($C62&"!G6")} -> 0 | N62: {=INDIRECT($C62&"!G9")} -> 5588.82 | O62: {=INDIRECT($C62&"!G5")} -> 5588.82 | P62: {=INDIRECT($C62&"!G7")} -> 931.47 | Q62: {=INDIRECT($C62&"!G8")} -> 0 | R62: =IF(ISERROR(J62/G62),0,J62/G62) -> 0.85714286 | S62: =IF(R62>1,R62-1,0) -> 0
C63: =IF(PQ!B68="","",PQ!B68) -> D. | D63: =IF(PQ!C68="","",PQ!C68) -> Implantação de Desvios 2 e 3 | E63: =IF(PQ!E68="","",PQ!E68) | F63: =IF(PQ!F68="","",PQ!F68) | G63: =IF(PQ!G68="","",PQ!G68) | M63: =SUBTOTAL(9,M64:M87) -> 400870.74 | N63: =SUBTOTAL(9,N64:N87) -> -9738.9274 | O63: =SUBTOTAL(9,O64:O87) -> 391131.81 | P63: =SUBTOTAL(9,P64:P87) -> 37971.001 | Q63: =SUBTOTAL(9,Q64:Q87) -> 0
C64: =IF(PQ!B69="","",PQ!B69) -> D.1 | D64: =IF(PQ!C69="","",PQ!C69) -> Terraplenagem | E64: =IF(PQ!E69="","",PQ!E69) | F64: =IF(PQ!F69="","",PQ!F69) | G64: =IF(PQ!G69="","",PQ!G69) | M64: =SUBTOTAL(9,M65:M69) -> 24827.802 | N64: =SUBTOTAL(9,N65:N69) -> -18079.327 | O64: =SUBTOTAL(9,O65:O69) -> 6748.4749 | P64: =SUBTOTAL(9,P65:P69) -> 23363.295 | Q64: =SUBTOTAL(9,Q65:Q69) -> 0
B65: =HYPERLINK("#"&"'"&C65&"'"&"!A1","LINK") -> LINK | C65: =IF(PQ!B70="","",PQ!B70) -> D.1.1 | D65: =IF(PQ!C70="","",PQ!C70) -> Desmatamento, destocamento, limpeza de área e estocagem do material de limpeza com árvores de diâmetro até 0,15 m | E65: =IF(PQ!E70="","",PQ!E70) -> m² | F65: =IF(PQ!F70="","",PQ!F70) -> 0.85999792 | G65: =IF(PQ!G70="","",PQ!G70) -> 2400.25 | H65: {=INDIRECT($C65&"!E6")} -> 1887.389 | I65: {=INDIRECT($C65&"!E9")} -> 0 | J65: {=INDIRECT($C65&"!E5")} -> 1887.389 | K65: {=INDIRECT($C65&"!E7")} -> 512.861 | L65: {=INDIRECT($C65&"!E8")} -> 0 | M65: {=INDIRECT($C65&"!G6")} -> 1623.1506 | N65: {=INDIRECT($C65&"!G9")} -> 0 | O65: {=INDIRECT($C65&"!G5")} -> 1623.1506 | P65: {=INDIRECT($C65&"!G7")} -> 441.05939 | Q65: {=INDIRECT($C65&"!G8")} -> 0 | R65: =IF(ISERROR(J65/G65),0,J65/G65) -> 0.78633017 | S65: =IF(R65>1,R65-1,0) -> 0
B66: =HYPERLINK("#"&"'"&C66&"'"&"!A1","LINK") -> LINK | C66: =IF(PQ!B71="","",PQ!B71) -> D.1.2 | D66: =IF(PQ!C71="","",PQ!C71) -> Transporte com caminhão basculante de 14 m³ - rodovia pavimentada | E66: =IF(PQ!E71="","",PQ!E71) -> T x Km | F66: =IF(PQ!F71="","",PQ!F71) -> 1.5399903 | G66: =IF(PQ!G71="","",PQ!G71) -> 184.67 | H66: {=INDIRECT($C66&"!E6")} -> 184.02043 | I66: {=INDIRECT($C66&"!E9")} -> 0 | J66: {=INDIRECT($C66&"!E5")} -> 184.02043 | K66: {=INDIRECT($C66&"!E7")} -> 0.6495725 | L66: {=INDIRECT($C66&"!E8")} -> 0 | M66: {=INDIRECT($C66&"!G6")} -> 283.38966 | N66: {=INDIRECT($C66&"!G9")} -> 0 | O66: {=INDIRECT($C66&"!G5")} -> 283.38966 | P66: {=INDIRECT($C66&"!G7")} -> 1.0003353 | Q66: {=INDIRECT($C66&"!G8")} -> 0 | R66: =IF(ISERROR(J66/G66),0,J66/G66) -> 0.99648252 | S66: =IF(R66>1,R66-1,0) -> 0
B67: =HYPERLINK("#"&"'"&C67&"'"&"!A1","LINK") -> LINK | C67: =IF(PQ!B72="","",PQ!B72) -> D.1.3 | D67: =IF(PQ!C72="","",PQ!C72) -> Escavação, carga e transporte de material de 1ª categoria - DMT de 1.000 a 1.200 m - com escavadeira e caminhão basculante de 14 m³ | E67: =IF(PQ!E72="","",PQ!E72) -> m³ | F67: =IF(PQ!F72="","",PQ!F72) -> 11.030008 | G67: =IF(PQ!G72="","",PQ!G72) -> 2078.08 | H67: {=INDIRECT($C67&"!E6")} -> 2078.082 | I67: {=INDIRECT($C67&"!E9")} -> -2078.082 | J67: {=INDIRECT($C67&"!E5")} -> 0 | K67: {=INDIRECT($C67&"!E7")} -> 2078.08 | L67: {=INDIRECT($C67&"!E8")} -> 0 | M67: {=INDIRECT($C67&"!G6")} -> 22921.262 | N67: {=INDIRECT($C67&"!G9")} -> -22921.262 | O67: {=INDIRECT($C67&"!G5")} -> 0 | P67: {=INDIRECT($C67&"!G7")} -> 22921.24 | Q67: {=INDIRECT($C67&"!G8")} -> 0 | R67: =IF(ISERROR(J67/G67),0,J67/G67) -> 0 | S67: =IF(R67>1,R67-1,0) -> 0
B68: =HYPERLINK("#"&"'"&C68&"'"&"!A1","LINK") -> LINK | C68: =IF(PQ!B73="","",PQ!B73) -> D.1.4 | D68: =IF(PQ!C73="","",PQ!C73) -> Regularização de bota-fora com espalhamento e execução de hidrossemeadura | E68: =IF(PQ!E73="","",PQ!E73) -> m³ | F68: =IF(PQ!F73="","",PQ!F73) -> 0 | G68: =IF(PQ!G73="","",PQ!G73) -> 0 | H68: {=INDIRECT($C68&"!E6")} -> 0 | I68: {=INDIRECT($C68&"!E9")} -> 0 | J68: {=INDIRECT($C68&"!E5")} -> 0 | K68: {=INDIRECT($C68&"!E7")} -> 0 | L68: {=INDIRECT($C68&"!E8")} -> 0 | M68: {=INDIRECT($C68&"!G6")} -> 0 | N68: {=INDIRECT($C68&"!G9")} -> 0 | O68: {=INDIRECT($C68&"!G5")} -> 0 | P68: {=INDIRECT($C68&"!G7")} -> 0 | Q68: {=INDIRECT($C68&"!G8")} -> 0 | R68: =IF(ISERROR(J68/G68),0,J68/G68) -> 0 | S68: =IF(R68>1,R68-1,0) -> 0
B69: =HYPERLINK("#"&"'"&C69&"'"&"!A1","LINK") -> LINK | C69: =IF(PQ!B74="","",PQ!B74) -> D.1.5 | D69: =IF(PQ!C74="","",PQ!C74) -> Regularização de bota-fora | E69: =IF(PQ!E74="","",PQ!E74) -> m³ | F69: =IF(PQ!F74="","",PQ!F74) -> 2.3300017 | G69: =IF(PQ!G74="","",PQ!G74) -> 2078.08 | H69: {=INDIRECT($C69&"!E6")} -> 0 | I69: {=INDIRECT($C69&"!E9")} -> 2078.082 | J69: {=INDIRECT($C69&"!E5")} -> 2078.082 | K69: {=INDIRECT($C69&"!E7")} -> -0.002 | L69: {=INDIRECT($C69&"!E8")} -> 0 | M69: {=INDIRECT($C69&"!G6")} -> 0 | N69: {=INDIRECT($C69&"!G9")} -> 4841.9347 | O69: {=INDIRECT($C69&"!G5")} -> 4841.9347 | P69: {=INDIRECT($C69&"!G7")} -> -0.0046600035 | Q69: {=INDIRECT($C69&"!G8")} -> 0 | R69: =IF(ISERROR(J69/G69),0,J69/G69) -> 1.000001 | S69: =IF(R69>1,R69-1,0) -> 9.6242686e-07
C70: =IF(PQ!B75="","",PQ!B75) -> D.2 | D70: =IF(PQ!C75="","",PQ!C75) -> Pavimento | E70: =IF(PQ!E75="","",PQ!E75) | F70: =IF(PQ!F75="","",PQ!F75) | G70: =IF(PQ!G75="","",PQ!G75) | M70: =SUBTOTAL(9,M71:M77) -> 215422.95 | N70: =SUBTOTAL(9,N71:N77) -> 0 | O70: =SUBTOTAL(9,O71:O77) -> 215422.95 | P70: =SUBTOTAL(9,P71:P77) -> 0.20445337 | Q70: =SUBTOTAL(9,Q71:Q77) -> 0
B71: =HYPERLINK("#"&"'"&C71&"'"&"!A1","LINK") -> LINK | C71: =IF(PQ!B76="","",PQ!B76) -> D.2.1 | D71: =IF(PQ!C76="","",PQ!C76) -> Fresagem contínua de revestimento betuminoso | E71: =IF(PQ!E76="","",PQ!E76) -> m³ | F71: =IF(PQ!F76="","",PQ!F76) -> 225.86635 | G71: =IF(PQ!G76="","",PQ!G76) -> 38.46 | H71: {=INDIRECT($C71&"!E6")} -> 38.4645 | I71: {=INDIRECT($C71&"!E9")} -> 0 | J71: {=INDIRECT($C71&"!E5")} -> 38.4645 | K71: {=INDIRECT($C71&"!E7")} -> -0.0045 | L71: {=INDIRECT($C71&"!E8")} -> 0 | M71: {=INDIRECT($C71&"!G6")} -> 8687.8364 | N71: {=INDIRECT($C71&"!G9")} -> 0 | O71: {=INDIRECT($C71&"!G5")} -> 8687.8364 | P71: {=INDIRECT($C71&"!G7")} -> -1.0163986 | Q71: {=INDIRECT($C71&"!G8")} -> 0 | R71: =IF(ISERROR(J71/G71),0,J71/G71) -> 1.000117 | S71: =IF(R71>1,R71-1,0) -> 0.00011700468
B72: =HYPERLINK("#"&"'"&C72&"'"&"!A1","LINK") -> LINK | C72: =IF(PQ!B77="","",PQ!B77) -> D.2.2 | D72: =IF(PQ!C77="","",PQ!C77) -> Preparo e melhoramento do subleito | E72: =IF(PQ!E77="","",PQ!E77) -> m² | F72: =IF(PQ!F77="","",PQ!F77) -> 4.2900015 | G72: =IF(PQ!G77="","",PQ!G77) -> 1018.65 | H72: {=INDIRECT($C72&"!E6")} -> 1018.651 | I72: {=INDIRECT($C72&"!E9")} -> 0 | J72: {=INDIRECT($C72&"!E5")} -> 1018.651 | K72: {=INDIRECT($C72&"!E7")} -> -0.001 | L72: {=INDIRECT($C72&"!E8")} -> 0 | M72: {=INDIRECT($C72&"!G6")} -> 4370.0143 | N72: {=INDIRECT($C72&"!G9")} -> 0 | O72: {=INDIRECT($C72&"!G5")} -> 4370.0143 | P72: {=INDIRECT($C72&"!G7")} -> -0.0042900015 | Q72: {=INDIRECT($C72&"!G8")} -> 0 | R72: =IF(ISERROR(J72/G72),0,J72/G72) -> 1.000001 | S72: =IF(R72>1,R72-1,0) -> 9.8169145e-07
B73: =HYPERLINK("#"&"'"&C73&"'"&"!A1","LINK") -> LINK | C73: =IF(PQ!B78="","",PQ!B78) -> D.2.3 | D73: =IF(PQ!C78="","",PQ!C78) -> Rachão ou pedra de mão | E73: =IF(PQ!E78="","",PQ!E78) -> m³ | F73: =IF(PQ!F78="","",PQ!F78) -> 153.91864 | G73: =IF(PQ!G78="","",PQ!G78) -> 509.33 | H73: {=INDIRECT($C73&"!E6")} -> 509.3255 | I73: {=INDIRECT($C73&"!E9")} -> 0 | J73: {=INDIRECT($C73&"!E5")} -> 509.3255 | K73: {=INDIRECT($C73&"!E7")} -> 0.0045 | L73: {=INDIRECT($C73&"!E8")} -> 0 | M73: {=INDIRECT($C73&"!G6")} -> 78394.687 | N73: {=INDIRECT($C73&"!G9")} -> 0 | O73: {=INDIRECT($C73&"!G5")} -> 78394.687 | P73: {=INDIRECT($C73&"!G7")} -> 0.69263387 | Q73: {=INDIRECT($C73&"!G8")} -> 0 | R73: =IF(ISERROR(J73/G73),0,J73/G73) -> 0.99999116 | S73: =IF(R73>1,R73-1,0) -> 0
B74: =HYPERLINK("#"&"'"&C74&"'"&"!A1","LINK") -> LINK | C74: =IF(PQ!B79="","",PQ!B79) -> D.2.4 | D74: =IF(PQ!C79="","",PQ!C79) -> Sub-base ou base de brita graduada simples (BGS) | E74: =IF(PQ!E79="","",PQ!E79) -> m³ | F74: =IF(PQ!F79="","",PQ!F79) -> 173.55019 | G74: =IF(PQ!G79="","",PQ!G79) -> 203.73 | H74: {=INDIRECT($C74&"!E6")} -> 203.7302 | I74: {=INDIRECT($C74&"!E9")} -> 0 | J74: {=INDIRECT($C74&"!E5")} -> 203.7302 | K74: {=INDIRECT($C74&"!E7")} -> -0.0002 | L74: {=INDIRECT($C74&"!E8")} -> 0 | M74: {=INDIRECT($C74&"!G6")} -> 35357.415 | N74: {=INDIRECT($C74&"!G9")} -> 0 | O74: {=INDIRECT($C74&"!G5")} -> 35357.415 | P74: {=INDIRECT($C74&"!G7")} -> -0.034710038 | Q74: {=INDIRECT($C74&"!G8")} -> 0 | R74: =IF(ISERROR(J74/G74),0,J74/G74) -> 1.000001 | S74: =IF(R74>1,R74-1,0) -> 9.8169145e-07
B75: =HYPERLINK("#"&"'"&C75&"'"&"!A1","LINK") -> LINK | C75: =IF(PQ!B80="","",PQ!B80) -> D.2.5 | D75: =IF(PQ!C80="","",PQ!C80) -> Imprimadura betuminosa impermeabilizante | E75: =IF(PQ!E80="","",PQ!E80) -> m² | F75: =IF(PQ!F80="","",PQ!F80) -> 0.87000442 | G75: =IF(PQ!G80="","",PQ!G80) -> 1018.65 | H75: {=INDIRECT($C75&"!E6")} -> 1018.651 | I75: {=INDIRECT($C75&"!E9")} -> 0 | J75: {=INDIRECT($C75&"!E5")} -> 1018.651 | K75: {=INDIRECT($C75&"!E7")} -> -0.001 | L75: {=INDIRECT($C75&"!E8")} -> 0 | M75: {=INDIRECT($C75&"!G6")} -> 886.23087 | N75: {=INDIRECT($C75&"!G9")} -> 0 | O75: {=INDIRECT($C75&"!G5")} -> 886.23087 | P75: {=INDIRECT($C75&"!G7")} -> -0.00087000442 | Q75: {=INDIRECT($C75&"!G8")} -> 0 | R75: =IF(ISERROR(J75/G75),0,J75/G75) -> 1.000001 | S75: =IF(R75>1,R75-1,0) -> 9.8169145e-07
B76: =HYPERLINK("#"&"'"&C76&"'"&"!A1","LINK") -> LINK | C76: =IF(PQ!B81="","",PQ!B81) -> D.2.6 | D76: =IF(PQ!C81="","",PQ!C81) -> Imprimadura betuminosa ligante | E76: =IF(PQ!E81="","",PQ!E81) -> m² | F76: =IF(PQ!F81="","",PQ!F81) -> 0.5299998 | G76: =IF(PQ!G81="","",PQ!G81) -> 3063.02 | H76: {=INDIRECT($C76&"!E6")} -> 3063.024 | I76: {=INDIRECT($C76&"!E9")} -> 0 | J76: {=INDIRECT($C76&"!E5")} -> 3063.024 | K76: {=INDIRECT($C76&"!E7")} -> -0.004 | L76: {=INDIRECT($C76&"!E8")} -> 0 | M76: {=INDIRECT($C76&"!G6")} -> 1623.4021 | N76: {=INDIRECT($C76&"!G9")} -> 0 | O76: {=INDIRECT($C76&"!G5")} -> 1623.4021 | P76: {=INDIRECT($C76&"!G7")} -> -0.0021199992 | Q76: {=INDIRECT($C76&"!G8")} -> 0 | R76: =IF(ISERROR(J76/G76),0,J76/G76) -> 1.0000013 | S76: =IF(R76>1,R76-1,0) -> 1.3059007e-06
B77: =HYPERLINK("#"&"'"&C77&"'"&"!A1","LINK") -> LINK | C77: =IF(PQ!B82="","",PQ!B82) -> D.2.7 | D77: =IF(PQ!C82="","",PQ!C82) -> CBUQ Faixa C/D c/ DOP ou polímero similar | E77: =IF(PQ!E82="","",PQ!E82) -> T | F77: =IF(PQ!F82="","",PQ!F82) -> 308.73796 | G77: =IF(PQ!G82="","",PQ!G82) -> 278.89 | H77: {=INDIRECT($C77&"!E6")} -> 278.88815 | I77: {=INDIRECT($C77&"!E9")} -> 0 | J77: {=INDIRECT($C77&"!E5")} -> 278.88815 | K77: {=INDIRECT($C77&"!E7")} -> 0.0018469 | L77: {=INDIRECT($C77&"!E8")} -> 0 | M77: {=INDIRECT($C77&"!G6")} -> 86103.36 | N77: {=INDIRECT($C77&"!G9")} -> 0 | O77: {=INDIRECT($C77&"!G5")} -> 86103.36 | P77: {=INDIRECT($C77&"!G7")} -> 0.57020814 | Q77: {=INDIRECT($C77&"!G8")} -> 0 | R77: =IF(ISERROR(J77/G77),0,J77/G77) -> 0.99999338 | S77: =IF(R77>1,R77-1,0) -> 0
C78: =IF(PQ!B83="","",PQ!B83) -> D.3 | D78: =IF(PQ!C83="","",PQ!C83) -> Material Betuminoso e Transportes | E78: =IF(PQ!E83="","",PQ!E83) | F78: =IF(PQ!F83="","",PQ!F83) | G78: =IF(PQ!G83="","",PQ!G83) | M78: =SUBTOTAL(9,M79:M84) -> 160619.99 | N78: =SUBTOTAL(9,N79:N84) -> 0 | O78: =SUBTOTAL(9,O79:O84) -> 160619.99 | P78: =SUBTOTAL(9,P79:P84) -> -31.298022 | Q78: =SUBTOTAL(9,Q79:Q84) -> 0
B79: =HYPERLINK("#"&"'"&C79&"'"&"!A1","LINK") -> LINK | C79: =IF(PQ!B84="","",PQ!B84) -> D.3.1 | D79: =IF(PQ!C84="","",PQ!C84) -> Fornecimento de CAP modificado com adição de polímero | E79: =IF(PQ!E84="","",PQ!E84) -> T | F79: =IF(PQ!F84="","",PQ!F84) -> 6078.7588 | G79: =IF(PQ!G84="","",PQ!G84) -> 14.22 | H79: {=INDIRECT($C79&"!E6")} -> 14.223296 | I79: {=INDIRECT($C79&"!E9")} -> 0 | J79: {=INDIRECT($C79&"!E5")} -> 14.223296 | K79: {=INDIRECT($C79&"!E7")} -> -0.0032958081 | L79: {=INDIRECT($C79&"!E8")} -> 0 | M79: {=INDIRECT($C79&"!G6")} -> 86459.984 | N79: {=INDIRECT($C79&"!G9")} -> 0 | O79: {=INDIRECT($C79&"!G5")} -> 86459.984 | P79: {=INDIRECT($C79&"!G7")} -> -20.034422 | Q79: {=INDIRECT($C79&"!G8")} -> 0 | R79: =IF(ISERROR(J79/G79),0,J79/G79) -> 1.0002318 | S79: =IF(R79>1,R79-1,0) -> 0.00023177272
B80: =HYPERLINK("#"&"'"&C80&"'"&"!A1","LINK") -> LINK | C80: =IF(PQ!B85="","",PQ!B85) -> D.3.2 | D80: =IF(PQ!C85="","",PQ!C85) -> Fornecimento de emulsão asfáltica tipo RR-1C | E80: =IF(PQ!E85="","",PQ!E85) -> T | F80: =IF(PQ!F85="","",PQ!F85) -> 3461.6376 | G80: =IF(PQ!G85="","",PQ!G85) -> 1.49 | H80: {=INDIRECT($C80&"!E6")} -> 1.492849 | I80: {=INDIRECT($C80&"!E9")} -> 0 | J80: {=INDIRECT($C80&"!E5")} -> 1.492849 | K80: {=INDIRECT($C80&"!E7")} -> -0.0028490102 | L80: {=INDIRECT($C80&"!E8")} -> 0 | M80: {=INDIRECT($C80&"!G6")} -> 5167.7022 | N80: {=INDIRECT($C80&"!G9")} -> 0 | O80: {=INDIRECT($C80&"!G5")} -> 5167.7022 | P80: {=INDIRECT($C80&"!G7")} -> -9.8622408 | Q80: {=INDIRECT($C80&"!G8")} -> 0 | R80: =IF(ISERROR(J80/G80),0,J80/G80) -> 1.0019121 | S80: =IF(R80>1,R80-1,0) -> 0.0019120874
B81: =HYPERLINK("#"&"'"&C81&"'"&"!A1","LINK") -> LINK | C81: =IF(PQ!B86="","",PQ!B86) -> D.3.3 | D81: =IF(PQ!C86="","",PQ!C86) -> Fornecimento de emulsão asfáltica Imprimer | E81: =IF(PQ!E86="","",PQ!E86) -> T | F81: =IF(PQ!F86="","",PQ!F86) -> 3053.9281 | G81: =IF(PQ!G86="","",PQ!G86) -> 1.39 | H81: {=INDIRECT($C81&"!E6")} -> 1.3904586 | I81: {=INDIRECT($C81&"!E9")} -> 0 | J81: {=INDIRECT($C81&"!E5")} -> 1.3904586 | K81: {=INDIRECT($C81&"!E7")} -> -0.000458615 | L81: {=INDIRECT($C81&"!E8")} -> 0 | M81: {=INDIRECT($C81&"!G6")} -> 4246.3606 | N81: {=INDIRECT($C81&"!G9")} -> 0 | O81: {=INDIRECT($C81&"!G5")} -> 4246.3606 | P81: {=INDIRECT($C81&"!G7")} -> -1.4005772 | Q81: {=INDIRECT($C81&"!G8")} -> 0 | R81: =IF(ISERROR(J81/G81),0,J81/G81) -> 1.0003299 | S81: =IF(R81>1,R81-1,0) -> 0.00032993885
B82: =HYPERLINK("#"&"'"&C82&"'"&"!A1","LINK") -> LINK | C82: =IF(PQ!B87="","",PQ!B87) -> D.3.4 | D82: =IF(PQ!C87="","",PQ!C87) -> Transporte com caminhão basculante de 14 m³ - rodovia pavimentada - Agregados | E82: =IF(PQ!E87="","",PQ!E87) -> T x Km | F82: =IF(PQ!F87="","",PQ!F87) -> 1.0600001 | G82: =IF(PQ!G87="","",PQ!G87) -> 45369.07 | H82: {=INDIRECT($C82&"!E6")} -> 45369.073 | I82: {=INDIRECT($C82&"!E9")} -> 0 | J82: {=INDIRECT($C82&"!E5")} -> 45369.073 | K82: {=INDIRECT($C82&"!E7")} -> -0.0031563751 | L82: {=INDIRECT($C82&"!E8")} -> 0 | M82: {=INDIRECT($C82&"!G6")} -> 48091.223 | N82: {=INDIRECT($C82&"!G9")} -> 0 | O82: {=INDIRECT($C82&"!G5")} -> 48091.223 | P82: {=INDIRECT($C82&"!G7")} -> -0.0033457581 | Q82: {=INDIRECT($C82&"!G8")} -> 0 | R82: =IF(ISERROR(J82/G82),0,J82/G82) -> 1.0000001 | S82: =IF(R82>1,R82-1,0) -> 6.9571079e-08
B83: =HYPERLINK("#"&"'"&C83&"'"&"!A1","LINK") -> LINK | C83: =IF(PQ!B88="","",PQ!B88) -> D.3.5 | D83: =IF(PQ!C88="","",PQ!C88) -> Transporte com caminhão basculante de 14 m³ - rodovia pavimentada - Massa Asfaltica | E83: =IF(PQ!E88="","",PQ!E88) -> T x Km | F83: =IF(PQ!F88="","",PQ!F88) -> 0.78999998 | G83: =IF(PQ!G88="","",PQ!G88) -> 17044.76 | H83: {=INDIRECT($C83&"!E6")} -> 17044.758 | I83: {=INDIRECT($C83&"!E9")} -> 0 | J83: {=INDIRECT($C83&"!E5")} -> 17044.758 | K83: {=INDIRECT($C83&"!E7")} -> 0.00165668 | L83: {=INDIRECT($C83&"!E8")} -> 0 | M83: {=INDIRECT($C83&"!G6")} -> 13465.359 | N83: {=INDIRECT($C83&"!G9")} -> 0 | O83: {=INDIRECT($C83&"!G5")} -> 13465.359 | P83: {=INDIRECT($C83&"!G7")} -> 0.0013087772 | Q83: {=INDIRECT($C83&"!G8")} -> 0 | R83: =IF(ISERROR(J83/G83),0,J83/G83) -> 0.9999999 | S83: =IF(R83>1,R83-1,0) -> 0
B84: =HYPERLINK("#"&"'"&C84&"'"&"!A1","LINK") -> LINK | C84: =IF(PQ!B89="","",PQ!B89) -> D.3.6 | D84: =IF(PQ!C89="","",PQ!C89) -> Transporte com caminhão basculante de 14 m³ - rodovia pavimentada - Materiais Betuminosos | E84: =IF(PQ!E89="","",PQ!E89) -> T x Km | F84: =IF(PQ!F89="","",PQ!F89) -> 0.79000089 | G84: =IF(PQ!G89="","",PQ!G89) -> 4037.16 | H84: {=INDIRECT($C84&"!E6")} -> 4037.1584 | I84: {=INDIRECT($C84&"!E9")} -> 0 | J84: {=INDIRECT($C84&"!E5")} -> 4037.1584 | K84: {=INDIRECT($C84&"!E7")} -> 0.0015897435 | L84: {=INDIRECT($C84&"!E8")} -> 0 | M84: {=INDIRECT($C84&"!G6")} -> 3189.3587 | N84: {=INDIRECT($C84&"!G9")} -> 0 | O84: {=INDIRECT($C84&"!G5")} -> 3189.3587 | P84: {=INDIRECT($C84&"!G7")} -> 0.0012558988 | Q84: {=INDIRECT($C84&"!G8")} -> 0 | R84: =IF(ISERROR(J84/G84),0,J84/G84) -> 0.99999961 | S84: =IF(R84>1,R84-1,0) -> 0
C85: =IF(PQ!B90="","",PQ!B90) -> D.4 | D85: =IF(PQ!C90="","",PQ!C90) -> Drenagem e OACs | E85: =IF(PQ!E90="","",PQ!E90) | F85: =IF(PQ!F90="","",PQ!F90) | G85: =IF(PQ!G90="","",PQ!G90) | M85: =SUBTOTAL(9,M86:M87) -> 0 | N85: =SUBTOTAL(9,N86:N87) -> 8340.4 | O85: =SUBTOTAL(9,O86:O87) -> 8340.4 | P85: =SUBTOTAL(9,P86:P87) -> 14638.8 | Q85: =SUBTOTAL(9,Q86:Q87) -> 0
B86: =HYPERLINK("#"&"'"&C86&"'"&"!A1","LINK") -> LINK | C86: =IF(PQ!B91="","",PQ!B91) -> D.4.1 | D86: =IF(PQ!C91="","",PQ!C91) -> Sarjeta triangular de concreto - STC 88-20 - escavação mecânica - areia e brita comerciais | E86: =IF(PQ!E91="","",PQ!E91) -> m | F86: =IF(PQ!F91="","",PQ!F91) -> 58 | G86: =IF(PQ!G91="","",PQ!G91) -> 313.5 | H86: {=INDIRECT($C86&"!E6")} -> 0 | I86: {=INDIRECT($C86&"!E9")} -> 143.8 | J86: {=INDIRECT($C86&"!E5")} -> 143.8 | K86: {=INDIRECT($C86&"!E7")} -> 169.7 | L86: {=INDIRECT($C86&"!E8")} -> 0 | M86: {=INDIRECT($C86&"!G6")} -> 0 | N86: {=INDIRECT($C86&"!G9")} -> 8340.4 | O86: {=INDIRECT($C86&"!G5")} -> 8340.4 | P86: {=INDIRECT($C86&"!G7")} -> 9842.6 | Q86: {=INDIRECT($C86&"!G8")} -> 0 | R86: =IF(ISERROR(J86/G86),0,J86/G86) -> 0.45869219 | S86: =IF(R86>1,R86-1,0) -> 0
B87: =HYPERLINK("#"&"'"&C87&"'"&"!A1","LINK") -> LINK | C87: =IF(PQ!B92="","",PQ!B92) -> D.4.2 | D87: =IF(PQ!C92="","",PQ!C92) -> Dissipador de energia - DES 88-264 - areia, brita e pedra de mão comerciais | E87: =IF(PQ!E92="","",PQ!E92) -> und. | F87: =IF(PQ!F92="","",PQ!F92) -> 959.24 | G87: =IF(PQ!G92="","",PQ!G92) -> 5 | H87: {=INDIRECT($C87&"!E6")} -> 0 | I87: {=INDIRECT($C87&"!E9")} -> 0 | J87: {=INDIRECT($C87&"!E5")} -> 0 | K87: {=INDIRECT($C87&"!E7")} -> 5 | L87: {=INDIRECT($C87&"!E8")} -> 0 | M87: {=INDIRECT($C87&"!G6")} -> 0 | N87: {=INDIRECT($C87&"!G9")} -> 0 | O87: {=INDIRECT($C87&"!G5")} -> 0 | P87: {=INDIRECT($C87&"!G7")} -> 4796.2 | Q87: {=INDIRECT($C87&"!G8")} -> 0 | R87: =IF(ISERROR(J87/G87),0,J87/G87) -> 0 | S87: =IF(R87>1,R87-1,0) -> 0
C88: =IF(PQ!B93="","",PQ!B93) -> E. | D88: =IF(PQ!C93="","",PQ!C93) -> Sinalização Horizontal, Vertical e Elementos de Proteção e Segurança | E88: =IF(PQ!E93="","",PQ!E93) | F88: =IF(PQ!F93="","",PQ!F93) | G88: =IF(PQ!G93="","",PQ!G93) | M88: =SUBTOTAL(9,M89) -> 19282.616 | N88: =SUBTOTAL(9,N89) -> 0 | O88: =SUBTOTAL(9,O89) -> 19282.616 | P88: =SUBTOTAL(9,P89) -> 119708.45 | Q88: =SUBTOTAL(9,Q89) -> 0
B89: =HYPERLINK("#"&"'"&C89&"'"&"!A1","LINK") -> LINK | C89: =IF(PQ!B94="","",PQ!B94) -> E.1 | D89: =IF(PQ!C94="","",PQ!C94) -> Manutenção/recomposição de sinalização - pintura de faixa com tinta acrílica emulsionada em água - espessura de 0,3 / 0,5 mm | E89: =IF(PQ!E94="","",PQ!E94) -> m² | F89: =IF(PQ!F94="","",PQ!F94) -> 47.689999 | G89: =IF(PQ!G94="","",PQ!G94) -> 2914.47 | H89: {=INDIRECT($C89&"!E6")} -> 404.3325 | I89: {=INDIRECT($C89&"!E9")} -> 0 | J89: {=INDIRECT($C89&"!E5")} -> 404.3325 | K89: {=INDIRECT($C89&"!E7")} -> 2510.1375 | L89: {=INDIRECT($C89&"!E8")} -> 0 | M89: {=INDIRECT($C89&"!G6")} -> 19282.616 | N89: {=INDIRECT($C89&"!G9")} -> 0 | O89: {=INDIRECT($C89&"!G5")} -> 19282.616 | P89: {=INDIRECT($C89&"!G7")} -> 119708.45 | Q89: {=INDIRECT($C89&"!G8")} -> 0 | R89: =IF(ISERROR(J89/G89),0,J89/G89) -> 0.13873277 | S89: =IF(R89>1,R89-1,0) -> 0
C90: =IF(PQ!B95="","",PQ!B95) -> F. | D90: =IF(PQ!C95="","",PQ!C95) -> Mão de Obra e Equipamentos | E90: =IF(PQ!E95="","",PQ!E95) | F90: =IF(PQ!F95="","",PQ!F95) | G90: =IF(PQ!G95="","",PQ!G95) | M90: =SUBTOTAL(9,M91:M100) -> 0 | N90: =SUBTOTAL(9,N91:N100) -> 102841.21 | O90: =SUBTOTAL(9,O91:O100) -> 102841.21 | P90: =SUBTOTAL(9,P91:P100) -> 126251.23 | Q90: =SUBTOTAL(9,Q91:Q100) -> 45730.191
C91: =IF(PQ!B96="","",PQ!B96) -> F.1 | D91: =IF(PQ!C96="","",PQ!C96) -> Mão de Obra | E91: =IF(PQ!E96="","",PQ!E96) | F91: =IF(PQ!F96="","",PQ!F96) | G91: =IF(PQ!G96="","",PQ!G96) | M91: =SUBTOTAL(9,M92:M94) -> 0 | N91: =SUBTOTAL(9,N92:N94) -> 12969.48 | O91: =SUBTOTAL(9,O92:O94) -> 12969.48 | P91: =SUBTOTAL(9,P92:P94) -> 6484.74 | Q91: =SUBTOTAL(9,Q92:Q94) -> 6484.74
B92: =HYPERLINK("#"&"'"&C92&"'"&"!A1","LINK") -> LINK | C92: =IF(PQ!B97="","",PQ!B97) -> F.1.1 | D92: =IF(PQ!C97="","",PQ!C97) -> Encarregado | E92: =IF(PQ!E97="","",PQ!E97) -> h | F92: =IF(PQ!F97="","",PQ!F97) -> 70.817037 | G92: =IF(PQ!G97="","",PQ!G97) -> 54 | H92: {=INDIRECT($C92&"!E6")} -> 0 | I92: {=INDIRECT($C92&"!E9")} -> 36 | J92: {=INDIRECT($C92&"!E5")} -> 36 | K92: {=INDIRECT($C92&"!E7")} -> 18 | L92: {=INDIRECT($C92&"!E8")} -> 18 | M92: {=INDIRECT($C92&"!G6")} -> 0 | N92: {=INDIRECT($C92&"!G9")} -> 2549.4133 | O92: {=INDIRECT($C92&"!G5")} -> 2549.4133 | P92: {=INDIRECT($C92&"!G7")} -> 1274.7067 | Q92: {=INDIRECT($C92&"!G8")} -> 1274.7067 | R92: =IF(ISERROR(J92/G92),0,J92/G92) -> 0.66666667 | S92: =IF(R92>1,R92-1,0) -> 0
B93: =HYPERLINK("#"&"'"&C93&"'"&"!A1","LINK") -> LINK | C93: =IF(PQ!B98="","",PQ!B98) -> F.1.2 | D93: =IF(PQ!C98="","",PQ!C98) -> Oficial | E93: =IF(PQ!E98="","",PQ!E98) -> h | F93: =IF(PQ!F98="","",PQ!F98) -> 40.88321 | G93: =IF(PQ!G98="","",PQ!G98) -> 162 | H93: {=INDIRECT($C93&"!E6")} -> 0 | I93: {=INDIRECT($C93&"!E9")} -> 108 | J93: {=INDIRECT($C93&"!E5")} -> 108 | K93: {=INDIRECT($C93&"!E7")} -> 54 | L93: {=INDIRECT($C93&"!E8")} -> 54 | M93: {=INDIRECT($C93&"!G6")} -> 0 | N93: {=INDIRECT($C93&"!G9")} -> 4415.3867 | O93: {=INDIRECT($C93&"!G5")} -> 4415.3867 | P93: {=INDIRECT($C93&"!G7")} -> 2207.6933 | Q93: {=INDIRECT($C93&"!G8")} -> 2207.6933 | R93: =IF(ISERROR(J93/G93),0,J93/G93) -> 0.66666667 | S93: =IF(R93>1,R93-1,0) -> 0
B94: =HYPERLINK("#"&"'"&C94&"'"&"!A1","LINK") -> LINK | C94: =IF(PQ!B99="","",PQ!B99) -> F.1.3 | D94: =IF(PQ!C99="","",PQ!C99) -> Servente | E94: =IF(PQ!E99="","",PQ!E99) -> h | F94: =IF(PQ!F99="","",PQ!F99) -> 33.359333 | G94: =IF(PQ!G99="","",PQ!G99) -> 270 | H94: {=INDIRECT($C94&"!E6")} -> 0 | I94: {=INDIRECT($C94&"!E9")} -> 180 | J94: {=INDIRECT($C94&"!E5")} -> 180 | K94: {=INDIRECT($C94&"!E7")} -> 90 | L94: {=INDIRECT($C94&"!E8")} -> 90 | M94: {=INDIRECT($C94&"!G6")} -> 0 | N94: {=INDIRECT($C94&"!G9")} -> 6004.68 | O94: {=INDIRECT($C94&"!G5")} -> 6004.68 | P94: {=INDIRECT($C94&"!G7")} -> 3002.34 | Q94: {=INDIRECT($C94&"!G8")} -> 3002.34 | R94: =IF(ISERROR(J94/G94),0,J94/G94) -> 0.66666667 | S94: =IF(R94>1,R94-1,0) -> 0
C95: =IF(PQ!B100="","",PQ!B100) -> F.2 | D95: =IF(PQ!C100="","",PQ!C100) -> Equipamentos | E95: =IF(PQ!E100="","",PQ!E100) | F95: =IF(PQ!F100="","",PQ!F100) | G95: =IF(PQ!G100="","",PQ!G100) | M95: =SUBTOTAL(9,M96:M100) -> 0 | N95: =SUBTOTAL(9,N96:N100) -> 89871.725 | O95: =SUBTOTAL(9,O96:O100) -> 89871.725 | P95: =SUBTOTAL(9,P96:P100) -> 119766.49 | Q95: =SUBTOTAL(9,Q96:Q100) -> 39245.451
B96: =HYPERLINK("#"&"'"&C96&"'"&"!A1","LINK") -> LINK | C96: =IF(PQ!B101="","",PQ!B101) -> F.2.1 | D96: =IF(PQ!C101="","",PQ!C101) -> Trator sobre Esteiras com Lâmina - 127 Kw | E96: =IF(PQ!E101="","",PQ!E101) -> h | F96: =IF(PQ!F101="","",PQ!F101) -> 272.35346 | G96: =IF(PQ!G101="","",PQ!G101) -> 81 | H96: {=INDIRECT($C96&"!E6")} -> 0 | I96: {=INDIRECT($C96&"!E9")} -> 21.705353 | J96: {=INDIRECT($C96&"!E5")} -> 21.705353 | K96: {=INDIRECT($C96&"!E7")} -> 59.294647 | L96: {=INDIRECT($C96&"!E8")} -> 6.2015296 | M96: {=INDIRECT($C96&"!G6")} -> 0 | N96: {=INDIRECT($C96&"!G9")} -> 5911.528 | O96: {=INDIRECT($C96&"!G5")} -> 5911.528 | P96: {=INDIRECT($C96&"!G7")} -> 16149.102 | Q96: {=INDIRECT($C96&"!G8")} -> 1689.008 | R96: =IF(ISERROR(J96/G96),0,J96/G96) -> 0.26796733 | S96: =IF(R96>1,R96-1,0) -> 0
B97: =HYPERLINK("#"&"'"&C97&"'"&"!A1","LINK") -> LINK | C97: =IF(PQ!B102="","",PQ!B102) -> F.2.2 | D97: =IF(PQ!C102="","",PQ!C102) -> Escavadeira Hidráulica sobre Esteiras | E97: =IF(PQ!E102="","",PQ!E102) -> h | F97: =IF(PQ!F102="","",PQ!F102) -> 282.33581 | G97: =IF(PQ!G102="","",PQ!G102) -> 117 | H97: {=INDIRECT($C97&"!E6")} -> 0 | I97: {=INDIRECT($C97&"!E9")} -> 38.82224 | J97: {=INDIRECT($C97&"!E5")} -> 38.82224 | K97: {=INDIRECT($C97&"!E7")} -> 78.17776 | L97: {=INDIRECT($C97&"!E8")} -> 17.254329 | M97: {=INDIRECT($C97&"!G6")} -> 0 | N97: {=INDIRECT($C97&"!G9")} -> 10960.909 | O97: {=INDIRECT($C97&"!G5")} -> 10960.909 | P97: {=INDIRECT($C97&"!G7")} -> 22072.381 | Q97: {=INDIRECT($C97&"!G8")} -> 4871.5149 | R97: =IF(ISERROR(J97/G97),0,J97/G97) -> 0.33181401 | S97: =IF(R97>1,R97-1,0) -> 0
B98: =HYPERLINK("#"&"'"&C98&"'"&"!A1","LINK") -> LINK | C98: =IF(PQ!B103="","",PQ!B103) -> F.2.3 | D98: =IF(PQ!C103="","",PQ!C103) -> Caminhão Basculante com Capacidade de 16 M³ - 188 Kw | E98: =IF(PQ!E103="","",PQ!E103) -> h | F98: =IF(PQ!F103="","",PQ!F103) -> 230.76026 | G98: =IF(PQ!G103="","",PQ!G103) -> 540 | H98: {=INDIRECT($C98&"!E6")} -> 0 | I98: {=INDIRECT($C98&"!E9")} -> 257.52762 | J98: {=INDIRECT($C98&"!E5")} -> 257.52762 | K98: {=INDIRECT($C98&"!E7")} -> 282.47238 | L98: {=INDIRECT($C98&"!E8")} -> 128.76381 | M98: {=INDIRECT($C98&"!G6")} -> 0 | N98: {=INDIRECT($C98&"!G9")} -> 59427.141 | O98: {=INDIRECT($C98&"!G5")} -> 59427.141 | P98: {=INDIRECT($C98&"!G7")} -> 65183.399 | Q98: {=INDIRECT($C98&"!G8")} -> 29713.571 | R98: =IF(ISERROR(J98/G98),0,J98/G98) -> 0.47690301 | S98: =IF(R98>1,R98-1,0) -> 0
B99: =HYPERLINK("#"&"'"&C99&"'"&"!A1","LINK") -> LINK | C99: =IF(PQ!B104="","",PQ!B104) -> F.2.4 | D99: =IF(PQ!C104="","",PQ!C104) -> Rolo Compactador Pé de Carneiro Vibratório Autopropelido por Pneus de 11,6 T - 82 Kw | E99: =IF(PQ!E104="","",PQ!E104) -> h | F99: =IF(PQ!F104="","",PQ!F104) -> 225.93852 | G99: =IF(PQ!G104="","",PQ!G104) -> 81 | H99: {=INDIRECT($C99&"!E6")} -> 0 | I99: {=INDIRECT($C99&"!E9")} -> 46.029114 | J99: {=INDIRECT($C99&"!E5")} -> 46.029114 | K99: {=INDIRECT($C99&"!E7")} -> 34.970886 | L99: {=INDIRECT($C99&"!E8")} -> 13.151175 | M99: {=INDIRECT($C99&"!G6")} -> 0 | N99: {=INDIRECT($C99&"!G9")} -> 10399.75 | O99: {=INDIRECT($C99&"!G5")} -> 10399.75 | P99: {=INDIRECT($C99&"!G7")} -> 7901.2703 | Q99: {=INDIRECT($C99&"!G8")} -> 2971.3571 | R99: =IF(ISERROR(J99/G99),0,J99/G99) -> 0.56826066 | S99: =IF(R99>1,R99-1,0) -> 0
B100: =HYPERLINK("#"&"'"&C100&"'"&"!A1","LINK") -> LINK | C100: =IF(PQ!B105="","",PQ!B105) -> F.2.5 | D100: =IF(PQ!C105="","",PQ!C105) -> Motoniveladora - 93 Kw | E100: =IF(PQ!E105="","",PQ!E105) -> h | F100: =IF(PQ!F105="","",PQ!F105) -> 430.84222 | G100: =IF(PQ!G105="","",PQ!G105) -> 27 | H100: {=INDIRECT($C100&"!E6")} -> 0 | I100: {=INDIRECT($C100&"!E9")} -> 7.3632469 | J100: {=INDIRECT($C100&"!E5")} -> 7.3632469 | K100: {=INDIRECT($C100&"!E7")} -> 19.636753 | L100: {=INDIRECT($C100&"!E8")} -> 0 | M100: {=INDIRECT($C100&"!G6")} -> 0 | N100: {=INDIRECT($C100&"!G9")} -> 3172.3977 | O100: {=INDIRECT($C100&"!G5")} -> 3172.3977 | P100: {=INDIRECT($C100&"!G7")} -> 8460.3423 | Q100: {=INDIRECT($C100&"!G8")} -> 0 | R100: =IF(ISERROR(J100/G100),0,J100/G100) -> 0.27271285 | S100: =IF(R100>1,R100-1,0) -> 0

Sheet MUNICIPIOS
A1: RECOMPOSIÇÃO DE TALUDES - SINISTRO 297+500 - OESTE - RATEIO ISS
A2: CÓDIGO | B2: DESCRIÇÃO | C2: 24/09/2025 a 23/10/2025 | D2: GOVERNADOR VALADARES | F2: PERIQUITO | H2: NAQUE | J2: BELO HORIENTE | L2: SANTANA DO PARAÍSO | N2: IPATINGA | P2: CORONEL FABRICIANO | R2: TIMÓTEO | T2: JAGUARAÇU | V2: ANTÔNIO DIAS | X2: NOVA ERA | Z2: BELA VISTA DE MINAS | AB2: JOÃO MONLEVADE | AD2: SÃO GONÇALO DO RIO ABAIXO | AF2: BARÃO DE COCAIS | AH2: BOM JESUS DO AMPARO | AJ2: NOVA UNIÃO | AL2: CAETÉ | AN2: ACUMULADO
C4: Nº MEDIÇÃO 03 | D4: % | E4: R$ | F4: % | G4: R$ | H4: % | I4: R$ | J4: % | K4: R$ | L4: % | M4: R$ | N4: % | O4: R$ | P4: % | Q4: R$ | R4: % | S4: R$ | T4: % | U4: R$ | V4: % | W4: R$ | X4: % | Y4: R$ | Z4: % | AA4: R$ | AB4: % | AC4: R$ | AD4: % | AE4: R$ | AF4: % | AG4: R$ | AH4: % | AI4: R$ | AJ4: % | AK4: R$ | AL4: % | AM4: R$ | AN4: % | AO4: R$
A6: =PQ!B13 -> A. | B6: =PQ!C13 -> Custos Indiretos | C6: =RESUMO!N8 -> 0 | E6: =SUBTOTAL(9,E7:E9) -> 0 | G6: =SUBTOTAL(9,G7:G9) -> 0 | I6: =SUBTOTAL(9,I7:I9) -> 0 | K6: =SUBTOTAL(9,K7:K9) -> 0 | M6: =SUBTOTAL(9,M7:M9) -> 0 | O6: =SUBTOTAL(9,O7:O9) -> 0 | Q6: =SUBTOTAL(9,Q7:Q9) -> 0 | S6: =SUBTOTAL(9,S7:S9) -> 0 | U6: =SUBTOTAL(9,U7:U9) -> 0 | W6: =SUBTOTAL(9,W7:W9) -> 0 | Y6: =SUBTOTAL(9,Y7:Y9) -> 0 | AA6: =SUBTOTAL(9,AA7:AA9) -> 0 | AC6: =SUBTOTAL(9,AC7:AC9) -> 0 | AE6: =SUBTOTAL(9,AE7:AE9) -> 0 | AG6: =SUBTOTAL(9,AG7:AG9) -> 0 | AI6: =SUBTOTAL(9,AI7:AI9) -> 0 | AK6: =SUBTOTAL(9,AK7:AK9) -> 0 | AM6: =SUBTOTAL(9,AM7:AM9) -> 0 | AO6: =SUBTOTAL(9,AO7:AO9) -> 0
A7: =PQ!B14 -> A.1 | B7: =PQ!C14 -> Mobilização e desmobilização | C7: =RESUMO!N9 -> 0 | E7: =$C7*D7 -> 0 | G7: =$C7*F7 -> 0 | I7: =$C7*H7 -> 0 | K7: =$C7*J7 -> 0 | M7: =$C7*L7 -> 0 | O7: =$C7*N7 -> 0 | Q7: =$C7*P7 -> 0 | S7: =$C7*R7 -> 0 | U7: =$C7*T7 -> 0 | W7: =$C7*V7 -> 0 | Y7: =$C7*X7 -> 0 | AA7: =$C7*Z7 -> 0 | AC7: =$C7*AB7 -> 0 | AE7: =$C7*AD7 -> 0 | AG7: =$C7*AF7 -> 0 | AI7: =$C7*AH7 -> 0 | AK7: =$C7*AJ7 -> 0 | AM7: =$C7*AL7 -> 0 | AN7: =SUM(D7,F7,H7,J7,L7,N7,P7,R7,T7,V7,X7,Z7,AB7,AD7,AF7,AH7,AJ7,AL7) -> 0 | AO7: =$C7*AN7 -> 0
A8: =PQ!B15 -> A.2 | B8: =PQ!C15 -> Sinalização e desvio de tráfego | C8: =RESUMO!N10 -> 0 | E8: =$C8*D8 -> 0 | G8: =$C8*F8 -> 0 | I8: =$C8*H8 -> 0 | K8: =$C8*J8 -> 0 | M8: =$C8*L8 -> 0 | O8: =$C8*N8 -> 0 | Q8: =$C8*P8 -> 0 | S8: =$C8*R8 -> 0 | U8: =$C8*T8 -> 0 | W8: =$C8*V8 -> 0 | Y8: =$C8*X8 -> 0 | AA8: =$C8*Z8 -> 0 | AC8: =$C8*AB8 -> 0 | AE8: =$C8*AD8 -> 0 | AG8: =$C8*AF8 -> 0 | AI8: =$C8*AH8 -> 0 | AK8: =$C8*AJ8 -> 0 | AM8: =$C8*AL8 -> 0 | AN8: =SUM(D8,F8,H8,J8,L8,N8,P8,R8,T8,V8,X8,Z8,AB8,AD8,AF8,AH8,AJ8,AL8) -> 0 | AO8: =$C8*AN8 -> 0
A9: =PQ!B16 -> A.3 | B9: =PQ!C16 -> Administração local | C9: =RESUMO!N11 -> 0 | E9: =$C9*D9 -> 0 | G9: =$C9*F9 -> 0 | I9: =$C9*H9 -> 0 | K9: =$C9*J9 -> 0 | M9: =$C9*L9 -> 0 | O9: =$C9*N9 -> 0 | Q9: =$C9*P9 -> 0 | S9: =$C9*R9 -> 0 | U9: =$C9*T9 -> 0 | W9: =$C9*V9 -> 0 | Y9: =$C9*X9 -> 0 | AA9: =$C9*Z9 -> 0 | AC9: =$C9*AB9 -> 0 | AE9: =$C9*AD9 -> 0 | AG9: =$C9*AF9 -> 0 | AI9: =$C9*AH9 -> 0 | AK9: =$C9*AJ9 -> 0 | AM9: =$C9*AL9 -> 0 | AN9: =SUM(D9,F9,H9,J9,L9,N9,P9,R9,T9,V9,X9,Z9,AB9,AD9,AF9,AH9,AJ9,AL9) -> 0 | AO9: =$C9*AN9 -> 0
A10: =PQ!B17 -> B. | B10: =PQ!C17 -> Estabilização de Talude | C10: =RESUMO!N12 -> 1870605.8 | E10: =SUBTOTAL(9,E11:E33) -> 0 | G10: =SUBTOTAL(9,G11:G33) -> 0 | I10: =SUBTOTAL(9,I11:I33) -> 0 | K10: =SUBTOTAL(9,K11:K33) -> 0 | M10: =SUBTOTAL(9,M11:M33) -> 0 | O10: =SUBTOTAL(9,O11:O33) -> 0 | Q10: =SUBTOTAL(9,Q11:Q33) -> 0 | S10: =SUBTOTAL(9,S11:S33) -> 0 | U10: =SUBTOTAL(9,U11:U33) -> 0 | W10: =SUBTOTAL(9,W11:W33) -> 1870605.8 | Y10: =SUBTOTAL(9,Y11:Y33) -> 0 | AA10: =SUBTOTAL(9,AA11:AA33) -> 0 | AC10: =SUBTOTAL(9,AC11:AC33) -> 0 | AE10: =SUBTOTAL(9,AE11:AE33) -> 0 | AG10: =SUBTOTAL(9,AG11:AG33) -> 0 | AI10: =SUBTOTAL(9,AI11:AI33) -> 0 | AK10: =SUBTOTAL(9,AK11:AK33) -> 0 | AM10: =SUBTOTAL(9,AM11:AM33) -> 0 | AO10: =SUBTOTAL(9,AO11:AO33) -> 1870605.8
A11: =PQ!B18 -> B.1 | B11: =PQ!C18 -> Terraplenagem | C11: =RESUMO!N13 -> 877293.31 | E11: =SUBTOTAL(9,E12:E20) -> 0 | G11: =SUBTOTAL(9,G12:G20) -> 0 | I11: =SUBTOTAL(9,I12:I20) -> 0 | K11: =SUBTOTAL(9,K12:K20) -> 0 | M11: =SUBTOTAL(9,M12:M20) -> 0 | O11: =SUBTOTAL(9,O12:O20) -> 0 | Q11: =SUBTOTAL(9,Q12:Q20) -> 0 | S11: =SUBTOTAL(9,S12:S20) -> 0 | U11: =SUBTOTAL(9,U12:U20) -> 0 | W11: =SUBTOTAL(9,W12:W20) -> 877293.31 | Y11: =SUBTOTAL(9,Y12:Y20) -> 0 | AA11: =SUBTOTAL(9,AA12:AA20) -> 0 | AC11: =SUBTOTAL(9,AC12:AC20) -> 0 | AE11: =SUBTOTAL(9,AE12:AE20) -> 0 | AG11: =SUBTOTAL(9,AG12:AG20) -> 0 | AI11: =SUBTOTAL(9,AI12:AI20) -> 0 | AK11: =SUBTOTAL(9,AK12:AK20) -> 0 | AM11: =SUBTOTAL(9,AM12:AM20) -> 0 | AO11: =SUBTOTAL(9,AO12:AO20) -> 877293.31
A12: =PQ!B19 -> B.1.1 | B12: =PQ!C19 -> Escavação, carga e transporte de material de 1ª categoria - DMT de 800 a 1.000 m - caminho de serviço pavimentado - com escavadeira e caminhão basculante de 14 m³ | C12: =RESUMO!N14 -> 0 | E12: =$C12*D12 -> 0 | G12: =$C12*F12 -> 0 | I12: =$C12*H12 -> 0 | K12: =$C12*J12 -> 0 | M12: =$C12*L12 -> 0 | O12: =$C12*N12 -> 0 | Q12: =$C12*P12 -> 0 | S12: =$C12*R12 -> 0 | U12: =$C12*T12 -> 0 | W12: =$C12*V12 -> 0 | Y12: =$C12*X12 -> 0 | AA12: =$C12*Z12 -> 0 | AC12: =$C12*AB12 -> 0 | AE12: =$C12*AD12 -> 0 | AG12: =$C12*AF12 -> 0 | AI12: =$C12*AH12 -> 0 | AK12: =$C12*AJ12 -> 0 | AM12: =$C12*AL12 -> 0 | AN12: =SUM(D12,F12,H12,J12,L12,N12,P12,R12,T12,V12,X12,Z12,AB12,AD12,AF12,AH12,AJ12,AL12) -> 0 | AO12: =$C12*AN12 -> 0
A13: =PQ!B20 -> B.1.2 | B13: =PQ!C20 -> Escavação e carga de material de 1ª categoria - DMT acima de 3.000 m | C13: =RESUMO!N15 -> 97492.676 | E13: =$C13*D13 -> 0 | G13: =$C13*F13 -> 0 | I13: =$C13*H13 -> 0 | K13: =$C13*J13 -> 0 | M13: =$C13*L13 -> 0 | O13: =$C13*N13 -> 0 | Q13: =$C13*P13 -> 0 | S13: =$C13*R13 -> 0 | U13: =$C13*T13 -> 0 | V13: 1 | W13: =$C13*V13 -> 97492.676 | Y13: =$C13*X13 -> 0 | AA13: =$C13*Z13 -> 0 | AC13: =$C13*AB13 -> 0 | AE13: =$C13*AD13 -> 0 | AG13: =$C13*AF13 -> 0 | AI13: =$C13*AH13 -> 0 | AK13: =$C13*AJ13 -> 0 | AM13: =$C13*AL13 -> 0 | AN13: =SUM(D13,F13,H13,J13,L13,N13,P13,R13,T13,V13,X13,Z13,AB13,AD13,AF13,AH13,AJ13,AL13) -> 1 | AO13: =$C13*AN13 -> 97492.676
A14: =PQ!B21 -> B.1.3 | B14: =PQ!C21 -> Transporte com caminhão basculante de 10 m³ - rodovia pavimentada (DMT 5 Km) | C14: =RESUMO!N16 -> 48774.217 | E14: =$C14*D14 -> 0 | G14: =$C14*F14 -> 0 | I14: =$C14*H14 -> 0 | K14: =$C14*J14 -> 0 | M14: =$C14*L14 -> 0 | O14: =$C14*N14 -> 0 | Q14: =$C14*P14 -> 0 | S14: =$C14*R14 -> 0 | U14: =$C14*T14 -> 0 | V14: 1 | W14: =$C14*V14 -> 48774.217 | Y14: =$C14*X14 -> 0 | AA14: =$C14*Z14 -> 0 | AC14: =$C14*AB14 -> 0 | AE14: =$C14*AD14 -> 0 | AG14: =$C14*AF14 -> 0 | AI14: =$C14*AH14 -> 0 | AK14: =$C14*AJ14 -> 0 | AM14: =$C14*AL14 -> 0 | AN14: =SUM(D14,F14,H14,J14,L14,N14,P14,R14,T14,V14,X14,Z14,AB14,AD14,AF14,AH14,AJ14,AL14) -> 1 | AO14: =$C14*AN14 -> 48774.217
A15: =PQ!B22 -> B.1.4 | B15: =PQ!C22 -> Regularização de bota-fora com espalhamento e execução de hidrossemeadura | C15: =RESUMO!N17 -> 0 | E15: =$C15*D15 -> 0 | G15: =$C15*F15 -> 0 | I15: =$C15*H15 -> 0 | K15: =$C15*J15 -> 0 | M15: =$C15*L15 -> 0 | O15: =$C15*N15 -> 0 | Q15: =$C15*P15 -> 0 | S15: =$C15*R15 -> 0 | U15: =$C15*T15 -> 0 | W15: =$C15*V15 -> 0 | Y15: =$C15*X15 -> 0 | AA15: =$C15*Z15 -> 0 | AC15: =$C15*AB15 -> 0 | AE15: =$C15*AD15 -> 0 | AG15: =$C15*AF15 -> 0 | AI15: =$C15*AH15 -> 0 | AK15: =$C15*AJ15 -> 0 | AM15: =$C15*AL15 -> 0 | AN15: =SUM(D15,F15,H15,J15,L15,N15,P15,R15,T15,V15,X15,Z15,AB15,AD15,AF15,AH15,AJ15,AL15) -> 0 | AO15: =$C15*AN15 -> 0
A16: =PQ!B23 -> B.1.5 | B16: =PQ!C23 -> Royaltie de bota-fora | C16: =RESUMO!N18 -> 0 | E16: =$C16*D16 -> 0 | G16: =$C16*F16 -> 0 | I16: =$C16*H16 -> 0 | K16: =$C16*J16 -> 0 | M16: =$C16*L16 -> 0 | O16: =$C16*N16 -> 0 | Q16: =$C16*P16 -> 0 | S16: =$C16*R16 -> 0 | U16: =$C16*T16 -> 0 | W16: =$C16*V16 -> 0 | Y16: =$C16*X16 -> 0 | AA16: =$C16*Z16 -> 0 | AC16: =$C16*AB16 -> 0 | AE16: =$C16*AD16 -> 0 | AG16: =$C16*AF16 -> 0 | AI16: =$C16*AH16 -> 0 | AK16: =$C16*AJ16 -> 0 | AM16: =$C16*AL16 -> 0 | AN16: =SUM(D16,F16,H16,J16,L16,N16,P16,R16,T16,V16,X16,Z16,AB16,AD16,AF16,AH16,AJ16,AL16) -> 0 | AO16: =$C16*AN16 -> 0
A17: =PQ!B24 -> B.1.6 | B17: =PQ!C24 -> Desmatamento, destocamento, limpeza de área e estocagem do material de limpeza com árvores de diâmetro até 0,15 m | C17: =RESUMO!N19 -> 18277.002 | E17: =$C17*D17 -> 0 | G17: =$C17*F17 -> 0 | I17: =$C17*H17 -> 0 | K17: =$C17*J17 -> 0 | M17: =$C17*L17 -> 0 | O17: =$C17*N17 -> 0 | Q17: =$C17*P17 -> 0 | S17: =$C17*R17 -> 0 | U17: =$C17*T17 -> 0 | V17: 1 | W17: =$C17*V17 -> 18277.002 | Y17: =$C17*X17 -> 0 | AA17: =$C17*Z17 -> 0 | AC17: =$C17*AB17 -> 0 | AE17: =$C17*AD17 -> 0 | AG17: =$C17*AF17 -> 0 | AI17: =$C17*AH17 -> 0 | AK17: =$C17*AJ17 -> 0 | AM17: =$C17*AL17 -> 0 | AN17: =SUM(D17,F17,H17,J17,L17,N17,P17,R17,T17,V17,X17,Z17,AB17,AD17,AF17,AH17,AJ17,AL17) -> 1 | AO17: =$C17*AN17 -> 18277.002
A18: =PQ!B25 -> B.1.7 | B18: =PQ!C25 -> Escavação, carga e transporte de material de 1ª categoria - DMT de 1.400 a 1.600 m - caminho de serviço pavimentado - com escavadeira e caminhão basculante de 14 m³ | C18: =RESUMO!N20 -> 695707.05 | E18: =$C18*D18 -> 0 | G18: =$C18*F18 -> 0 | I18: =$C18*H18 -> 0 | K18: =$C18*J18 -> 0 | M18: =$C18*L18 -> 0 | O18: =$C18*N18 -> 0 | Q18: =$C18*P18 -> 0 | S18: =$C18*R18 -> 0 | U18: =$C18*T18 -> 0 | V18: 1 | W18: =$C18*V18 -> 695707.05 | Y18: =$C18*X18 -> 0 | AA18: =$C18*Z18 -> 0 | AC18: =$C18*AB18 -> 0 | AE18: =$C18*AD18 -> 0 | AG18: =$C18*AF18 -> 0 | AI18: =$C18*AH18 -> 0 | AK18: =$C18*AJ18 -> 0 | AM18: =$C18*AL18 -> 0 | AN18: =SUM(D18,F18,H18,J18,L18,N18,P18,R18,T18,V18,X18,Z18,AB18,AD18,AF18,AH18,AJ18,AL18) -> 1 | AO18: =$C18*AN18 -> 695707.05
A19: =PQ!B26 -> B.1.8 | B19: =PQ!C26 -> Escavação e carga de material de 2ª categoria - DMT acima de 3.000 m | C19: =RESUMO!N21 -> 2722.6105 | E19: =$C19*D19 -> 0 | G19: =$C19*F19 -> 0 | I19: =$C19*H19 -> 0 | K19: =$C19*J19 -> 0 | M19: =$C19*L19 -> 0 | O19: =$C19*N19 -> 0 | Q19: =$C19*P19 -> 0 | S19: =$C19*R19 -> 0 | U19: =$C19*T19 -> 0 | V19: 1 | W19: =$C19*V19 -> 2722.6105 | Y19: =$C19*X19 -> 0 | AA19: =$C19*Z19 -> 0 | AC19: =$C19*AB19 -> 0 | AE19: =$C19*AD19 -> 0 | AG19: =$C19*AF19 -> 0 | AI19: =$C19*AH19 -> 0 | AK19: =$C19*AJ19 -> 0 | AM19: =$C19*AL19 -> 0 | AN19: =SUM(D19,F19,H19,J19,L19,N19,P19,R19,T19,V19,X19,Z19,AB19,AD19,AF19,AH19,AJ19,AL19) -> 1 | AO19: =$C19*AN19 -> 2722.6105
A20: =PQ!B27 -> B.1.9 | B20: =PQ!C27 -> Regularização de bota-fora | C20: =RESUMO!N22 -> 14319.751 | E20: =$C20*D20 -> 0 | G20: =$C20*F20 -> 0 | I20: =$C20*H20 -> 0 | K20: =$C20*J20 -> 0 | M20: =$C20*L20 -> 0 | O20: =$C20*N20 -> 0 | Q20: =$C20*P20 -> 0 | S20: =$C20*R20 -> 0 | U20: =$C20*T20 -> 0 | V20: 1 | W20: =$C20*V20 -> 14319.751 | Y20: =$C20*X20 -> 0 | AA20: =$C20*Z20 -> 0 | AC20: =$C20*AB20 -> 0 | AE20: =$C20*AD20 -> 0 | AG20: =$C20*AF20 -> 0 | AI20: =$C20*AH20 -> 0 | AK20: =$C20*AJ20 -> 0 | AM20: =$C20*AL20 -> 0 | AN20: =SUM(D20,F20,H20,J20,L20,N20,P20,R20,T20,V20,X20,Z20,AB20,AD20,AF20,AH20,AJ20,AL20) -> 1 | AO20: =$C20*AN20 -> 14319.751
A21: =PQ!B28 -> B.2 | B21: =PQ!C28 -> Drenagem e OACs | C21: =RESUMO!N23 -> 372089.89 | E21: =SUBTOTAL(9,E22:E30) -> 0 | G21: =SUBTOTAL(9,G22:G30) -> 0 | I21: =SUBTOTAL(9,I22:I30) -> 0 | K21: =SUBTOTAL(9,K22:K30) -> 0 | M21: =SUBTOTAL(9,M22:M30) -> 0 | O21: =SUBTOTAL(9,O22:O30) -> 0 | Q21: =SUBTOTAL(9,Q22:Q30) -> 0 | S21: =SUBTOTAL(9,S22:S30) -> 0 | U21: =SUBTOTAL(9,U22:U30) -> 0 | W21: =SUBTOTAL(9,W22:W30) -> 372089.89 | Y21: =SUBTOTAL(9,Y22:Y30) -> 0 | AA21: =SUBTOTAL(9,AA22:AA30) -> 0 | AC21: =SUBTOTAL(9,AC22:AC30) -> 0 | AE21: =SUBTOTAL(9,AE22:AE30) -> 0 | AG21: =SUBTOTAL(9,AG22:AG30) -> 0 | AI21: =SUBTOTAL(9,AI22:AI30) -> 0 | AK21: =SUBTOTAL(9,AK22:AK30) -> 0 | AM21: =SUBTOTAL(9,AM22:AM30) -> 0 | AO21: =SUBTOTAL(9,AO22:AO30) -> 372089.89
A22: =PQ!B29 -> B.2.1 | B22: =PQ!C29 -> Demolição de dispositivos de drenagem | C22: =RESUMO!N24 -> 0 | E22: =$C22*D22 -> 0 | G22: =$C22*F22 -> 0 | I22: =$C22*H22 -> 0 | K22: =$C22*J22 -> 0 | M22: =$C22*L22 -> 0 | O22: =$C22*N22 -> 0 | Q22: =$C22*P22 -> 0 | S22: =$C22*R22 -> 0 | U22: =$C22*T22 -> 0 | W22: =$C22*V22 -> 0 | Y22: =$C22*X22 -> 0 | AA22: =$C22*Z22 -> 0 | AC22: =$C22*AB22 -> 0 | AE22: =$C22*AD22 -> 0 | AG22: =$C22*AF22 -> 0 | AI22: =$C22*AH22 -> 0 | AK22: =$C22*AJ22 -> 0 | AM22: =$C22*AL22 -> 0 | AN22: =SUM(D22,F22,H22,J22,L22,N22,P22,R22,T22,V22,X22,Z22,AB22,AD22,AF22,AH22,AJ22,AL22) -> 0 | AO22: =$C22*AN22 -> 0
A23: =PQ!B30 -> B.2.2 | B23: =PQ!C30 -> Sarjeta triangular de concreto - STC 150-30 - escavação mecânica - areia e brita comerciais | C23: =RESUMO!N25 -> 0 | E23: =$C23*D23 -> 0 | G23: =$C23*F23 -> 0 | I23: =$C23*H23 -> 0 | K23: =$C23*J23 -> 0 | M23: =$C23*L23 -> 0 | O23: =$C23*N23 -> 0 | Q23: =$C23*P23 -> 0 | S23: =$C23*R23 -> 0 | U23: =$C23*T23 -> 0 | W23: =$C23*V23 -> 0 | Y23: =$C23*X23 -> 0 | AA23: =$C23*Z23 -> 0 | AC23: =$C23*AB23 -> 0 | AE23: =$C23*AD23 -> 0 | AG23: =$C23*AF23 -> 0 | AI23: =$C23*AH23 -> 0 | AK23: =$C23*AJ23 -> 0 | AM23: =$C23*AL23 -> 0 | AN23: =SUM(D23,F23,H23,J23,L23,N23,P23,R23,T23,V23,X23,Z23,AB23,AD23,AF23,AH23,AJ23,AL23) -> 0 | AO23: =$C23*AN23 -> 0
A24: =PQ!B31 -> B.2.3 | B24: =PQ!C31 -> Valeta de proteção de cortes com revestimento de concreto - VPC 04 - areia e brita comerciais | C24: =RESUMO!N26 -> 0 | E24: =$C24*D24 -> 0 | G24: =$C24*F24 -> 0 | I24: =$C24*H24 -> 0 | K24: =$C24*J24 -> 0 | M24: =$C24*L24 -> 0 | O24: =$C24*N24 -> 0 | Q24: =$C24*P24 -> 0 | S24: =$C24*R24 -> 0 | U24: =$C24*T24 -> 0 | W24: =$C24*V24 -> 0 | Y24: =$C24*X24 -> 0 | AA24: =$C24*Z24 -> 0 | AC24: =$C24*AB24 -> 0 | AE24: =$C24*AD24 -> 0 | AG24: =$C24*AF24 -> 0 | AI24: =$C24*AH24 -> 0 | AK24: =$C24*AJ24 -> 0 | AM24: =$C24*AL24 -> 0 | AN24: =SUM(D24,F24,H24,J24,L24,N24,P24,R24,T24,V24,X24,Z24,AB24,AD24,AF24,AH24,AJ24,AL24) -> 0 | AO24: =$C24*AN24 -> 0
A25: =PQ!B32 -> B.2.4 | B25: =PQ!C32 -> Caixa coletora A6 - CCS 200-60A | C25: =RESUMO!N27 -> 0 | E25: =$C25*D25 -> 0 | G25: =$C25*F25 -> 0 | I25: =$C25*H25 -> 0 | K25: =$C25*J25 -> 0 | M25: =$C25*L25 -> 0 | O25: =$C25*N25 -> 0 | Q25: =$C25*P25 -> 0 | S25: =$C25*R25 -> 0 | U25: =$C25*T25 -> 0 | W25: =$C25*V25 -> 0 | Y25: =$C25*X25 -> 0 | AA25: =$C25*Z25 -> 0 | AC25: =$C25*AB25 -> 0 | AE25: =$C25*AD25 -> 0 | AG25: =$C25*AF25 -> 0 | AI25: =$C25*AH25 -> 0 | AK25: =$C25*AJ25 -> 0 | AM25: =$C25*AL25 -> 0 | AN25: =SUM(D25,F25,H25,J25,L25,N25,P25,R25,T25,V25,X25,Z25,AB25,AD25,AF25,AH25,AJ25,AL25) -> 0 | AO25: =$C25*AN25 -> 0
A26: =PQ!B33 -> B.2.5 | B26: =PQ!C33 -> Descida d'água de cortes em degraus - DCD 02 - areia e brita comerciais | C26: =RESUMO!N28 -> 0 | E26: =$C26*D26 -> 0 | G26: =$C26*F26 -> 0 | I26: =$C26*H26 -> 0 | K26: =$C26*J26 -> 0 | M26: =$C26*L26 -> 0 | O26: =$C26*N26 -> 0 | Q26: =$C26*P26 -> 0 | S26: =$C26*R26 -> 0 | U26: =$C26*T26 -> 0 | W26: =$C26*V26 -> 0 | Y26: =$C26*X26 -> 0 | AA26: =$C26*Z26 -> 0 | AC26: =$C26*AB26 -> 0 | AE26: =$C26*AD26 -> 0 | AG26: =$C26*AF26 -> 0 | AI26: =$C26*AH26 -> 0 | AK26: =$C26*AJ26 -> 0 | AM26: =$C26*AL26 -> 0 | AN26: =SUM(D26,F26,H26,J26,L26,N26,P26,R26,T26,V26,X26,Z26,AB26,AD26,AF26,AH26,AJ26,AL26) -> 0 | AO26: =$C26*AN26 -> 0
A27: =PQ!B34 -> B.2.6 | B27: =PQ!C34 -> Descida d'água de cortes em degraus - DCD 100-50 - areia e brita comerciais | C27: =RESUMO!N29 -> 116366.36 | E27: =$C27*D27 -> 0 | G27: =$C27*F27 -> 0 | I27: =$C27*H27 -> 0 | K27: =$C27*J27 -> 0 | M27: =$C27*L27 -> 0 | O27: =$C27*N27 -> 0 | Q27: =$C27*P27 -> 0 | S27: =$C27*R27 -> 0 | U27: =$C27*T27 -> 0 | V27: 1 | W27: =$C27*V27 -> 116366.36 | Y27: =$C27*X27 -> 0 | AA27: =$C27*Z27 -> 0 | AC27: =$C27*AB27 -> 0 | AE27: =$C27*AD27 -> 0 | AG27: =$C27*AF27 -> 0 | AI27: =$C27*AH27 -> 0 | AK27: =$C27*AJ27 -> 0 | AM27: =$C27*AL27 -> 0 | AN27: =SUM(D27,F27,H27,J27,L27,N27,P27,R27,T27,V27,X27,Z27,AB27,AD27,AF27,AH27,AJ27,AL27) -> 1 | AO27: =$C27*AN27 -> 116366.36
A28: =PQ!B35 -> B.2.7 | B28: =PQ!C35 -> Valeta de proteção de cortes com revestimento de concreto - VPCC 120-30 - escavação mecânica - areia e brita comerciais | C28: =RESUMO!N30 -> 214620.43 | E28: =$C28*D28 -> 0 | G28: =$C28*F28 -> 0 | I28: =$C28*H28 -> 0 | K28: =$C28*J28 -> 0 | M28: =$C28*L28 -> 0 | O28: =$C28*N28 -> 0 | Q28: =$C28*P28 -> 0 | S28: =$C28*R28 -> 0 | U28: =$C28*T28 -> 0 | V28: 1 | W28: =$C28*V28 -> 214620.43 | Y28: =$C28*X28 -> 0 | AA28: =$C28*Z28 -> 0 | AC28: =$C28*AB28 -> 0 | AE28: =$C28*AD28 -> 0 | AG28: =$C28*AF28 -> 0 | AI28: =$C28*AH28 -> 0 | AK28: =$C28*AJ28 -> 0 | AM28: =$C28*AL28 -> 0 | AN28: =SUM(D28,F28,H28,J28,L28,N28,P28,R28,T28,V28,X28,Z28,AB28,AD28,AF28,AH28,AJ28,AL28) -> 1 | AO28: =$C28*AN28 -> 214620.43
A29: =PQ!B36 -> B.2.8 | B29: =PQ!C36 -> Caixa coletora de sarjeta - CCS 250-120 A - com grelha de concreto - areia e brita comerciais | C29: =RESUMO!N31 -> 29887.64 | E29: =$C29*D29 -> 0 | G29: =$C29*F29 -> 0 | I29: =$C29*H29 -> 0 | K29: =$C29*J29 -> 0 | M29: =$C29*L29 -> 0 | O29: =$C29*N29 -> 0 | Q29: =$C29*P29 -> 0 | S29: =$C29*R29 -> 0 | U29: =$C29*T29 -> 0 | V29: 1 | W29: =$C29*V29 -> 29887.64 | Y29: =$C29*X29 -> 0 | AA29: =$C29*Z29 -> 0 | AC29: =$C29*AB29 -> 0 | AE29: =$C29*AD29 -> 0 | AG29: =$C29*AF29 -> 0 | AI29: =$C29*AH29 -> 0 | AK29: =$C29*AJ29 -> 0 | AM29: =$C29*AL29 -> 0 | AN29: =SUM(D29,F29,H29,J29,L29,N29,P29,R29,T29,V29,X29,Z29,AB29,AD29,AF29,AH29,AJ29,AL29) -> 1 | AO29: =$C29*AN29 -> 29887.64
A30: =PQ!B37 -> B.2.9 | B30: =PQ!C37 -> Sarjeta triangular de concreto - STC 88-20 - escavação mecânica - areia e brita comerciais | C30: =RESUMO!N32 -> 11215.46 | E30: =$C30*D30 -> 0 | G30: =$C30*F30 -> 0 | I30: =$C30*H30 -> 0 | K30: =$C30*J30 -> 0 | M30: =$C30*L30 -> 0 | O30: =$C30*N30 -> 0 | Q30: =$C30*P30 -> 0 | S30: =$C30*R30 -> 0 | U30: =$C30*T30 -> 0 | V30: 1 | W30: =$C30*V30 -> 11215.46 | Y30: =$C30*X30 -> 0 | AA30: =$C30*Z30 -> 0 | AC30: =$C30*AB30 -> 0 | AE30: =$C30*AD30 -> 0 | AG30: =$C30*AF30 -> 0 | AI30: =$C30*AH30 -> 0 | AK30: =$C30*AJ30 -> 0 | AM30: =$C30*AL30 -> 0 | AN30: =SUM(D30,F30,H30,J30,L30,N30,P30,R30,T30,V30,X30,Z30,AB30,AD30,AF30,AH30,AJ30,AL30) -> 1 | AO30: =$C30*AN30 -> 11215.46
A31: =PQ!B38 -> B.3 | B31: =PQ!C38 -> Revestimento Vegetal | C31: =RESUMO!N33 -> 621222.57 | E31: =SUBTOTAL(9,E32:E33) -> 0 | G31: =SUBTOTAL(9,G32:G33) -> 0 | I31: =SUBTOTAL(9,I32:I33) -> 0 | K31: =SUBTOTAL(9,K32:K33) -> 0 | M31: =SUBTOTAL(9,M32:M33) -> 0 | O31: =SUBTOTAL(9,O32:O33) -> 0 | Q31: =SUBTOTAL(9,Q32:Q33) -> 0 | S31: =SUBTOTAL(9,S32:S33) -> 0 | U31: =SUBTOTAL(9,U32:U33) -> 0 | W31: =SUBTOTAL(9,W32:W33) -> 621222.57 | Y31: =SUBTOTAL(9,Y32:Y33) -> 0 | AA31: =SUBTOTAL(9,AA32:AA33) -> 0 | AC31: =SUBTOTAL(9,AC32:AC33) -> 0 | AE31: =SUBTOTAL(9,AE32:AE33) -> 0 | AG31: =SUBTOTAL(9,AG32:AG33) -> 0 | AI31: =SUBTOTAL(9,AI32:AI33) -> 0 | AK31: =SUBTOTAL(9,AK32:AK33) -> 0 | AM31: =SUBTOTAL(9,AM32:AM33) -> 0 | AO31: =SUBTOTAL(9,AO32:AO33) -> 621222.57
A32: =PQ!B39 -> B.3.1 | B32: =PQ!C39 -> Proteção Vegetal (Hidrossemeadura + Biomanta) | C32: =RESUMO!N34 -> 574843.77 | E32: =$C32*D32 -> 0 | G32: =$C32*F32 -> 0 | I32: =$C32*H32 -> 0 | K32: =$C32*J32 -> 0 | M32: =$C32*L32 -> 0 | O32: =$C32*N32 -> 0 | Q32: =$C32*P32 -> 0 | S32: =$C32*R32 -> 0 | U32: =$C32*T32 -> 0 | V32: 1 | W32: =$C32*V32 -> 574843.77 | Y32: =$C32*X32 -> 0 | AA32: =$C32*Z32 -> 0 | AC32: =$C32*AB32 -> 0 | AE32: =$C32*AD32 -> 0 | AG32: =$C32*AF32 -> 0 | AI32: =$C32*AH32 -> 0 | AK32: =$C32*AJ32 -> 0 | AM32: =$C32*AL32 -> 0 | AN32: =SUM(D32,F32,H32,J32,L32,N32,P32,R32,T32,V32,X32,Z32,AB32,AD32,AF32,AH32,AJ32,AL32) -> 1 | AO32: =$C32*AN32 -> 574843.77
A33: =PQ!B40 -> B.3.2 | B33: =PQ!C40 -> Cerca com 4 fios de arame farpado e mourão de concreto de seção quadrada de 11 cm a cada 2,5 m e esticador de 15 cm a cada 50 m - areia e brita comerciais | C33: =RESUMO!N35 -> 46378.8 | E33: =$C33*D33 -> 0 | G33: =$C33*F33 -> 0 | I33: =$C33*H33 -> 0 | K33: =$C33*J33 -> 0 | M33: =$C33*L33 -> 0 | O33: =$C33*N33 -> 0 | Q33: =$C33*P33 -> 0 | S33: =$C33*R33 -> 0 | U33: =$C33*T33 -> 0 | V33: 1 | W33: =$C33*V33 -> 46378.8 | Y33: =$C33*X33 -> 0 | AA33: =$C33*Z33 -> 0 | AC33: =$C33*AB33 -> 0 | AE33: =$C33*AD33 -> 0 | AG33: =$C33*AF33 -> 0 | AI33: =$C33*AH33 -> 0 | AK33: =$C33*AJ33 -> 0 | AM33: =$C33*AL33 -> 0 | AN33: =SUM(D33,F33,H33,J33,L33,N33,P33,R33,T33,V33,X33,Z33,AB33,AD33,AF33,AH33,AJ33,AL33) -> 1 | AO33: =$C33*AN33 -> 46378.8
A34: =PQ!B41 -> C. | B34: =PQ!C41 -> Implantação de Desvio 1 - Km 303+450 - Leste | C34: =RESUMO!N36 -> 26511.6 | E34: =SUBTOTAL(9,E35:E60) -> 0 | G34: =SUBTOTAL(9,G35:G60) -> 0 | I34: =SUBTOTAL(9,I35:I60) -> 0 | K34: =SUBTOTAL(9,K35:K60) -> 0 | M34: =SUBTOTAL(9,M35:M60) -> 0 | O34: =SUBTOTAL(9,O35:O60) -> 0 | Q34: =SUBTOTAL(9,Q35:Q60) -> 0 | S34: =SUBTOTAL(9,S35:S60) -> 0 | U34: =SUBTOTAL(9,U35:U60) -> 0 | W34: =SUBTOTAL(9,W35:W60) -> 26511.6 | Y34: =SUBTOTAL(9,Y35:Y60) -> 0 | AA34: =SUBTOTAL(9,AA35:AA60) -> 0 | AC34: =SUBTOTAL(9,AC35:AC60) -> 0 | AE34: =SUBTOTAL(9,AE35:AE60) -> 0 | AG34: =SUBTOTAL(9,AG35:AG60) -> 0 | AI34: =SUBTOTAL(9,AI35:AI60) -> 0 | AK34: =SUBTOTAL(9,AK35:AK60) -> 0 | AM34: =SUBTOTAL(9,AM35:AM60) -> 0 | AO34: =SUBTOTAL(9,AO35:AO60) -> 26511.6
A35: =PQ!B42 -> C.1 | B35: =PQ!C42 -> Terraplenagem | C35: =RESUMO!N37 -> 0 | E35: =SUBTOTAL(9,E36:E40) -> 0 | G35: =SUBTOTAL(9,G36:G40) -> 0 | I35: =SUBTOTAL(9,I36:I40) -> 0 | K35: =SUBTOTAL(9,K36:K40) -> 0 | M35: =SUBTOTAL(9,M36:M40) -> 0 | O35: =SUBTOTAL(9,O36:O40) -> 0 | Q35: =SUBTOTAL(9,Q36:Q40) -> 0 | S35: =SUBTOTAL(9,S36:S40) -> 0 | U35: =SUBTOTAL(9,U36:U40) -> 0 | W35: =SUBTOTAL(9,W36:W40) -> 0 | Y35: =SUBTOTAL(9,Y36:Y40) -> 0 | AA35: =SUBTOTAL(9,AA36:AA40) -> 0 | AC35: =SUBTOTAL(9,AC36:AC40) -> 0 | AE35: =SUBTOTAL(9,AE36:AE40) -> 0 | AG35: =SUBTOTAL(9,AG36:AG40) -> 0 | AI35: =SUBTOTAL(9,AI36:AI40) -> 0 | AK35: =SUBTOTAL(9,AK36:AK40) -> 0 | AM35: =SUBTOTAL(9,AM36:AM40) -> 0 | AO35: =SUBTOTAL(9,AO36:AO40) -> 0
A36: =PQ!B43 -> C.1.1 | B36: =PQ!C43 -> Desmatamento, destocamento, limpeza de área e estocagem do material de limpeza com árvores de diâmetro até 0,15 m | C36: =RESUMO!N38 -> 0 | E36: =$C36*D36 -> 0 | G36: =$C36*F36 -> 0 | I36: =$C36*H36 -> 0 | K36: =$C36*J36 -> 0 | M36: =$C36*L36 -> 0 | O36: =$C36*N36 -> 0 | Q36: =$C36*P36 -> 0 | S36: =$C36*R36 -> 0 | U36: =$C36*T36 -> 0 | W36: =$C36*V36 -> 0 | Y36: =$C36*X36 -> 0 | AA36: =$C36*Z36 -> 0 | AC36: =$C36*AB36 -> 0 | AE36: =$C36*AD36 -> 0 | AG36: =$C36*AF36 -> 0 | AI36: =$C36*AH36 -> 0 | AK36: =$C36*AJ36 -> 0 | AM36: =$C36*AL36 -> 0 | AN36: =SUM(D36,F36,H36,J36,L36,N36,P36,R36,T36,V36,X36,Z36,AB36,AD36,AF36,AH36,AJ36,AL36) -> 0 | AO36: =$C36*AN36 -> 0
A37: =PQ!B44 -> C.1.2 | B37: =PQ!C44 -> Transporte com caminhão basculante de 14 m³ - rodovia pavimentada | C37: =RESUMO!N39 -> 0 | E37: =$C37*D37 -> 0 | G37: =$C37*F37 -> 0 | I37: =$C37*H37 -> 0 | K37: =$C37*J37 -> 0 | M37: =$C37*L37 -> 0 | O37: =$C37*N37 -> 0 | Q37: =$C37*P37 -> 0 | S37: =$C37*R37 -> 0 | U37: =$C37*T37 -> 0 | W37: =$C37*V37 -> 0 | Y37: =$C37*X37 -> 0 | AA37: =$C37*Z37 -> 0 | AC37: =$C37*AB37 -> 0 | AE37: =$C37*AD37 -> 0 | AG37: =$C37*AF37 -> 0 | AI37: =$C37*AH37 -> 0 | AK37: =$C37*AJ37 -> 0 | AM37: =$C37*AL37 -> 0 | AN37: =SUM(D37,F37,H37,J37,L37,N37,P37,R37,T37,V37,X37,Z37,AB37,AD37,AF37,AH37,AJ37,AL37) -> 0 | AO37: =$C37*AN37 -> 0
A38: =PQ!B45 -> C.1.3 | B38: =PQ!C45 -> Escavação, carga e transporte de material de 1ª categoria - DMT de 1.000 a 1.200 m - com escavadeira e caminhão basculante de 14 m³ | C38: =RESUMO!N40 -> 0 | E38: =$C38*D38 -> 0 | G38: =$C38*F38 -> 0 | I38: =$C38*H38 -> 0 | K38: =$C38*J38 -> 0 | M38: =$C38*L38 -> 0 | O38: =$C38*N38 -> 0 | Q38: =$C38*P38 -> 0 | S38: =$C38*R38 -> 0 | U38: =$C38*T38 -> 0 | W38: =$C38*V38 -> 0 | Y38: =$C38*X38 -> 0 | AA38: =$C38*Z38 -> 0 | AC38: =$C38*AB38 -> 0 | AE38: =$C38*AD38 -> 0 | AG38: =$C38*AF38 -> 0 | AI38: =$C38*AH38 -> 0 | AK38: =$C38*AJ38 -> 0 | AM38: =$C38*AL38 -> 0 | AN38: =SUM(D38,F38,H38,J38,L38,N38,P38,R38,T38,V38,X38,Z38,AB38,AD38,AF38,AH38,AJ38,AL38) -> 0 | AO38: =$C38*AN38 -> 0
A39: =PQ!B46 -> C.1.4 | B39: =PQ!C46 -> Regularização de bota-fora com espalhamento e execução de hidrossemeadura | C39: =RESUMO!N41 -> 0 | E39: =$C39*D39 -> 0 | G39: =$C39*F39 -> 0 | I39: =$C39*H39 -> 0 | K39: =$C39*J39 -> 0 | M39: =$C39*L39 -> 0 | O39: =$C39*N39 -> 0 | Q39: =$C39*P39 -> 0 | S39: =$C39*R39 -> 0 | U39: =$C39*T39 -> 0 | W39: =$C39*V39 -> 0 | Y39: =$C39*X39 -> 0 | AA39: =$C39*Z39 -> 0 | AC39: =$C39*AB39 -> 0 | AE39: =$C39*AD39 -> 0 | AG39: =$C39*AF39 -> 0 | AI39: =$C39*AH39 -> 0 | AK39: =$C39*AJ39 -> 0 | AM39: =$C39*AL39 -> 0 | AN39: =SUM(D39,F39,H39,J39,L39,N39,P39,R39,T39,V39,X39,Z39,AB39,AD39,AF39,AH39,AJ39,AL39) -> 0 | AO39: =$C39*AN39 -> 0
A40: =PQ!B47 -> C.1.5 | B40: =PQ!C47 -> Regularização de bota-fora | C40: =RESUMO!N42 -> 0 | E40: =$C40*D40 -> 0 | G40: =$C40*F40 -> 0 | I40: =$C40*H40 -> 0 | K40: =$C40*J40 -> 0 | M40: =$C40*L40 -> 0 | O40: =$C40*N40 -> 0 | Q40: =$C40*P40 -> 0 | S40: =$C40*R40 -> 0 | U40: =$C40*T40 -> 0 | W40: =$C40*V40 -> 0 | Y40: =$C40*X40 -> 0 | AA40: =$C40*Z40 -> 0 | AC40: =$C40*AB40 -> 0 | AE40: =$C40*AD40 -> 0 | AG40: =$C40*AF40 -> 0 | AI40: =$C40*AH40 -> 0 | AK40: =$C40*AJ40 -> 0 | AM40: =$C40*AL40 -> 0 | AN40: =SUM(D40,F40,H40,J40,L40,N40,P40,R40,T40,V40,X40,Z40,AB40,AD40,AF40,AH40,AJ40,AL40) -> 0 | AO40: =$C40*AN40 -> 0
A41: =PQ!B48 -> C.2 | B41: =PQ!C48 -> Pavimentação | C41: =RESUMO!N43 -> 0 | E41: =SUBTOTAL(9,E42:E47) -> 0 | G41: =SUBTOTAL(9,G42:G47) -> 0 | I41: =SUBTOTAL(9,I42:I47) -> 0 | K41: =SUBTOTAL(9,K42:K47) -> 0 | M41: =SUBTOTAL(9,M42:M47) -> 0 | O41: =SUBTOTAL(9,O42:O47) -> 0 | Q41: =SUBTOTAL(9,Q42:Q47) -> 0 | S41: =SUBTOTAL(9,S42:S47) -> 0 | U41: =SUBTOTAL(9,U42:U47) -> 0 | W41: =SUBTOTAL(9,W42:W47) -> 0 | Y41: =SUBTOTAL(9,Y42:Y47) -> 0 | AA41: =SUBTOTAL(9,AA42:AA47) -> 0 | AC41: =SUBTOTAL(9,AC42:AC47) -> 0 | AE41: =SUBTOTAL(9,AE42:AE47) -> 0 | AG41: =SUBTOTAL(9,AG42:AG47) -> 0 | AI41: =SUBTOTAL(9,AI42:AI47) -> 0 | AK41: =SUBTOTAL(9,AK42:AK47) -> 0 | AM41: =SUBTOTAL(9,AM42:AM47) -> 0 | AO41: =SUBTOTAL(9,AO42:AO47) -> 0
A42: =PQ!B49 -> C.2.1 | B42: =PQ!C49 -> Preparo e melhoramento do subleito | C42: =RESUMO!N44 -> 0 | E42: =$C42*D42 -> 0 | G42: =$C42*F42 -> 0 | I42: =$C42*H42 -> 0 | K42: =$C42*J42 -> 0 | M42: =$C42*L42 -> 0 | O42: =$C42*N42 -> 0 | Q42: =$C42*P42 -> 0 | S42: =$C42*R42 -> 0 | U42: =$C42*T42 -> 0 | W42: =$C42*V42 -> 0 | Y42: =$C42*X42 -> 0 | AA42: =$C42*Z42 -> 0 | AC42: =$C42*AB42 -> 0 | AE42: =$C42*AD42 -> 0 | AG42: =$C42*AF42 -> 0 | AI42: =$C42*AH42 -> 0 | AK42: =$C42*AJ42 -> 0 | AM42: =$C42*AL42 -> 0 | AN42: =SUM(D42,F42,H42,J42,L42,N42,P42,R42,T42,V42,X42,Z42,AB42,AD42,AF42,AH42,AJ42,AL42) -> 0 | AO42: =$C42*AN42 -> 0
A43: =PQ!B50 -> C.2.2 | B43: =PQ!C50 -> Rachão ou pedra de mão | C43: =RESUMO!N45 -> 0 | E43: =$C43*D43 -> 0 | G43: =$C43*F43 -> 0 | I43: =$C43*H43 -> 0 | K43: =$C43*J43 -> 0 | M43: =$C43*L43 -> 0 | O43: =$C43*N43 -> 0 | Q43: =$C43*P43 -> 0 | S43: =$C43*R43 -> 0 | U43: =$C43*T43 -> 0 | W43: =$C43*V43 -> 0 | Y43: =$C43*X43 -> 0 | AA43: =$C43*Z43 -> 0 | AC43: =$C43*AB43 -> 0 | AE43: =$C43*AD43 -> 0 | AG43: =$C43*AF43 -> 0 | AI43: =$C43*AH43 -> 0 | AK43: =$C43*AJ43 -> 0 | AM43: =$C43*AL43 -> 0 | AN43: =SUM(D43,F43,H43,J43,L43,N43,P43,R43,T43,V43,X43,Z43,AB43,AD43,AF43,AH43,AJ43,AL43) -> 0 | AO43: =$C43*AN43 -> 0
A44: =PQ!B51 -> C.2.3 | B44: =PQ!C51 -> Sub-base ou base de brita graduada simples (BGS) | C44: =RESUMO!N46 -> 0 | E44: =$C44*D44 -> 0 | G44: =$C44*F44 -> 0 | I44: =$C44*H44 -> 0 | K44: =$C44*J44 -> 0 | M44: =$C44*L44 -> 0 | O44: =$C44*N44 -> 0 | Q44: =$C44*P44 -> 0 | S44: =$C44*R44 -> 0 | U44: =$C44*T44 -> 0 | W44: =$C44*V44 -> 0 | Y44: =$C44*X44 -> 0 | AA44: =$C44*Z44 -> 0 | AC44: =$C44*AB44 -> 0 | AE44: =$C44*AD44 -> 0 | AG44: =$C44*AF44 -> 0 | AI44: =$C44*AH44 -> 0 | AK44: =$C44*AJ44 -> 0 | AM44: =$C44*AL44 -> 0 | AN44: =SUM(D44,F44,H44,J44,L44,N44,P44,R44,T44,V44,X44,Z44,AB44,AD44,AF44,AH44,AJ44,AL44) -> 0 | AO44: =$C44*AN44 -> 0
A45: =PQ!B52 -> C.2.4 | B45: =PQ!C52 -> Imprimadura betuminosa impermeabilizante | C45: =RESUMO!N47 -> 0 | E45: =$C45*D45 -> 0 | G45: =$C45*F45 -> 0 | I45: =$C45*H45 -> 0 | K45: =$C45*J45 -> 0 | M45: =$C45*L45 -> 0 | O45: =$C45*N45 -> 0 | Q45: =$C45*P45 -> 0 | S45: =$C45*R45 -> 0 | U45: =$C45*T45 -> 0 | W45: =$C45*V45 -> 0 | Y45: =$C45*X45 -> 0 | AA45: =$C45*Z45 -> 0 | AC45: =$C45*AB45 -> 0 | AE45: =$C45*AD45 -> 0 | AG45: =$C45*AF45 -> 0 | AI45: =$C45*AH45 -> 0 | AK45: =$C45*AJ45 -> 0 | AM45: =$C45*AL45 -> 0 | AN45: =SUM(D45,F45,H45,J45,L45,N45,P45,R45,T45,V45,X45,Z45,AB45,AD45,AF45,AH45,AJ45,AL45) -> 0 | AO45: =$C45*AN45 -> 0
A46: =PQ!B53 -> C.2.5 | B46: =PQ!C53 -> Imprimadura betuminosa ligante | C46: =RESUMO!N48 -> 0 | E46: =$C46*D46 -> 0 | G46: =$C46*F46 -> 0 | I46: =$C46*H46 -> 0 | K46: =$C46*J46 -> 0 | M46: =$C46*L46 -> 0 | O46: =$C46*N46 -> 0 | Q46: =$C46*P46 -> 0 | S46: =$C46*R46 -> 0 | U46: =$C46*T46 -> 0 | W46: =$C46*V46 -> 0 | Y46: =$C46*X46 -> 0 | AA46: =$C46*Z46 -> 0 | AC46: =$C46*AB46 -> 0 | AE46: =$C46*AD46 -> 0 | AG46: =$C46*AF46 -> 0 | AI46: =$C46*AH46 -> 0 | AK46: =$C46*AJ46 -> 0 | AM46: =$C46*AL46 -> 0 | AN46: =SUM(D46,F46,H46,J46,L46,N46,P46,R46,T46,V46,X46,Z46,AB46,AD46,AF46,AH46,AJ46,AL46) -> 0 | AO46: =$C46*AN46 -> 0
A47: =PQ!B54 -> C.2.6 | B47: =PQ!C54 -> CBUQ Faixa C/D c/ DOP ou polímero similar | C47: =RESUMO!N49 -> 0 | E47: =$C47*D47 -> 0 | G47: =$C47*F47 -> 0 | I47: =$C47*H47 -> 0 | K47: =$C47*J47 -> 0 | M47: =$C47*L47 -> 0 | O47: =$C47*N47 -> 0 | Q47: =$C47*P47 -> 0 | S47: =$C47*R47 -> 0 | U47: =$C47*T47 -> 0 | W47: =$C47*V47 -> 0 | Y47: =$C47*X47 -> 0 | AA47: =$C47*Z47 -> 0 | AC47: =$C47*AB47 -> 0 | AE47: =$C47*AD47 -> 0 | AG47: =$C47*AF47 -> 0 | AI47: =$C47*AH47 -> 0 | AK47: =$C47*AJ47 -> 0 | AM47: =$C47*AL47 -> 0 | AN47: =SUM(D47,F47,H47,J47,L47,N47,P47,R47,T47,V47,X47,Z47,AB47,AD47,AF47,AH47,AJ47,AL47) -> 0 | AO47: =$C47*AN47 -> 0
A48: =PQ!B55 -> C.3 | B48: =PQ!C55 -> Material Betuminoso e Transportes | C48: =RESUMO!N50 -> 0 | E48: =SUBTOTAL(9,E49:E54) -> 0 | G48: =SUBTOTAL(9,G49:G54) -> 0 | I48: =SUBTOTAL(9,I49:I54) -> 0 | K48: =SUBTOTAL(9,K49:K54) -> 0 | M48: =SUBTOTAL(9,M49:M54) -> 0 | O48: =SUBTOTAL(9,O49:O54) -> 0 | Q48: =SUBTOTAL(9,Q49:Q54) -> 0 | S48: =SUBTOTAL(9,S49:S54) -> 0 | U48: =SUBTOTAL(9,U49:U54) -> 0 | W48: =SUBTOTAL(9,W49:W54) -> 0 | Y48: =SUBTOTAL(9,Y49:Y54) -> 0 | AA48: =SUBTOTAL(9,AA49:AA54) -> 0 | AC48: =SUBTOTAL(9,AC49:AC54) -> 0 | AE48: =SUBTOTAL(9,AE49:AE54) -> 0 | AG48: =SUBTOTAL(9,AG49:AG54) -> 0 | AI48: =SUBTOTAL(9,AI49:AI54) -> 0 | AK48: =SUBTOTAL(9,AK49:AK54) -> 0 | AM48: =SUBTOTAL(9,AM49:AM54) -> 0 | AO48: =SUBTOTAL(9,AO49:AO54) -> 0
A49: =PQ!B56 -> C.3.1 | B49: =PQ!C56 -> Fornecimento de emulsão asfáltica Imprimer | C49: =RESUMO!N51 -> 0 | E49: =$C49*D49 -> 0 | G49: =$C49*F49 -> 0 | I49: =$C49*H49 -> 0 | K49: =$C49*J49 -> 0 | M49: =$C49*L49 -> 0 | O49: =$C49*N49 -> 0 | Q49: =$C49*P49 -> 0 | S49: =$C49*R49 -> 0 | U49: =$C49*T49 -> 0 | W49: =$C49*V49 -> 0 | Y49: =$C49*X49 -> 0 | AA49: =$C49*Z49 -> 0 | AC49: =$C49*AB49 -> 0 | AE49: =$C49*AD49 -> 0 | AG49: =$C49*AF49 -> 0 | AI49: =$C49*AH49 -> 0 | AK49: =$C49*AJ49 -> 0 | AM49: =$C49*AL49 -> 0 | AN49: =SUM(D49,F49,H49,J49,L49,N49,P49,R49,T49,V49,X49,Z49,AB49,AD49,AF49,AH49,AJ49,AL49) -> 0 | AO49: =$C49*AN49 -> 0
A50: =PQ!B57 -> C.3.2 | B50: =PQ!C57 -> Fornecimento de emulsão asfáltica tipo RR-1C | C50: =RESUMO!N52 -> 0 | E50: =$C50*D50 -> 0 | G50: =$C50*F50 -> 0 | I50: =$C50*H50 -> 0 | K50: =$C50*J50 -> 0 | M50: =$C50*L50 -> 0 | O50: =$C50*N50 -> 0 | Q50: =$C50*P50 -> 0 | S50: =$C50*R50 -> 0 | U50: =$C50*T50 -> 0 | W50: =$C50*V50 -> 0 | Y50: =$C50*X50 -> 0 | AA50: =$C50*Z50 -> 0 | AC50: =$C50*AB50 -> 0 | AE50: =$C50*AD50 -> 0 | AG50: =$C50*AF50 -> 0 | AI50: =$C50*AH50 -> 0 | AK50: =$C50*AJ50 -> 0 | AM50: =$C50*AL50 -> 0 | AN50: =SUM(D50,F50,H50,J50,L50,N50,P50,R50,T50,V50,X50,Z50,AB50,AD50,AF50,AH50,AJ50,AL50) -> 0 | AO50: =$C50*AN50 -> 0
A51: =PQ!B58 -> C.3.3 | B51: =PQ!C58 -> Fornecimento de CAP modificado com adição de polímero | C51: =RESUMO!N53 -> 0 | E51: =$C51*D51 -> 0 | G51: =$C51*F51 -> 0 | I51: =$C51*H51 -> 0 | K51: =$C51*J51 -> 0 | M51: =$C51*L51 -> 0 | O51: =$C51*N51 -> 0 | Q51: =$C51*P51 -> 0 | S51: =$C51*R51 -> 0 | U51: =$C51*T51 -> 0 | W51: =$C51*V51 -> 0 | Y51: =$C51*X51 -> 0 | AA51: =$C51*Z51 -> 0 | AC51: =$C51*AB51 -> 0 | AE51: =$C51*AD51 -> 0 | AG51: =$C51*AF51 -> 0 | AI51: =$C51*AH51 -> 0 | AK51: =$C51*AJ51 -> 0 | AM51: =$C51*AL51 -> 0 | AN51: =SUM(D51,F51,H51,J51,L51,N51,P51,R51,T51,V51,X51,Z51,AB51,AD51,AF51,AH51,AJ51,AL51) -> 0 | AO51: =$C51*AN51 -> 0
A52: =PQ!B59 -> C.3.4 | B52: =PQ!C59 -> Transporte com caminhão basculante de 14 m³ - rodovia pavimentada - Agregados | C52: =RESUMO!N54 -> 0 | E52: =$C52*D52 -> 0 | G52: =$C52*F52 -> 0 | I52: =$C52*H52 -> 0 | K52: =$C52*J52 -> 0 | M52: =$C52*L52 -> 0 | O52: =$C52*N52 -> 0 | Q52: =$C52*P52 -> 0 | S52: =$C52*R52 -> 0 | U52: =$C52*T52 -> 0 | W52: =$C52*V52 -> 0 | Y52: =$C52*X52 -> 0 | AA52: =$C52*Z52 -> 0 | AC52: =$C52*AB52 -> 0 | AE52: =$C52*AD52 -> 0 | AG52: =$C52*AF52 -> 0 | AI52: =$C52*AH52 -> 0 | AK52: =$C52*AJ52 -> 0 | AM52: =$C52*AL52 -> 0 | AN52: =SUM(D52,F52,H52,J52,L52,N52,P52,R52,T52,V52,X52,Z52,AB52,AD52,AF52,AH52,AJ52,AL52) -> 0 | AO52: =$C52*AN52 -> 0
A53: =PQ!B60 -> C.3.5 | B53: =PQ!C60 -> Transporte com caminhão basculante de 14 m³ - rodovia pavimentada - Massa Asfaltica | C53: =RESUMO!N55 -> 0 | E53: =$C53*D53 -> 0 | G53: =$C53*F53 -> 0 | I53: =$C53*H53 -> 0 | K53: =$C53*J53 -> 0 | M53: =$C53*L53 -> 0 | O53: =$C53*N53 -> 0 | Q53: =$C53*P53 -> 0 | S53: =$C53*R53 -> 0 | U53: =$C53*T53 -> 0 | W53: =$C53*V53 -> 0 | Y53: =$C53*X53 -> 0 | AA53: =$C53*Z53 -> 0 | AC53: =$C53*AB53 -> 0 | AE53: =$C53*AD53 -> 0 | AG53: =$C53*AF53 -> 0 | AI53: =$C53*AH53 -> 0 | AK53: =$C53*AJ53 -> 0 | AM53: =$C53*AL53 -> 0 | AN53: =SUM(D53,F53,H53,J53,L53,N53,P53,R53,T53,V53,X53,Z53,AB53,AD53,AF53,AH53,AJ53,AL53) -> 0 | AO53: =$C53*AN53 -> 0
A54: =PQ!B61 -> C.3.6 | B54: =PQ!C61 -> Transporte com caminhão basculante de 14 m³ - rodovia pavimentada - Materiais Betuminosos | C54: =RESUMO!N56 -> 0 | E54: =$C54*D54 -> 0 | G54: =$C54*F54 -> 0 | I54: =$C54*H54 -> 0 | K54: =$C54*J54 -> 0 | M54: =$C54*L54 -> 0 | O54: =$C54*N54 -> 0 | Q54: =$C54*P54 -> 0 | S54: =$C54*R54 -> 0 | U54: =$C54*T54 -> 0 | W54: =$C54*V54 -> 0 | Y54: =$C54*X54 -> 0 | AA54: =$C54*Z54 -> 0 | AC54: =$C54*AB54 -> 0 | AE54: =$C54*AD54 -> 0 | AG54: =$C54*AF54 -> 0 | AI54: =$C54*AH54 -> 0 | AK54: =$C54*AJ54 -> 0 | AM54: =$C54*AL54 -> 0 | AN54: =SUM(D54,F54,H54,J54,L54,N54,P54,R54,T54,V54,X54,Z54,AB54,AD54,AF54,AH54,AJ54,AL54) -> 0 | AO54: =$C54*AN54 -> 0
A55: =PQ!B62 -> C.4 | B55: =PQ!C62 -> Drenagem e OACs | C55: =RESUMO!N57 -> 26511.6 | E55: =SUBTOTAL(9,E56:E60) -> 0 | G55: =SUBTOTAL(9,G56:G60) -> 0 | I55: =SUBTOTAL(9,I56:I60) -> 0 | K55: =SUBTOTAL(9,K56:K60) -> 0 | M55: =SUBTOTAL(9,M56:M60) -> 0 | O55: =SUBTOTAL(9,O56:O60) -> 0 | Q55: =SUBTOTAL(9,Q56:Q60) -> 0 | S55: =SUBTOTAL(9,S56:S60) -> 0 | U55: =SUBTOTAL(9,U56:U60) -> 0 | W55: =SUBTOTAL(9,W56:W60) -> 26511.6 | Y55: =SUBTOTAL(9,Y56:Y60) -> 0 | AA55: =SUBTOTAL(9,AA56:AA60) -> 0 | AC55: =SUBTOTAL(9,AC56:AC60) -> 0 | AE55: =SUBTOTAL(9,AE56:AE60) -> 0 | AG55: =SUBTOTAL(9,AG56:AG60) -> 0 | AI55: =SUBTOTAL(9,AI56:AI60) -> 0 | AK55: =SUBTOTAL(9,AK56:AK60) -> 0 | AM55: =SUBTOTAL(9,AM56:AM60) -> 0 | AO55: =SUBTOTAL(9,AO56:AO60) -> 26511.6
A56: =PQ!B63 -> C.4.1 | B56: =PQ!C63 -> Sarjeta triangular de concreto - STC 88-20 - escavação mecânica - areia e brita comerciais | C56: =RESUMO!N58 -> 16553.2 | E56: =$C56*D56 -> 0 | G56: =$C56*F56 -> 0 | I56: =$C56*H56 -> 0 | K56: =$C56*J56 -> 0 | M56: =$C56*L56 -> 0 | O56: =$C56*N56 -> 0 | Q56: =$C56*P56 -> 0 | S56: =$C56*R56 -> 0 | U56: =$C56*T56 -> 0 | V56: 1 | W56: =$C56*V56 -> 16553.2 | Y56: =$C56*X56 -> 0 | AA56: =$C56*Z56 -> 0 | AC56: =$C56*AB56 -> 0 | AE56: =$C56*AD56 -> 0 | AG56: =$C56*AF56 -> 0 | AI56: =$C56*AH56 -> 0 | AK56: =$C56*AJ56 -> 0 | AM56: =$C56*AL56 -> 0 | AN56: =SUM(D56,F56,H56,J56,L56,N56,P56,R56,T56,V56,X56,Z56,AB56,AD56,AF56,AH56,AJ56,AL56) -> 1 | AO56: =$C56*AN56 -> 16553.2
A57: =PQ!B64 -> C.4.2 | B57: =PQ!C64 -> Dissipador de energia - DES 88-264 - areia, brita e pedra de mão comerciais | C57: =RESUMO!N59 -> 0 | E57: =$C57*D57 -> 0 | G57: =$C57*F57 -> 0 | I57: =$C57*H57 -> 0 | K57: =$C57*J57 -> 0 | M57: =$C57*L57 -> 0 | O57: =$C57*N57 -> 0 | Q57: =$C57*P57 -> 0 | S57: =$C57*R57 -> 0 | U57: =$C57*T57 -> 0 | W57: =$C57*V57 -> 0 | Y57: =$C57*X57 -> 0 | AA57: =$C57*Z57 -> 0 | AC57: =$C57*AB57 -> 0 | AE57: =$C57*AD57 -> 0 | AG57: =$C57*AF57 -> 0 | AI57: =$C57*AH57 -> 0 | AK57: =$C57*AJ57 -> 0 | AM57: =$C57*AL57 -> 0 | AN57: =SUM(D57,F57,H57,J57,L57,N57,P57,R57,T57,V57,X57,Z57,AB57,AD57,AF57,AH57,AJ57,AL57) -> 0 | AO57: =$C57*AN57 -> 0
A58: =PQ!B65 -> C.4.3 | B58: =PQ!C65 -> Dreno longitudinal profundo para corte em solo - DPS 01 - tubo PEAD e areia comercial | C58: =RESUMO!N60 -> 2327.5 | E58: =$C58*D58 -> 0 | G58: =$C58*F58 -> 0 | I58: =$C58*H58 -> 0 | K58: =$C58*J58 -> 0 | M58: =$C58*L58 -> 0 | O58: =$C58*N58 -> 0 | Q58: =$C58*P58 -> 0 | S58: =$C58*R58 -> 0 | U58: =$C58*T58 -> 0 | V58: 1 | W58: =$C58*V58 -> 2327.5 | Y58: =$C58*X58 -> 0 | AA58: =$C58*Z58 -> 0 | AC58: =$C58*AB58 -> 0 | AE58: =$C58*AD58 -> 0 | AG58: =$C58*AF58 -> 0 | AI58: =$C58*AH58 -> 0 | AK58: =$C58*AJ58 -> 0 | AM58: =$C58*AL58 -> 0 | AN58: =SUM(D58,F58,H58,J58,L58,N58,P58,R58,T58,V58,X58,Z58,AB58,AD58,AF58,AH58,AJ58,AL58) -> 1 | AO58: =$C58*AN58 -> 2327.5
A59: =PQ!B66 -> C.4.4 | B59: =PQ!C66 -> Concreto fck = 20 MPa - confecção em central dosadora de 30 m³/h - areia e brita comerciais | C59: =RESUMO!N61 -> 2042.08 | E59: =$C59*D59 -> 0 | G59: =$C59*F59 -> 0 | I59: =$C59*H59 -> 0 | K59: =$C59*J59 -> 0 | M59: =$C59*L59 -> 0 | O59: =$C59*N59 -> 0 | Q59: =$C59*P59 -> 0 | S59: =$C59*R59 -> 0 | U59: =$C59*T59 -> 0 | V59: 1 | W59: =$C59*V59 -> 2042.08 | Y59: =$C59*X59 -> 0 | AA59: =$C59*Z59 -> 0 | AC59: =$C59*AB59 -> 0 | AE59: =$C59*AD59 -> 0 | AG59: =$C59*AF59 -> 0 | AI59: =$C59*AH59 -> 0 | AK59: =$C59*AJ59 -> 0 | AM59: =$C59*AL59 -> 0 | AN59: =SUM(D59,F59,H59,J59,L59,N59,P59,R59,T59,V59,X59,Z59,AB59,AD59,AF59,AH59,AJ59,AL59) -> 1 | AO59: =$C59*AN59 -> 2042.08
A60: =PQ!B67 -> C.4.5 | B60: =PQ!C67 -> Tubo PEAD para drenagem - D = 800 mm - fornecimento e instalação | C60: =RESUMO!N62 -> 5588.82 | E60: =$C60*D60 -> 0 | G60: =$C60*F60 -> 0 | I60: =$C60*H60 -> 0 | K60: =$C60*J60 -> 0 | M60: =$C60*L60 -> 0 | O60: =$C60*N60 -> 0 | Q60: =$C60*P60 -> 0 | S60: =$C60*R60 -> 0 | U60: =$C60*T60 -> 0 | V60: 1 | W60: =$C60*V60 -> 5588.82 | Y60: =$C60*X60 -> 0 | AA60: =$C60*Z60 -> 0 | AC60: =$C60*AB60 -> 0 | AE60: =$C60*AD60 -> 0 | AG60: =$C60*AF60 -> 0 | AI60: =$C60*AH60 -> 0 | AK60: =$C60*AJ60 -> 0 | AM60: =$C60*AL60 -> 0 | AN60: =SUM(D60,F60,H60,J60,L60,N60,P60,R60,T60,V60,X60,Z60,AB60,AD60,AF60,AH60,AJ60,AL60) -> 1 | AO60: =$C60*AN60 -> 5588.82
A61: =PQ!B68 -> D. | B61: =PQ!C68 -> Implantação de Desvios 2 e 3 | C61: =RESUMO!N63 -> -9738.9274 | E61: =SUBTOTAL(9,E62:E85) -> 0 | G61: =SUBTOTAL(9,G62:G85) -> 0 | I61: =SUBTOTAL(9,I62:I85) -> 0 | K61: =SUBTOTAL(9,K62:K85) -> 0 | M61: =SUBTOTAL(9,M62:M85) -> 0 | O61: =SUBTOTAL(9,O62:O85) -> 0 | Q61: =SUBTOTAL(9,Q62:Q85) -> 0 | S61: =SUBTOTAL(9,S62:S85) -> 0 | U61: =SUBTOTAL(9,U62:U85) -> 0 | W61: =SUBTOTAL(9,W62:W85) -> -9738.9274 | Y61: =SUBTOTAL(9,Y62:Y85) -> 0 | AA61: =SUBTOTAL(9,AA62:AA85) -> 0 | AC61: =SUBTOTAL(9,AC62:AC85) -> 0 | AE61: =SUBTOTAL(9,AE62:AE85) -> 0 | AG61: =SUBTOTAL(9,AG62:AG85) -> 0 | AI61: =SUBTOTAL(9,AI62:AI85) -> 0 | AK61: =SUBTOTAL(9,AK62:AK85) -> 0 | AM61: =SUBTOTAL(9,AM62:AM85) -> 0 | AO61: =SUBTOTAL(9,AO62:AO85) -> -9738.9274
A62: =PQ!B69 -> D.1 | B62: =PQ!C69 -> Terraplenagem | C62: =RESUMO!N64 -> -18079.327 | E62: =SUBTOTAL(9,E63:E67) -> 0 | G62: =SUBTOTAL(9,G63:G67) -> 0 | I62: =SUBTOTAL(9,I63:I67) -> 0 | K62: =SUBTOTAL(9,K63:K67) -> 0 | M62: =SUBTOTAL(9,M63:M67) -> 0 | O62: =SUBTOTAL(9,O63:O67) -> 0 | Q62: =SUBTOTAL(9,Q63:Q67) -> 0 | S62: =SUBTOTAL(9,S63:S67) -> 0 | U62: =SUBTOTAL(9,U63:U67) -> 0 | W62: =SUBTOTAL(9,W63:W67) -> -18079.327 | Y62: =SUBTOTAL(9,Y63:Y67) -> 0 | AA62: =SUBTOTAL(9,AA63:AA67) -> 0 | AC62: =SUBTOTAL(9,AC63:AC67) -> 0 | AE62: =SUBTOTAL(9,AE63:AE67) -> 0 | AG62: =SUBTOTAL(9,AG63:AG67) -> 0 | AI62: =SUBTOTAL(9,AI63:AI67) -> 0 | AK62: =SUBTOTAL(9,AK63:AK67) -> 0 | AM62: =SUBTOTAL(9,AM63:AM67) -> 0 | AO62: =SUBTOTAL(9,AO63:AO67) -> -18079.327
A63: =PQ!B70 -> D.1.1 | B63: =PQ!C70 -> Desmatamento, destocamento, limpeza de área e estocagem do material de limpeza com árvores de diâmetro até 0,15 m | C63: =RESUMO!N65 -> 0 | E63: =$C63*D63 -> 0 | G63: =$C63*F63 -> 0 | I63: =$C63*H63 -> 0 | K63: =$C63*J63 -> 0 | M63: =$C63*L63 -> 0 | O63: =$C63*N63 -> 0 | Q63: =$C63*P63 -> 0 | S63: =$C63*R63 -> 0 | U63: =$C63*T63 -> 0 | W63: =$C63*V63 -> 0 | Y63: =$C63*X63 -> 0 | AA63: =$C63*Z63 -> 0 | AC63: =$C63*AB63 -> 0 | AE63: =$C63*AD63 -> 0 | AG63: =$C63*AF63 -> 0 | AI63: =$C63*AH63 -> 0 | AK63: =$C63*AJ63 -> 0 | AM63: =$C63*AL63 -> 0 | AN63: =SUM(D63,F63,H63,J63,L63,N63,P63,R63,T63,V63,X63,Z63,AB63,AD63,AF63,AH63,AJ63,AL63) -> 0 | AO63: =$C63*AN63 -> 0
A64: =PQ!B71 -> D.1.2 | B64: =PQ!C71 -> Transporte com caminhão basculante de 14 m³ - rodovia pavimentada | C64: =RESUMO!N66 -> 0 | E64: =$C64*D64 -> 0 | G64: =$C64*F64 -> 0 | I64: =$C64*H64 -> 0 | K64: =$C64*J64 -> 0 | M64: =$C64*L64 -> 0 | O64: =$C64*N64 -> 0 | Q64: =$C64*P64 -> 0 | S64: =$C64*R64 -> 0 | U64: =$C64*T64 -> 0 | W64: =$C64*V64 -> 0 | Y64: =$C64*X64 -> 0 | AA64: =$C64*Z64 -> 0 | AC64: =$C64*AB64 -> 0 | AE64: =$C64*AD64 -> 0 | AG64: =$C64*AF64 -> 0 | AI64: =$C64*AH64 -> 0 | AK64: =$C64*AJ64 -> 0 | AM64: =$C64*AL64 -> 0 | AN64: =SUM(D64,F64,H64,J64,L64,N64,P64,R64,T64,V64,X64,Z64,AB64,AD64,AF64,AH64,AJ64,AL64) -> 0 | AO64: =$C64*AN64 -> 0
A65: =PQ!B72 -> D.1.3 | B65: =PQ!C72 -> Escavação, carga e transporte de material de 1ª categoria - DMT de 1.000 a 1.200 m - com escavadeira e caminhão basculante de 14 m³ | C65: =RESUMO!N67 -> -22921.262 | E65: =$C65*D65 -> 0 | G65: =$C65*F65 -> 0 | I65: =$C65*H65 -> 0 | K65: =$C65*J65 -> 0 | M65: =$C65*L65 -> 0 | O65: =$C65*N65 -> 0 | Q65: =$C65*P65 -> 0 | S65: =$C65*R65 -> 0 | U65: =$C65*T65 -> 0 | V65: 1 | W65: =$C65*V65 -> -22921.262 | Y65: =$C65*X65 -> 0 | AA65: =$C65*Z65 -> 0 | AC65: =$C65*AB65 -> 0 | AE65: =$C65*AD65 -> 0 | AG65: =$C65*AF65 -> 0 | AI65: =$C65*AH65 -> 0 | AK65: =$C65*AJ65 -> 0 | AM65: =$C65*AL65 -> 0 | AN65: =SUM(D65,F65,H65,J65,L65,N65,P65,R65,T65,V65,X65,Z65,AB65,AD65,AF65,AH65,AJ65,AL65) -> 1 | AO65: =$C65*AN65 -> -22921.262
A66: =PQ!B73 -> D.1.4 | B66: =PQ!C73 -> Regularização de bota-fora com espalhamento e execução de hidrossemeadura | C66: =RESUMO!N68 -> 0 | E66: =$C66*D66 -> 0 | G66: =$C66*F66 -> 0 | I66: =$C66*H66 -> 0 | K66: =$C66*J66 -> 0 | M66: =$C66*L66 -> 0 | O66: =$C66*N66 -> 0 | Q66: =$C66*P66 -> 0 | S66: =$C66*R66 -> 0 | U66: =$C66*T66 -> 0 | W66: =$C66*V66 -> 0 | Y66: =$C66*X66 -> 0 | AA66: =$C66*Z66 -> 0 | AC66: =$C66*AB66 -> 0 | AE66: =$C66*AD66 -> 0 | AG66: =$C66*AF66 -> 0 | AI66: =$C66*AH66 -> 0 | AK66: =$C66*AJ66 -> 0 | AM66: =$C66*AL66 -> 0 | AN66: =SUM(D66,F66,H66,J66,L66,N66,P66,R66,T66,V66,X66,Z66,AB66,AD66,AF66,AH66,AJ66,AL66) -> 0 | AO66: =$C66*AN66 -> 0
A67: =PQ!B74 -> D.1.5 | B67: =PQ!C74 -> Regularização de bota-fora | C67: =RESUMO!N69 -> 4841.9347 | E67: =$C67*D67 -> 0 | G67: =$C67*F67 -> 0 | I67: =$C67*H67 -> 0 | K67: =$C67*J67 -> 0 | M67: =$C67*L67 -> 0 | O67: =$C67*N67 -> 0 | Q67: =$C67*P67 -> 0 | S67: =$C67*R67 -> 0 | U67: =$C67*T67 -> 0 | V67: 1 | W67: =$C67*V67 -> 4841.9347 | Y67: =$C67*X67 -> 0 | AA67: =$C67*Z67 -> 0 | AC67: =$C67*AB67 -> 0 | AE67: =$C67*AD67 -> 0 | AG67: =$C67*AF67 -> 0 | AI67: =$C67*AH67 -> 0 | AK67: =$C67*AJ67 -> 0 | AM67: =$C67*AL67 -> 0 | AN67: =SUM(D67,F67,H67,J67,L67,N67,P67,R67,T67,V67,X67,Z67,AB67,AD67,AF67,AH67,AJ67,AL67) -> 1 | AO67: =$C67*AN67 -> 4841.9347
A68: =PQ!B75 -> D.2 | B68: =PQ!C75 -> Pavimento | C68: =RESUMO!N70 -> 0 | E68: =SUBTOTAL(9,E69:E75) -> 0 | G68: =SUBTOTAL(9,G69:G75) -> 0 | I68: =SUBTOTAL(9,I69:I75) -> 0 | K68: =SUBTOTAL(9,K69:K75) -> 0 | M68: =SUBTOTAL(9,M69:M75) -> 0 | O68: =SUBTOTAL(9,O69:O75) -> 0 | Q68: =SUBTOTAL(9,Q69:Q75) -> 0 | S68: =SUBTOTAL(9,S69:S75) -> 0 | U68: =SUBTOTAL(9,U69:U75) -> 0 | W68: =SUBTOTAL(9,W69:W75) -> 0 | Y68: =SUBTOTAL(9,Y69:Y75) -> 0 | AA68: =SUBTOTAL(9,AA69:AA75) -> 0 | AC68: =SUBTOTAL(9,AC69:AC75) -> 0 | AE68: =SUBTOTAL(9,AE69:AE75) -> 0 | AG68: =SUBTOTAL(9,AG69:AG75) -> 0 | AI68: =SUBTOTAL(9,AI69:AI75) -> 0 | AK68: =SUBTOTAL(9,AK69:AK75) -> 0 | AM68: =SUBTOTAL(9,AM69:AM75) -> 0 | AO68: =SUBTOTAL(9,AO69:AO75) -> 0
A69: =PQ!B76 -> D.2.1 | B69: =PQ!C76 -> Fresagem contínua de revestimento betuminoso | C69: =RESUMO!N71 -> 0 | E69: =$C69*D69 -> 0 | G69: =$C69*F69 -> 0 | I69: =$C69*H69 -> 0 | K69: =$C69*J69 -> 0 | M69: =$C69*L69 -> 0 | O69: =$C69*N69 -> 0 | Q69: =$C69*P69 -> 0 | S69: =$C69*R69 -> 0 | U69: =$C69*T69 -> 0 | W69: =$C69*V69 -> 0 | Y69: =$C69*X69 -> 0 | AA69: =$C69*Z69 -> 0 | AC69: =$C69*AB69 -> 0 | AE69: =$C69*AD69 -> 0 | AG69: =$C69*AF69 -> 0 | AI69: =$C69*AH69 -> 0 | AK69: =$C69*AJ69 -> 0 | AM69: =$C69*AL69 -> 0 | AN69: =SUM(D69,F69,H69,J69,L69,N69,P69,R69,T69,V69,X69,Z69,AB69,AD69,AF69,AH69,AJ69,AL69) -> 0 | AO69: =$C69*AN69 -> 0
A70: =PQ!B77 -> D.2.2 | B70: =PQ!C77 -> Preparo e melhoramento do subleito | C70: =RESUMO!N72 -> 0 | E70: =$C70*D70 -> 0 | G70: =$C70*F70 -> 0 | I70: =$C70*H70 -> 0 | K70: =$C70*J70 -> 0 | M70: =$C70*L70 -> 0 | O70: =$C70*N70 -> 0 | Q70: =$C70*P70 -> 0 | S70: =$C70*R70 -> 0 | U70: =$C70*T70 -> 0 | W70: =$C70*V70 -> 0 | Y70: =$C70*X70 -> 0 | AA70: =$C70*Z70 -> 0 | AC70: =$C70*AB70 -> 0 | AE70: =$C70*AD70 -> 0 | AG70: =$C70*AF70 -> 0 | AI70: =$C70*AH70 -> 0 | AK70: =$C70*AJ70 -> 0 | AM70: =$C70*AL70 -> 0 | AN70: =SUM(D70,F70,H70,J70,L70,N70,P70,R70,T70,V70,X70,Z70,AB70,AD70,AF70,AH70,AJ70,AL70) -> 0 | AO70: =$C70*AN70 -> 0
A71: =PQ!B78 -> D.2.3 | B71: =PQ!C78 -> Rachão ou pedra de mão | C71: =RESUMO!N73 -> 0 | E71: =$C71*D71 -> 0 | G71: =$C71*F71 -> 0 | I71: =$C71*H71 -> 0 | K71: =$C71*J71 -> 0 | M71: =$C71*L71 -> 0 | O71: =$C71*N71 -> 0 | Q71: =$C71*P71 -> 0 | S71: =$C71*R71 -> 0 | U71: =$C71*T71 -> 0 | W71: =$C71*V71 -> 0 | Y71: =$C71*X71 -> 0 | AA71: =$C71*Z71 -> 0 | AC71: =$C71*AB71 -> 0 | AE71: =$C71*AD71 -> 0 | AG71: =$C71*AF71 -> 0 | AI71: =$C71*AH71 -> 0 | AK71: =$C71*AJ71 -> 0 | AM71: =$C71*AL71 -> 0 | AN71: =SUM(D71,F71,H71,J71,L71,N71,P71,R71,T71,V71,X71,Z71,AB71,AD71,AF71,AH71,AJ71,AL71) -> 0 | AO71: =$C71*AN71 -> 0
A72: =PQ!B79 -> D.2.4 | B72: =PQ!C79 -> Sub-base ou base de brita graduada simples (BGS) | C72: =RESUMO!N74 -> 0 | E72: =$C72*D72 -> 0 | G72: =$C72*F72 -> 0 | I72: =$C72*H72 -> 0 | K72: =$C72*J72 -> 0 | M72: =$C72*L72 -> 0 | O72: =$C72*N72 -> 0 | Q72: =$C72*P72 -> 0 | S72: =$C72*R72 -> 0 | U72: =$C72*T72 -> 0 | W72: =$C72*V72 -> 0 | Y72: =$C72*X72 -> 0 | AA72: =$C72*Z72 -> 0 | AC72: =$C72*AB72 -> 0 | AE72: =$C72*AD72 -> 0 | AG72: =$C72*AF72 -> 0 | AI72: =$C72*AH72 -> 0 | AK72: =$C72*AJ72 -> 0 | AM72: =$C72*AL72 -> 0 | AN72: =SUM(D72,F72,H72,J72,L72,N72,P72,R72,T72,V72,X72,Z72,AB72,AD72,AF72,AH72,AJ72,AL72) -> 0 | AO72: =$C72*AN72 -> 0
A73: =PQ!B80 -> D.2.5 | B73: =PQ!C80 -> Imprimadura betuminosa impermeabilizante | C73: =RESUMO!N75 -> 0 | E73: =$C73*D73 -> 0 | G73: =$C73*F73 -> 0 | I73: =$C73*H73 -> 0 | K73: =$C73*J73 -> 0 | M73: =$C73*L73 -> 0 | O73: =$C73*N73 -> 0 | Q73: =$C73*P73 -> 0 | S73: =$C73*R73 -> 0 | U73: =$C73*T73 -> 0 | W73: =$C73*V73 -> 0 | Y73: =$C73*X73 -> 0 | AA73: =$C73*Z73 -> 0 | AC73: =$C73*AB73 -> 0 | AE73: =$C73*AD73 -> 0 | AG73: =$C73*AF73 -> 0 | AI73: =$C73*AH73 -> 0 | AK73: =$C73*AJ73 -> 0 | AM73: =$C73*AL73 -> 0 | AN73: =SUM(D73,F73,H73,J73,L73,N73,P73,R73,T73,V73,X73,Z73,AB73,AD73,AF73,AH73,AJ73,AL73) -> 0 | AO73: =$C73*AN73 -> 0
A74: =PQ!B81 -> D.2.6 | B74: =PQ!C81 -> Imprimadura betuminosa ligante | C74: =RESUMO!N76 -> 0 | E74: =$C74*D74 -> 0 | G74: =$C74*F74 -> 0 | I74: =$C74*H74 -> 0 | K74: =$C74*J74 -> 0 | M74: =$C74*L74 -> 0 | O74: =$C74*N74 -> 0 | Q74: =$C74*P74 -> 0 | S74: =$C74*R74 -> 0 | U74: =$C74*T74 -> 0 | W74: =$C74*V74 -> 0 | Y74: =$C74*X74 -> 0 | AA74: =$C74*Z74 -> 0 | AC74: =$C74*AB74 -> 0 | AE74: =$C74*AD74 -> 0 | AG74: =$C74*AF74 -> 0 | AI74: =$C74*AH74 -> 0 | AK74: =$C74*AJ74 -> 0 | AM74: =$C74*AL74 -> 0 | AN74: =SUM(D74,F74,H74,J74,L74,N74,P74,R74,T74,V74,X74,Z74,AB74,AD74,AF74,AH74,AJ74,AL74) -> 0 | AO74: =$C74*AN74 -> 0
A75: =PQ!B82 -> D.2.7 | B75: =PQ!C82 -> CBUQ Faixa C/D c/ DOP ou polímero similar | C75: =RESUMO!N77 -> 0 | E75: =$C75*D75 -> 0 | G75: =$C75*F75 -> 0 | I75: =$C75*H75 -> 0 | K75: =$C75*J75 -> 0 | M75: =$C75*L75 -> 0 | O75: =$C75*N75 -> 0 | Q75: =$C75*P75 -> 0 | S75: =$C75*R75 -> 0 | U75: =$C75*T75 -> 0 | W75: =$C75*V75 -> 0 | Y75: =$C75*X75 -> 0 | AA75: =$C75*Z75 -> 0 | AC75: =$C75*AB75 -> 0 | AE75: =$C75*AD75 -> 0 | AG75: =$C75*AF75 -> 0 | AI75: =$C75*AH75 -> 0 | AK75: =$C75*AJ75 -> 0 | AM75: =$C75*AL75 -> 0 | AN75: =SUM(D75,F75,H75,J75,L75,N75,P75,R75,T75,V75,X75,Z75,AB75,AD75,AF75,AH75,AJ75,AL75) -> 0 | AO75: =$C75*AN75 -> 0
A76: =PQ!B83 -> D.3 | B76: =PQ!C83 -> Material Betuminoso e Transportes | C76: =RESUMO!N78 -> 0 | E76: =SUBTOTAL(9,E77:E82) -> 0 | G76: =SUBTOTAL(9,G77:G82) -> 0 | I76: =SUBTOTAL(9,I77:I82) -> 0 | K76: =SUBTOTAL(9,K77:K82) -> 0 | M76: =SUBTOTAL(9,M77:M82) -> 0 | O76: =SUBTOTAL(9,O77:O82) -> 0 | Q76: =SUBTOTAL(9,Q77:Q82) -> 0 | S76: =SUBTOTAL(9,S77:S82) -> 0 | U76: =SUBTOTAL(9,U77:U82) -> 0 | W76: =SUBTOTAL(9,W77:W82) -> 0 | Y76: =SUBTOTAL(9,Y77:Y82) -> 0 | AA76: =SUBTOTAL(9,AA77:AA82) -> 0 | AC76: =SUBTOTAL(9,AC77:AC82) -> 0 | AE76: =SUBTOTAL(9,AE77:AE82) -> 0 | AG76: =SUBTOTAL(9,AG77:AG82) -> 0 | AI76: =SUBTOTAL(9,AI77:AI82) -> 0 | AK76: =SUBTOTAL(9,AK77:AK82) -> 0 | AM76: =SUBTOTAL(9,AM77:AM82) -> 0 | AO76: =SUBTOTAL(9,AO77:AO82) -> 0
A77: =PQ!B84 -> D.3.1 | B77: =PQ!C84 -> Fornecimento de CAP modificado com adição de polímero | C77: =RESUMO!N79 -> 0 | E77: =$C77*D77 -> 0 | G77: =$C77*F77 -> 0 | I77: =$C77*H77 -> 0 | K77: =$C77*J77 -> 0 | M77: =$C77*L77 -> 0 | O77: =$C77*N77 -> 0 | Q77: =$C77*P77 -> 0 | S77: =$C77*R77 -> 0 | U77: =$C77*T77 -> 0 | W77: =$C77*V77 -> 0 | Y77: =$C77*X77 -> 0 | AA77: =$C77*Z77 -> 0 | AC77: =$C77*AB77 -> 0 | AE77: =$C77*AD77 -> 0 | AG77: =$C77*AF77 -> 0 | AI77: =$C77*AH77 -> 0 | AK77: =$C77*AJ77 -> 0 | AM77: =$C77*AL77 -> 0 | AN77: =SUM(D77,F77,H77,J77,L77,N77,P77,R77,T77,V77,X77,Z77,AB77,AD77,AF77,AH77,AJ77,AL77) -> 0 | AO77: =$C77*AN77 -> 0
A78: =PQ!B85 -> D.3.2 | B78: =PQ!C85 -> Fornecimento de emulsão asfáltica tipo RR-1C | C78: =RESUMO!N80 -> 0 | E78: =$C78*D78 -> 0 | G78: =$C78*F78 -> 0 | I78: =$C78*H78 -> 0 | K78: =$C78*J78 -> 0 | M78: =$C78*L78 -> 0 | O78: =$C78*N78 -> 0 | Q78: =$C78*P78 -> 0 | S78: =$C78*R78 -> 0 | U78: =$C78*T78 -> 0 | W78: =$C78*V78 -> 0 | Y78: =$C78*X78 -> 0 | AA78: =$C78*Z78 -> 0 | AC78: =$C78*AB78 -> 0 | AE78: =$C78*AD78 -> 0 | AG78: =$C78*AF78 -> 0 | AI78: =$C78*AH78 -> 0 | AK78: =$C78*AJ78 -> 0 | AM78: =$C78*AL78 -> 0 | AN78: =SUM(D78,F78,H78,J78,L78,N78,P78,R78,T78,V78,X78,Z78,AB78,AD78,AF78,AH78,AJ78,AL78) -> 0 | AO78: =$C78*AN78 -> 0
A79: =PQ!B86 -> D.3.3 | B79: =PQ!C86 -> Fornecimento de emulsão asfáltica Imprimer | C79: =RESUMO!N81 -> 0 | E79: =$C79*D79 -> 0 | G79: =$C79*F79 -> 0 | I79: =$C79*H79 -> 0 | K79: =$C79*J79 -> 0 | M79: =$C79*L79 -> 0 | O79: =$C79*N79 -> 0 | Q79: =$C79*P79 -> 0 | S79: =$C79*R79 -> 0 | U79: =$C79*T79 -> 0 | W79: =$C79*V79 -> 0 | Y79: =$C79*X79 -> 0 | AA79: =$C79*Z79 -> 0 | AC79: =$C79*AB79 -> 0 | AE79: =$C79*AD79 -> 0 | AG79: =$C79*AF79 -> 0 | AI79: =$C79*AH79 -> 0 | AK79: =$C79*AJ79 -> 0 | AM79: =$C79*AL79 -> 0 | AN79: =SUM(D79,F79,H79,J79,L79,N79,P79,R79,T79,V79,X79,Z79,AB79,AD79,AF79,AH79,AJ79,AL79) -> 0 | AO79: =$C79*AN79 -> 0
A80: =PQ!B87 -> D.3.4 | B80: =PQ!C87 -> Transporte com caminhão basculante de 14 m³ - rodovia pavimentada - Agregados | C80: =RESUMO!N82 -> 0 | E80: =$C80*D80 -> 0 | G80: =$C80*F80 -> 0 | I80: =$C80*H80 -> 0 | K80: =$C80*J80 -> 0 | M80: =$C80*L80 -> 0 | O80: =$C80*N80 -> 0 | Q80: =$C80*P80 -> 0 | S80: =$C80*R80 -> 0 | U80: =$C80*T80 -> 0 | W80: =$C80*V80 -> 0 | Y80: =$C80*X80 -> 0 | AA80: =$C80*Z80 -> 0 | AC80: =$C80*AB80 -> 0 | AE80: =$C80*AD80 -> 0 | AG80: =$C80*AF80 -> 0 | AI80: =$C80*AH80 -> 0 | AK80: =$C80*AJ80 -> 0 | AM80: =$C80*AL80 -> 0 | AN80: =SUM(D80,F80,H80,J80,L80,N80,P80,R80,T80,V80,X80,Z80,AB80,AD80,AF80,AH80,AJ80,AL80) -> 0 | AO80: =$C80*AN80 -> 0
A81: =PQ!B88 -> D.3.5 | B81: =PQ!C88 -> Transporte com caminhão basculante de 14 m³ - rodovia pavimentada - Massa Asfaltica | C81: =RESUMO!N83 -> 0 | E81: =$C81*D81 -> 0 | G81: =$C81*F81 -> 0 | I81: =$C81*H81 -> 0 | K81: =$C81*J81 -> 0 | M81: =$C81*L81 -> 0 | O81: =$C81*N81 -> 0 | Q81: =$C81*P81 -> 0 | S81: =$C81*R81 -> 0 | U81: =$C81*T81 -> 0 | W81: =$C81*V81 -> 0 | Y81: =$C81*X81 -> 0 | AA81: =$C81*Z81 -> 0 | AC81: =$C81*AB81 -> 0 | AE81: =$C81*AD81 -> 0 | AG81: =$C81*AF81 -> 0 | AI81: =$C81*AH81 -> 0 | AK81: =$C81*AJ81 -> 0 | AM81: =$C81*AL81 -> 0 | AN81: =SUM(D81,F81,H81,J81,L81,N81,P81,R81,T81,V81,X81,Z81,AB81,AD81,AF81,AH81,AJ81,AL81) -> 0 | AO81: =$C81*AN81 -> 0
A82: =PQ!B89 -> D.3.6 | B82: =PQ!C89 -> Transporte com caminhão basculante de 14 m³ - rodovia pavimentada - Materiais Betuminosos | C82: =RESUMO!N84 -> 0 | E82: =$C82*D82 -> 0 | G82: =$C82*F82 -> 0 | I82: =$C82*H82 -> 0 | K82: =$C82*J82 -> 0 | M82: =$C82*L82 -> 0 | O82: =$C82*N82 -> 0 | Q82: =$C82*P82 -> 0 | S82: =$C82*R82 -> 0 | U82: =$C82*T82 -> 0 | W82: =$C82*V82 -> 0 | Y82: =$C82*X82 -> 0 | AA82: =$C82*Z82 -> 0 | AC82: =$C82*AB82 -> 0 | AE82: =$C82*AD82 -> 0 | AG82: =$C82*AF82 -> 0 | AI82: =$C82*AH82 -> 0 | AK82: =$C82*AJ82 -> 0 | AM82: =$C82*AL82 -> 0 | AN82: =SUM(D82,F82,H82,J82,L82,N82,P82,R82,T82,V82,X82,Z82,AB82,AD82,AF82,AH82,AJ82,AL82) -> 0 | AO82: =$C82*AN82 -> 0
A83: =PQ!B90 -> D.4 | B83: =PQ!C90 -> Drenagem e OACs | C83: =RESUMO!N85 -> 8340.4 | E83: =SUBTOTAL(9,E84:E85) -> 0 | G83: =SUBTOTAL(9,G84:G85) -> 0 | I83: =SUBTOTAL(9,I84:I85) -> 0 | K83: =SUBTOTAL(9,K84:K85) -> 0 | M83: =SUBTOTAL(9,M84:M85) -> 0 | O83: =SUBTOTAL(9,O84:O85) -> 0 | Q83: =SUBTOTAL(9,Q84:Q85) -> 0 | S83: =SUBTOTAL(9,S84:S85) -> 0 | U83: =SUBTOTAL(9,U84:U85) -> 0 | W83: =SUBTOTAL(9,W84:W85) -> 8340.4 | Y83: =SUBTOTAL(9,Y84:Y85) -> 0 | AA83: =SUBTOTAL(9,AA84:AA85) -> 0 | AC83: =SUBTOTAL(9,AC84:AC85) -> 0 | AE83: =SUBTOTAL(9,AE84:AE85) -> 0 | AG83: =SUBTOTAL(9,AG84:AG85) -> 0 | AI83: =SUBTOTAL(9,AI84:AI85) -> 0 | AK83: =SUBTOTAL(9,AK84:AK85) -> 0 | AM83: =SUBTOTAL(9,AM84:AM85) -> 0 | AO83: =SUBTOTAL(9,AO84:AO85) -> 8340.4
A84: =PQ!B91 -> D.4.1 | B84: =PQ!C91 -> Sarjeta triangular de concreto - STC 88-20 - escavação mecânica - areia e brita comerciais | C84: =RESUMO!N86 -> 8340.4 | E84: =$C84*D84 -> 0 | G84: =$C84*F84 -> 0 | I84: =$C84*H84 -> 0 | K84: =$C84*J84 -> 0 | M84: =$C84*L84 -> 0 | O84: =$C84*N84 -> 0 | Q84: =$C84*P84 -> 0 | S84: =$C84*R84 -> 0 | U84: =$C84*T84 -> 0 | V84: 1 | W84: =$C84*V84 -> 8340.4 | Y84: =$C84*X84 -> 0 | AA84: =$C84*Z84 -> 0 | AC84: =$C84*AB84 -> 0 | AE84: =$C84*AD84 -> 0 | AG84: =$C84*AF84 -> 0 | AI84: =$C84*AH84 -> 0 | AK84: =$C84*AJ84 -> 0 | AM84: =$C84*AL84 -> 0 | AN84: =SUM(D84,F84,H84,J84,L84,N84,P84,R84,T84,V84,X84,Z84,AB84,AD84,AF84,AH84,AJ84,AL84) -> 1 | AO84: =$C84*AN84 -> 8340.4
A85: =PQ!B92 -> D.4.2 | B85: =PQ!C92 -> Dissipador de energia - DES 88-264 - areia, brita e pedra de mão comerciais | C85: =RESUMO!N87 -> 0 | E85: =$C85*D85 -> 0 | G85: =$C85*F85 -> 0 | I85: =$C85*H85 -> 0 | K85: =$C85*J85 -> 0 | M85: =$C85*L85 -> 0 | O85: =$C85*N85 -> 0 | Q85: =$C85*P85 -> 0 | S85: =$C85*R85 -> 0 | U85: =$C85*T85 -> 0 | W85: =$C85*V85 -> 0 | Y85: =$C85*X85 -> 0 | AA85: =$C85*Z85 -> 0 | AC85: =$C85*AB85 -> 0 | AE85: =$C85*AD85 -> 0 | AG85: =$C85*AF85 -> 0 | AI85: =$C85*AH85 -> 0 | AK85: =$C85*AJ85 -> 0 | AM85: =$C85*AL85 -> 0 | AN85: =SUM(D85,F85,H85,J85,L85,N85,P85,R85,T85,V85,X85,Z85,AB85,AD85,AF85,AH85,AJ85,AL85) -> 0 | AO85: =$C85*AN85 -> 0
A86: =PQ!B93 -> E. | B86: =PQ!C93 -> Sinalização Horizontal, Vertical e Elementos de Proteção e Segurança | C86: =RESUMO!N88 -> 0 | E86: =SUBTOTAL(9,E87) -> 0 | G86: =SUBTOTAL(9,G87) -> 0 | I86: =SUBTOTAL(9,I87) -> 0 | K86: =SUBTOTAL(9,K87) -> 0 | M86: =SUBTOTAL(9,M87) -> 0 | O86: =SUBTOTAL(9,O87) -> 0 | Q86: =SUBTOTAL(9,Q87) -> 0 | S86: =SUBTOTAL(9,S87) -> 0 | U86: =SUBTOTAL(9,U87) -> 0 | W86: =SUBTOTAL(9,W87) -> 0 | Y86: =SUBTOTAL(9,Y87) -> 0 | AA86: =SUBTOTAL(9,AA87) -> 0 | AC86: =SUBTOTAL(9,AC87) -> 0 | AE86: =SUBTOTAL(9,AE87) -> 0 | AG86: =SUBTOTAL(9,AG87) -> 0 | AI86: =SUBTOTAL(9,AI87) -> 0 | AK86: =SUBTOTAL(9,AK87) -> 0 | AM86: =SUBTOTAL(9,AM87) -> 0 | AO86: =SUBTOTAL(9,AO87) -> 0
A87: =PQ!B94 -> E.1 | B87: =PQ!C94 -> Manutenção/recomposição de sinalização - pintura de faixa com tinta acrílica emulsionada em água - espessura de 0,3 / 0,5 mm | C87: =RESUMO!N89 -> 0 | E87: =$C87*D87 -> 0 | G87: =$C87*F87 -> 0 | I87: =$C87*H87 -> 0 | K87: =$C87*J87 -> 0 | M87: =$C87*L87 -> 0 | O87: =$C87*N87 -> 0 | Q87: =$C87*P87 -> 0 | S87: =$C87*R87 -> 0 | U87: =$C87*T87 -> 0 | W87: =$C87*V87 -> 0 | Y87: =$C87*X87 -> 0 | AA87: =$C87*Z87 -> 0 | AC87: =$C87*AB87 -> 0 | AE87: =$C87*AD87 -> 0 | AG87: =$C87*AF87 -> 0 | AI87: =$C87*AH87 -> 0 | AK87: =$C87*AJ87 -> 0 | AM87: =$C87*AL87 -> 0 | AN87: =SUM(D87,F87,H87,J87,L87,N87,P87,R87,T87,V87,X87,Z87,AB87,AD87,AF87,AH87,AJ87,AL87) -> 0 | AO87: =$C87*AN87 -> 0
A88: =PQ!B95 -> F. | B88: =PQ!C95 -> Mão de Obra e Equipamentos | C88: =RESUMO!N90 -> 102841.21 | E88: =SUBTOTAL(9,E89:E98) -> 0 | G88: =SUBTOTAL(9,G89:G98) -> 0 | I88: =SUBTOTAL(9,I89:I98) -> 0 | K88: =SUBTOTAL(9,K89:K98) -> 0 | M88: =SUBTOTAL(9,M89:M98) -> 0 | O88: =SUBTOTAL(9,O89:O98) -> 0 | Q88: =SUBTOTAL(9,Q89:Q98) -> 0 | S88: =SUBTOTAL(9,S89:S98) -> 0 | U88: =SUBTOTAL(9,U89:U98) -> 0 | W88: =SUBTOTAL(9,W89:W98) -> 102841.21 | Y88: =SUBTOTAL(9,Y89:Y98) -> 0 | AA88: =SUBTOTAL(9,AA89:AA98) -> 0 | AC88: =SUBTOTAL(9,AC89:AC98) -> 0 | AE88: =SUBTOTAL(9,AE89:AE98) -> 0 | AG88: =SUBTOTAL(9,AG89:AG98) -> 0 | AI88: =SUBTOTAL(9,AI89:AI98) -> 0 | AK88: =SUBTOTAL(9,AK89:AK98) -> 0 | AM88: =SUBTOTAL(9,AM89:AM98) -> 0 | AO88: =SUBTOTAL(9,AO89:AO98) -> 102841.21
A89: =PQ!B96 -> F.1 | B89: =PQ!C96 -> Mão de Obra | C89: =RESUMO!N91 -> 12969.48 | E89: =SUBTOTAL(9,E90:E92) -> 0 | G89: =SUBTOTAL(9,G90:G92) -> 0 | I89: =SUBTOTAL(9,I90:I92) -> 0 | K89: =SUBTOTAL(9,K90:K92) -> 0 | M89: =SUBTOTAL(9,M90:M92) -> 0 | O89: =SUBTOTAL(9,O90:O92) -> 0 | Q89: =SUBTOTAL(9,Q90:Q92) -> 0 | S89: =SUBTOTAL(9,S90:S92) -> 0 | U89: =SUBTOTAL(9,U90:U92) -> 0 | W89: =SUBTOTAL(9,W90:W92) -> 12969.48 | Y89: =SUBTOTAL(9,Y90:Y92) -> 0 | AA89: =SUBTOTAL(9,AA90:AA92) -> 0 | AC89: =SUBTOTAL(9,AC90:AC92) -> 0 | AE89: =SUBTOTAL(9,AE90:AE92) -> 0 | AG89: =SUBTOTAL(9,AG90:AG92) -> 0 | AI89: =SUBTOTAL(9,AI90:AI92) -> 0 | AK89: =SUBTOTAL(9,AK90:AK92) -> 0 | AM89: =SUBTOTAL(9,AM90:AM92) -> 0 | AO89: =SUBTOTAL(9,AO90:AO92) -> 12969.48
A90: =PQ!B97 -> F.1.1 | B90: =PQ!C97 -> Encarregado | C90: =RESUMO!N92 -> 2549.4133 | E90: =$C90*D90 -> 0 | G90: =$C90*F90 -> 0 | I90: =$C90*H90 -> 0 | K90: =$C90*J90 -> 0 | M90: =$C90*L90 -> 0 | O90: =$C90*N90 -> 0 | Q90: =$C90*P90 -> 0 | S90: =$C90*R90 -> 0 | U90: =$C90*T90 -> 0 | V90: 1 | W90: =$C90*V90 -> 2549.4133 | Y90: =$C90*X90 -> 0 | AA90: =$C90*Z90 -> 0 | AC90: =$C90*AB90 -> 0 | AE90: =$C90*AD90 -> 0 | AG90: =$C90*AF90 -> 0 | AI90: =$C90*AH90 -> 0 | AK90: =$C90*AJ90 -> 0 | AM90: =$C90*AL90 -> 0 | AN90: =SUM(D90,F90,H90,J90,L90,N90,P90,R90,T90,V90,X90,Z90,AB90,AD90,AF90,AH90,AJ90,AL90) -> 1 | AO90: =$C90*AN90 -> 2549.4133
A91: =PQ!B98 -> F.1.2 | B91: =PQ!C98 -> Oficial | C91: =RESUMO!N93 -> 4415.3867 | E91: =$C91*D91 -> 0 | G91: =$C91*F91 -> 0 | I91: =$C91*H91 -> 0 | K91: =$C91*J91 -> 0 | M91: =$C91*L91 -> 0 | O91: =$C91*N91 -> 0 | Q91: =$C91*P91 -> 0 | S91: =$C91*R91 -> 0 | U91: =$C91*T91 -> 0 | V91: 1 | W91: =$C91*V91 -> 4415.3867 | Y91: =$C91*X91 -> 0 | AA91: =$C91*Z91 -> 0 | AC91: =$C91*AB91 -> 0 | AE91: =$C91*AD91 -> 0 | AG91: =$C91*AF91 -> 0 | AI91: =$C91*AH91 -> 0 | AK91: =$C91*AJ91 -> 0 | AM91: =$C91*AL91 -> 0 | AN91: =SUM(D91,F91,H91,J91,L91,N91,P91,R91,T91,V91,X91,Z91,AB91,AD91,AF91,AH91,AJ91,AL91) -> 1 | AO91: =$C91*AN91 -> 4415.3867
A92: =PQ!B99 -> F.1.3 | B92: =PQ!C99 -> Servente | C92: =RESUMO!N94 -> 6004.68 | E92: =$C92*D92 -> 0 | G92: =$C92*F92 -> 0 | I92: =$C92*H92 -> 0 | K92: =$C92*J92 -> 0 | M92: =$C92*L92 -> 0 | O92: =$C92*N92 -> 0 | Q92: =$C92*P92 -> 0 | S92: =$C92*R92 -> 0 | U92: =$C92*T92 -> 0 | V92: 1 | W92: =$C92*V92 -> 6004.68 | Y92: =$C92*X92 -> 0 | AA92: =$C92*Z92 -> 0 | AC92: =$C92*AB92 -> 0 | AE92: =$C92*AD92 -> 0 | AG92: =$C92*AF92 -> 0 | AI92: =$C92*AH92 -> 0 | AK92: =$C92*AJ92 -> 0 | AM92: =$C92*AL92 -> 0 | AN92: =SUM(D92,F92,H92,J92,L92,N92,P92,R92,T92,V92,X92,Z92,AB92,AD92,AF92,AH92,AJ92,AL92) -> 1 | AO92: =$C92*AN92 -> 6004.68
A93: =PQ!B100 -> F.2 | B93: =PQ!C100 -> Equipamentos | C93: =RESUMO!N95 -> 89871.725 | E93: =SUBTOTAL(9,E94:E98) -> 0 | G93: =SUBTOTAL(9,G94:G98) -> 0 | I93: =SUBTOTAL(9,I94:I98) -> 0 | K93: =SUBTOTAL(9,K94:K98) -> 0 | M93: =SUBTOTAL(9,M94:M98) -> 0 | O93: =SUBTOTAL(9,O94:O98) -> 0 | Q93: =SUBTOTAL(9,Q94:Q98) -> 0 | S93: =SUBTOTAL(9,S94:S98) -> 0 | U93: =SUBTOTAL(9,U94:U98) -> 0 | W93: =SUBTOTAL(9,W94:W98) -> 89871.725 | Y93: =SUBTOTAL(9,Y94:Y98) -> 0 | AA93: =SUBTOTAL(9,AA94:AA98) -> 0 | AC93: =SUBTOTAL(9,AC94:AC98) -> 0 | AE93: =SUBTOTAL(9,AE94:AE98) -> 0 | AG93: =SUBTOTAL(9,AG94:AG98) -> 0 | AI93: =SUBTOTAL(9,AI94:AI98) -> 0 | AK93: =SUBTOTAL(9,AK94:AK98) -> 0 | AM93: =SUBTOTAL(9,AM94:AM98) -> 0 | AO93: =SUBTOTAL(9,AO94:AO98) -> 89871.725
A94: =PQ!B101 -> F.2.1 | B94: =PQ!C101 -> Trator sobre Esteiras com Lâmina - 127 Kw | C94: =RESUMO!N96 -> 5911.528 | E94: =$C94*D94 -> 0 | G94: =$C94*F94 -> 0 | I94: =$C94*H94 -> 0 | K94: =$C94*J94 -> 0 | M94: =$C94*L94 -> 0 | O94: =$C94*N94 -> 0 | Q94: =$C94*P94 -> 0 | S94: =$C94*R94 -> 0 | U94: =$C94*T94 -> 0 | V94: 1 | W94: =$C94*V94 -> 5911.528 | Y94: =$C94*X94 -> 0 | AA94: =$C94*Z94 -> 0 | AC94: =$C94*AB94 -> 0 | AE94: =$C94*AD94 -> 0 | AG94: =$C94*AF94 -> 0 | AI94: =$C94*AH94 -> 0 | AK94: =$C94*AJ94 -> 0 | AM94: =$C94*AL94 -> 0 | AN94: =SUM(D94,F94,H94,J94,L94,N94,P94,R94,T94,V94,X94,Z94,AB94,AD94,AF94,AH94,AJ94,AL94) -> 1 | AO94: =$C94*AN94 -> 5911.528
A95: =PQ!B102 -> F.2.2 | B95: =PQ!C102 -> Escavadeira Hidráulica sobre Esteiras | C95: =RESUMO!N97 -> 10960.909 | E95: =$C95*D95 -> 0 | G95: =$C95*F95 -> 0 | I95: =$C95*H95 -> 0 | K95: =$C95*J95 -> 0 | M95: =$C95*L95 -> 0 | O95: =$C95*N95 -> 0 | Q95: =$C95*P95 -> 0 | S95: =$C95*R95 -> 0 | U95: =$C95*T95 -> 0 | V95: 1 | W95: =$C95*V95 -> 10960.909 | Y95: =$C95*X95 -> 0 | AA95: =$C95*Z95 -> 0 | AC95: =$C95*AB95 -> 0 | AE95: =$C95*AD95 -> 0 | AG95: =$C95*AF95 -> 0 | AI95: =$C95*AH95 -> 0 | AK95: =$C95*AJ95 -> 0 | AM95: =$C95*AL95 -> 0 | AN95: =SUM(D95,F95,H95,J95,L95,N95,P95,R95,T95,V95,X95,Z95,AB95,AD95,AF95,AH95,AJ95,AL95) -> 1 | AO95: =$C95*AN95 -> 10960.909
A96: =PQ!B103 -> F.2.3 | B96: =PQ!C103 -> Caminhão Basculante com Capacidade de 16 M³ - 188 Kw | C96: =RESUMO!N98 -> 59427.141 | E96: =$C96*D96 -> 0 | G96: =$C96*F96 -> 0 | I96: =$C96*H96 -> 0 | K96: =$C96*J96 -> 0 | M96: =$C96*L96 -> 0 | O96: =$C96*N96 -> 0 | Q96: =$C96*P96 -> 0 | S96: =$C96*R96 -> 0 | U96: =$C96*T96 -> 0 | V96: 1 | W96: =$C96*V96 -> 59427.141 | Y96: =$C96*X96 -> 0 | AA96: =$C96*Z96 -> 0 | AC96: =$C96*AB96 -> 0 | AE96: =$C96*AD96 -> 0 | AG96: =$C96*AF96 -> 0 | AI96: =$C96*AH96 -> 0 | AK96: =$C96*AJ96 -> 0 | AM96: =$C96*AL96 -> 0 | AN96: =SUM(D96,F96,H96,J96,L96,N96,P96,R96,T96,V96,X96,Z96,AB96,AD96,AF96,AH96,AJ96,AL96) -> 1 | AO96: =$C96*AN96 -> 59427.141
A97: =PQ!B104 -> F.2.4 | B97: =PQ!C104 -> Rolo Compactador Pé de Carneiro Vibratório Autopropelido por Pneus de 11,6 T - 82 Kw | C97: =RESUMO!N99 -> 10399.75 | E97: =$C97*D97 -> 0 | G97: =$C97*F97 -> 0 | I97: =$C97*H97 -> 0 | K97: =$C97*J97 -> 0 | M97: =$C97*L97 -> 0 | O97: =$C97*N97 -> 0 | Q97: =$C97*P97 -> 0 | S97: =$C97*R97 -> 0 | U97: =$C97*T97 -> 0 | V97: 1 | W97: =$C97*V97 -> 10399.75 | Y97: =$C97*X97 -> 0 | AA97: =$C97*Z97 -> 0 | AC97: =$C97*AB97 -> 0 | AE97: =$C97*AD97 -> 0 | AG97: =$C97*AF97 -> 0 | AI97: =$C97*AH97 -> 0 | AK97: =$C97*AJ97 -> 0 | AM97: =$C97*AL97 -> 0 | AN97: =SUM(D97,F97,H97,J97,L97,N97,P97,R97,T97,V97,X97,Z97,AB97,AD97,AF97,AH97,AJ97,AL97) -> 1 | AO97: =$C97*AN97 -> 10399.75
A98: =PQ!B105 -> F.2.5 | B98: =PQ!C105 -> Motoniveladora - 93 Kw | C98: =RESUMO!N100 -> 3172.3977 | E98: =$C98*D98 -> 0 | G98: =$C98*F98 -> 0 | I98: =$C98*H98 -> 0 | K98: =$C98*J98 -> 0 | M98: =$C98*L98 -> 0 | O98: =$C98*N98 -> 0 | Q98: =$C98*P98 -> 0 | S98: =$C98*R98 -> 0 | U98: =$C98*T98 -> 0 | V98: 1 | W98: =$C98*V98 -> 3172.3977 | Y98: =$C98*X98 -> 0 | AA98: =$C98*Z98 -> 0 | AC98: =$C98*AB98 -> 0 | AE98: =$C98*AD98 -> 0 | AG98: =$C98*AF98 -> 0 | AI98: =$C98*AH98 -> 0 | AK98: =$C98*AJ98 -> 0 | AM98: =$C98*AL98 -> 0 | AN98: =SUM(D98,F98,H98,J98,L98,N98,P98,R98,T98,V98,X98,Z98,AB98,AD98,AF98,AH98,AJ98,AL98) -> 1 | AO98: =$C98*AN98 -> 3172.3977
A100: FATURAMENTO TOTAL | C100: =SUM(C6,C10,C34,C61,C86,C88,) -> 1990219.7 | D100: GOVERNADOR VALADARES | F100: PERIQUITO | H100: NAQUE | J100: BELO HORIENTE | L100: SANTANA DO PARAÍSO | N100: IPATINGA | P100: CORONEL FABRICIANO | R100: TIMÓTEO | T100: JAGUARAÇU | V100: ANTÔNIO DIAS | X100: NOVA ERA | Z100: BELA VISTA DE MINAS | AB100: JOÃO MONLEVADE | AD100: SÃO GONÇALO DO RIO ABAIXO | AF100: BARÃO DE COCAIS | AH100: BOM JESUS DO AMPARO | AJ100: NOVA UNIÃO | AL100: CAETÉ | AN100: ACUMULADO
D101: =IF(ISERROR(E101/$AO$101),"",E101/$AO$101) -> 0 | E101: =SUM(E6,E10,E34,E61,E86,E88) -> 0 | F101: =IF(ISERROR(G101/$AO$101),"",G101/$AO$101) -> 0 | G101: =SUM(G6,G10,G34,G61,G86,G88) -> 0 | H101: =IF(ISERROR(I101/$AO$101),"",I101/$AO$101) -> 0 | I101: =SUM(I6,I10,I34,I61,I86,I88) -> 0 | J101: =IF(ISERROR(K101/$AO$101),"",K101/$AO$101) -> 0 | K101: =SUM(K6,K10,K34,K61,K86,K88) -> 0 | L101: =IF(ISERROR(M101/$AO$101),"",M101/$AO$101) -> 0 | M101: =SUM(M6,M10,M34,M61,M86,M88) -> 0 | N101: =IF(ISERROR(O101/$AO$101),"",O101/$AO$101) -> 0 | O101: =SUM(O6,O10,O34,O61,O86,O88) -> 0 | P101: =IF(ISERROR(Q101/$AO$101),"",Q101/$AO$101) -> 0 | Q101: =SUM(Q6,Q10,Q34,Q61,Q86,Q88) -> 0 | R101: =IF(ISERROR(S101/$AO$101),"",S101/$AO$101) -> 0 | S101: =SUM(S6,S10,S34,S61,S86,S88) -> 0 | T101: =IF(ISERROR(U101/$AO$101),"",U101/$AO$101) -> 0 | U101: =SUM(U6,U10,U34,U61,U86,U88) -> 0 | V101: =IF(ISERROR(W101/$AO$101),"",W101/$AO$101) -> 1 | W101: =SUM(W6,W10,W34,W61,W86,W88) -> 1990219.7 | X101: =IF(ISERROR(Y101/$AO$101),"",Y101/$AO$101) -> 0 | Y101: =SUM(Y6,Y10,Y34,Y61,Y86,Y88) -> 0 | Z101: =IF(ISERROR(AA101/$AO$101),"",AA101/$AO$101) -> 0 | AA101: =SUM(AA6,AA10,AA34,AA61,AA86,AA88) -> 0 | AB101: =IF(ISERROR(AC101/$AO$101),"",AC101/$AO$101) -> 0 | AC101: =SUM(AC6,AC10,AC34,AC61,AC86,AC88) -> 0 | AD101: =IF(ISERROR(AE101/$AO$101),"",AE101/$AO$101) -> 0 | AE101: =SUM(AE6,AE10,AE34,AE61,AE86,AE88) -> 0 | AF101: =IF(ISERROR(AG101/$AO$101),"",AG101/$AO$101) -> 0 | AG101: =SUM(AG6,AG10,AG34,AG61,AG86,AG88) -> 0 | AH101: =IF(ISERROR(AI101/$AO$101),"",AI101/$AO$101) -> 0 | AI101: =SUM(AI6,AI10,AI34,AI61,AI86,AI88) -> 0 | AJ101: =IF(ISERROR(AK101/$AO$101),"",AK101/$AO$101) -> 0 | AK101: =SUM(AK6,AK10,AK34,AK61,AK86,AK88) -> 0 | AL101: =IF(ISERROR(AM101/$AO$101),"",AM101/$AO$101) -> 0 | AM101: =SUM(AM6,AM10,AM34,AM61,AM86,AM88) -> 0 | AN101: =IF(ISERROR(AO101/$AO$101),"",AO101/$AO$101) -> 1 | AO101: =SUM(E101,G101,I101,K101,M101,O101,Q101,S101,U101,W101,Y101,AA101,AC101,AE101,AG101,AI101,AK101,AM101,) -> 1990219.7
A102: BDI - 18,20% | C102: =C100*1.182 -> 2352439.6 | D102: =IF(ISERROR(E102/$AO$102),"",E102/$AO$102) -> 0 | E102: =E101*1.182 -> 0 | F102: =IF(ISERROR(G102/$AO$102),"",G102/$AO$102) -> 0 | G102: =G101*1.182 -> 0 | H102: =IF(ISERROR(I102/$AO$102),"",I102/$AO$102) -> 0 | I102: =I101*1.182 -> 0 | J102: =IF(ISERROR(K102/$AO$102),"",K102/$AO$102) -> 0 | K102: =K101*1.182 -> 0 | L102: =IF(ISERROR(M102/$AO$102),"",M102/$AO$102) -> 0 | M102: =M101*1.182 -> 0 | N102: =IF(ISERROR(O102/$AO$102),"",O102/$AO$102) -> 0 | O102: =O101*1.182 -> 0 | P102: =IF(ISERROR(Q102/$AO$102),"",Q102/$AO$102) -> 0 | Q102: =Q101*1.182 -> 0 | R102: =IF(ISERROR(S102/$AO$102),"",S102/$AO$102) -> 0 | S102: =S101*1.182 -> 0 | T102: =IF(ISERROR(U102/$AO$102),"",U102/$AO$102) -> 0 | U102: =U101*1.182 -> 0 | V102: =IF(ISERROR(W102/$AO$102),"",W102/$AO$102) -> 1 | W102: =W101*1.182 -> 2352439.6 | X102: =IF(ISERROR(Y102/$AO$102),"",Y102/$AO$102) -> 0 | Y102: =Y101*1.182 -> 0 | Z102: =IF(ISERROR(AA102/$AO$102),"",AA102/$AO$102) -> 0 | AA102: =AA101*1.182 -> 0 | AB102: =IF(ISERROR(AC102/$AO$102),"",AC102/$AO$102) -> 0 | AC102: =AC101*1.182 -> 0 | AD102: =IF(ISERROR(AE102/$AO$102),"",AE102/$AO$102) -> 0 | AE102: =AE101*1.182 -> 0 | AF102: =IF(ISERROR(AG102/$AO$101),"",AG102/$AO$101) -> 0 | AG102: =AG101*1.182 -> 0 | AH102: =IF(ISERROR(AI102/$AO$101),"",AI102/$AO$101) -> 0 | AI102: =AI101*1.182 -> 0 | AJ102: =IF(ISERROR(AK102/$AO$101),"",AK102/$AO$101) -> 0 | AK102: =AK101*1.182 -> 0 | AL102: =IF(ISERROR(AM102/$AO$101),"",AM102/$AO$101) -> 0 | AM102: =AM101*1.182 -> 0 | AN102: =IF(ISERROR(AO102/$C$102),"",AO102/$C$102) -> 1 | AO102: =SUM(E102,G102,I102,K102,M102,O102,Q102,S102,U102,W102,Y102,AA102,AC102,AE102,AG102,AI102,AK102,AM102,) -> 2352439.6

Sheet A.1
B2: QUADRO RESUMO | E2: CONTRATO | J2: HISTÓRICO DE MEDIÇÃO: | P2: NAVEGAÇÃO
E3: QUANTIDADES | G3: R$ FINANCEIRO
B4: QUANTIDADE DE PROJETO: | E4: =IF($G$13="","",VLOOKUP($G$13,RESUMO!$C:$G,5,FALSE)) -> 1 | G4: =E4*$M$13 -> 22570.81
B5: QUANTIDADE ACUMULADA: | E5: =SUMIFS(I:I,N:N,"<>") -> 1 | G5: =E5*$M$13 -> 22570.81
B6: QUANTIDADE ACUM. ANTERIOR: | E6: =E5-E9 -> 1 | G6: =E6*$M$13 -> 22570.81
B7: SALDO CONTRATUAL: | E7: =E4-E5 -> 0 | G7: =E7*$M$13 -> 0
B8: NÃO MEDIDO: | E8: =SUM(I:I)-E5 -> 0 | G8: =E8*$M$13 -> 0
B9: MEDIÇÃO ATUAL: | E9: =SUMIF(N:N,CAPA!$I$2,I:I) -> 0 | G9: =E9*$M$13 -> 0
B11: GRUPO | G11: ITEM
B12: CÓDIGO | C12: DESCRIÇÃO | G12: CÓDIGO | H12: DESCRIÇÃO | L12: UNIDADE | M12: R$ UNIT.
B13: =RESUMO!C8 -> A. | C13: =IF($B$13="","",VLOOKUP($B$13,RESUMO!$C:$F,2,FALSE)) -> Custos Indiretos | G13: =RESUMO!C9 -> A.1 | H13: =IF($G$13="","",VLOOKUP($G$13,RESUMO!$C:$F,2,FALSE)) -> Mobilização e desmobilização | L13: =IF($G$13="","",VLOOKUP($G$13,RESUMO!$C:$F,3,FALSE)) -> vb. | M13: =IF($G$13="","",VLOOKUP($G$13,RESUMO!$C:$F,4,FALSE)) -> 22570.81
B15: LOCAL | C15: EIXO | D15: ESTACA/KM INICIAL | F15: ESTACA/KM FINAL | H15: LADO | I15: QUANTIDADE | J15: QUANTIDADE ACUMULADA | K15: OBSERVAÇÃO | N15: MEDIÇÃO | P15: ITEM REFERÊNCIA
D16: INTEIRA | E16: FRAÇÃO | F16: INTEIRA | G16: FRAÇÃO | P16: CÓDIGO | Q16: DESCRIÇÃO
B17: BR381 | C17: DIVERSOS | I17: 0.5 | J17: =IF(OR(B17="",I17=""),"",IF(AND(J16="",N17=""),J16,SUM(I17,J16))) -> 0.5 | K17: EXECUÇÃO DE DESVIOS E TALUDES | N17: 1 | P17: A.1 | Q17: =IF($P17="","",VLOOKUP($P17,RESUMO!$C:$D,2,FALSE)) -> Mobilização e desmobilização | S17: =HYPERLINK("#"&"'"&P17&"'"&"!A1","LINK") -> LINK
B18: BR381 | C18: DIVERSOS | I18: 0.5 | J18: =IF(B18="","",IF(OR(J17="",N18=""),J17,SUM(I18,J17))) -> 1 | K18: EXECUÇÃO DE DESVIOS E TALUDES | N18: 2 | P18: A.2 | Q18: =IF($P18="","",VLOOKUP($P18,RESUMO!$C:$D,2,FALSE)) -> Sinalização e desvio de tráfego | S18: =HYPERLINK("#"&"'"&P18&"'"&"!A1","LINK") -> LINK
J19: =IF(B19="","",IF(OR(J18="",N19=""),J18,SUM(I19,J18))) | P19: A.3 | Q19: =IF($P19="","",VLOOKUP($P19,RESUMO!$C:$D,2,FALSE)) -> Administração local | S19: =HYPERLINK("#"&"'"&P19&"'"&"!A1","LINK") -> LINK
J20: =IF(B20="","",IF(OR(J19="",N20=""),J19,SUM(I20,J19)))
J21: =IF(B21="","",IF(OR(J20="",N21=""),J20,SUM(I21,J20)))
J22: =IF(B22="","",IF(OR(J21="",N22=""),J21,SUM(I22,J21)))
J23: =IF(B23="","",IF(OR(J22="",N23=""),J22,SUM(I23,J22)))
J24: =IF(B24="","",IF(OR(J23="",N24=""),J23,SUM(I24,J23)))
J25: =IF(B25="","",IF(OR(J24="",N25=""),J24,SUM(I25,J24)))
J26: =IF(B26="","",IF(OR(J25="",N26=""),J25,SUM(I26,J25)))
J27: =IF(B27="","",IF(OR(J26="",N27=""),J26,SUM(I27,J26)))
J28: =IF(B28="","",IF(OR(J27="",N28=""),J27,SUM(I28,J27)))
J29: =IF(B29="","",IF(OR(J28="",N29=""),J28,SUM(I29,J28)))
J30: =IF(B30="","",IF(OR(J29="",N30=""),J29,SUM(I30,J29)))

Sheet A.2
B2: QUADRO RESUMO | E2: CONTRATO | J2: HISTÓRICO DE MEDIÇÃO: | P2: NAVEGAÇÃO
E3: QUANTIDADES | G3: R$ FINANCEIRO
B4: QUANTIDADE DE PROJETO: | E4: =IF($G$13="","",VLOOKUP($G$13,RESUMO!$C:$G,5,FALSE)) -> 1 | G4: =E4*$M$13 -> 45141.63
B5: QUANTIDADE ACUMULADA: | E5: =SUMIFS(I:I,N:N,"<>") -> 1 | G5: =E5*$M$13 -> 45141.63
B6: QUANTIDADE ACUM. ANTERIOR: | E6: =E5-E9 -> 1 | G6: =E6*$M$13 -> 45141.63
B7: SALDO CONTRATUAL: | E7: =E4-E5 -> 0 | G7: =E7*$M$13 -> 0
B8: NÃO MEDIDO: | E8: =SUM(I:I)-E5 -> 0 | G8: =E8*$M$13 -> 0
B9: MEDIÇÃO ATUAL: | E9: =SUMIF(N:N,CAPA!$I$2,I:I) -> 0 | G9: =E9*$M$13 -> 0
B11: GRUPO | G11: ITEM
B12: CÓDIGO | C12: DESCRIÇÃO | G12: CÓDIGO | H12: DESCRIÇÃO | L12: UNIDADE | M12: R$ UNIT.
B13: =RESUMO!C8 -> A. | C13: =IF($B$13="","",VLOOKUP($B$13,RESUMO!$C:$F,2,FALSE)) -> Custos Indiretos | G13: =RESUMO!C10 -> A.2 | H13: =IF($G$13="","",VLOOKUP($G$13,RESUMO!$C:$F,2,FALSE)) -> Sinalização e desvio de tráfego | L13: =IF($G$13="","",VLOOKUP($G$13,RESUMO!$C:$F,3,FALSE)) -> vb. | M13: =IF($G$13="","",VLOOKUP($G$13,RESUMO!$C:$F,4,FALSE)) -> 45141.63
B15: LOCAL | C15: EIXO | D15: ESTACA/KM INICIAL | F15: ESTACA/KM FINAL | H15: LADO | I15: QUANTIDADE | J15: QUANTIDADE ACUMULADA | K15: OBSERVAÇÃO | N15: MEDIÇÃO | P15: ITEM REFERÊNCIA
D16: INTEIRA | E16: FRAÇÃO | F16: INTEIRA | G16: FRAÇÃO | P16: CÓDIGO | Q16: DESCRIÇÃO
B17: BR381 | C17: DIVERSOS | I17: 0.5 | J17: =IF(OR(B17="",I17=""),"",IF(AND(J16="",N17=""),J16,SUM(I17,J16))) -> 0.5 | K17: EXECUÇÃO DE DESVIOS E TALUDES | N17: 1 | P17: A.1 | Q17: =IF($P17="","",VLOOKUP($P17,RESUMO!$C:$D,2,FALSE)) -> Mobilização e desmobilização | S17: =HYPERLINK("#"&"'"&P17&"'"&"!A1","LINK") -> LINK
B18: BR381 | C18: DIVERSOS | I18: 0.5 | J18: =IF(B18="","",IF(OR(J17="",N18=""),J17,SUM(I18,J17))) -> 1 | K18: EXECUÇÃO DE DESVIOS E TALUDES | N18: 2 | P18: A.2 | Q18: =IF($P18="","",VLOOKUP($P18,RESUMO!$C:$D,2,FALSE)) -> Sinalização e desvio de tráfego | S18: =HYPERLINK("#"&"'"&P18&"'"&"!A1","LINK") -> LINK
J19: =IF(B19="","",IF(OR(J18="",N19=""),J18,SUM(I19,J18))) | P19: A.3 | Q19: =IF($P19="","",VLOOKUP($P19,RESUMO!$C:$D,2,FALSE)) -> Administração local | S19: =HYPERLINK("#"&"'"&P19&"'"&"!A1","LINK") -> LINK
J20: =IF(B20="","",IF(OR(J19="",N20=""),J19,SUM(I20,J19)))
J21: =IF(B21="","",IF(OR(J20="",N21=""),J20,SUM(I21,J20)))
J22: =IF(B22="","",IF(OR(J21="",N22=""),J21,SUM(I22,J21)))
J23: =IF(B23="","",IF(OR(J22="",N23=""),J22,SUM(I23,J22)))
J24: =IF(B24="","",IF(OR(J23="",N24=""),J23,SUM(I24,J23)))
J25: =IF(B25="","",IF(OR(J24="",N25=""),J24,SUM(I25,J24)))
J26: =IF(B26="","",IF(OR(J25="",N26=""),J25,SUM(I26,J25)))
J27: =IF(B27="","",IF(OR(J26="",N27=""),J26,SUM(I27,J26)))
J28: =IF(B28="","",IF(OR(J27="",N28=""),J27,SUM(I28,J27)))
J29: =IF(B29="","",IF(OR(J28="",N29=""),J28,SUM(I29,J28)))
J30: =IF(B30="","",IF(OR(J29="",N30=""),J29,SUM(I30,J29)))

Sheet A.3
B2: QUADRO RESUMO | E2: CONTRATO | J2: HISTÓRICO DE MEDIÇÃO: | P2: NAVEGAÇÃO
E3: QUANTIDADES | G3: R$ FINANCEIRO
B4: QUANTIDADE DE PROJETO: | E4: =IF($G$13="","",VLOOKUP($G$13,RESUMO!$C:$G,5,FALSE)) -> 1 | G4: =E4*$M$13 -> 482795.22
B5: QUANTIDADE ACUMULADA: | E5: =SUMIFS(I:I,N:N,"<>") -> 1 | G5: =E5*$M$13 -> 482795.22
B6: QUANTIDADE ACUM. ANTERIOR: | E6: =E5-E9 -> 1 | G6: =E6*$M$13 -> 482795.22
B7: SALDO CONTRATUAL: | E7: =E4-E5 -> 0 | G7: =E7*$M$13 -> 0
B8: NÃO MEDIDO: | E8: =SUM(I:I)-E5 -> 0 | G8: =E8*$M$13 -> 0
B9: MEDIÇÃO ATUAL: | E9: =SUMIF(N:N,CAPA!$I$2,I:I) -> 0 | G9: =E9*$M$13 -> 0
B11: GRUPO | G11: ITEM
B12: CÓDIGO | C12: DESCRIÇÃO | G12: CÓDIGO | H12: DESCRIÇÃO | L12: UNIDADE | M12: R$ UNIT.
B13: =RESUMO!C8 -> A. | C13: =IF($B$13="","",VLOOKUP($B$13,RESUMO!$C:$F,2,FALSE)) -> Custos Indiretos | G13: =RESUMO!C11 -> A.3 | H13: =IF($G$13="","",VLOOKUP($G$13,RESUMO!$C:$F,2,FALSE)) -> Administração local | L13: =IF($G$13="","",VLOOKUP($G$13,RESUMO!$C:$F,3,FALSE)) -> vb. | M13: =IF($G$13="","",VLOOKUP($G$13,RESUMO!$C:$F,4,FALSE)) -> 482795.22
B15: LOCAL | C15: EIXO | D15: ESTACA/KM INICIAL | F15: ESTACA/KM FINAL | H15: LADO | I15: QUANTIDADE | J15: QUANTIDADE ACUMULADA | K15: OBSERVAÇÃO | N15: MEDIÇÃO | P15: ITEM REFERÊNCIA
D16: INTEIRA | E16: FRAÇÃO | F16: INTEIRA | G16: FRAÇÃO | P16: CÓDIGO | Q16: DESCRIÇÃO
B17: BR381 | C17: DIVERSOS | I17: 0.5 | J17: =IF(OR(B17="",I17=""),"",IF(AND(J16="",N17=""),J16,SUM(I17,J16))) -> 0.5 | K17: EXECUÇÃO DE DESVIOS E TALUDES | N17: 1 | P17: A.1 | Q17: =IF($P17="","",VLOOKUP($P17,RESUMO!$C:$D,2,FALSE)) -> Mobilização e desmobilização | S17: =HYPERLINK("#"&"'"&P17&"'"&"!A1","LINK") -> LINK
B18: BR381 | C18: DIVERSOS | I18: 0.5 | J18: =IF(B18="","",IF(OR(J17="",N18=""),J17,SUM(I18,J17))) -> 1 | K18: EXECUÇÃO DE DESVIOS E TALUDES | N18: 2 | P18: A.2 | Q18: =IF($P18="","",VLOOKUP($P18,RESUMO!$C:$D,2,FALSE)) -> Sinalização e desvio de tráfego | S18: =HYPERLINK("#"&"'"&P18&"'"&"!A1","LINK") -> LINK
J19: =IF(B19="","",IF(OR(J18="",N19=""),J18,SUM(I19,J18))) | P19: A.3 | Q19: =IF($P19="","",VLOOKUP($P19,RESUMO!$C:$D,2,FALSE)) -> Administração local | S19: =HYPERLINK("#"&"'"&P19&"'"&"!A1","LINK") -> LINK
J20: =IF(B20="","",IF(OR(J19="",N20=""),J19,SUM(I20,J19)))
J21: =IF(B21="","",IF(OR(J20="",N21=""),J20,SUM(I21,J20)))
J22: =IF(B22="","",IF(OR(J21="",N22=""),J21,SUM(I22,J21)))
J23: =IF(B23="","",IF(OR(J22="",N23=""),J22,SUM(I23,J22)))
J24: =IF(B24="","",IF(OR(J23="",N24=""),J23,SUM(I24,J23)))
J25: =IF(B25="","",IF(OR(J24="",N25=""),J24,SUM(I25,J24)))
J26: =IF(B26="","",IF(OR(J25="",N26=""),J25,SUM(I26,J25)))
J27: =IF(B27="","",IF(OR(J26="",N27=""),J26,SUM(I27,J26)))
J28: =IF(B28="","",IF(OR(J27="",N28=""),J27,SUM(I28,J27)))
J29: =IF(B29="","",IF(OR(J28="",N29=""),J28,SUM(I29,J28)))
J30: =IF(B30="","",IF(OR(J29="",N30=""),J29,SUM(I30,J29)))

Sheet B.1.1
B2: QUADRO RESUMO | E2: CONTRATO | J2: HISTÓRICO DE MEDIÇÃO: | S2: NAVEGAÇÃO
E3: QUANTIDADES | G3: R$ FINANCEIRO
B4: QUANTIDADE DE PROJETO: | E4: =IF($G$13="","",VLOOKUP($G$13,RESUMO!$C:$G,5,FALSE)) -> 0 | G4: =E4*$P$13 -> 0
B5: QUANTIDADE ACUMULADA: | E5: =SUMIFS(L:L,Q:Q,"<>") -> 0 | G5: =E5*$P$13 -> 0
B6: QUANTIDADE ACUM. ANTERIOR: | E6: =E5-E9 -> 0 | G6: =E6*$P$13 -> 0
B7: SALDO CONTRATUAL: | E7: =E4-E5 -> 0 | G7: =E7*$P$13 -> 0
B8: NÃO MEDIDO: | E8: =SUM(L:L)-E5 -> 0 | G8: =E8*$P$13 -> 0
B9: MEDIÇÃO ATUAL: | E9: =SUMIF(Q:Q,CAPA!$I$2,L:L) -> 0 | G9: =E9*$P$13 -> 0
B11: GRUPO | G11: ITEM
B12: CÓDIGO | C12: DESCRIÇÃO | G12: CÓDIGO | H12: DESCRIÇÃO | O12: UNIDADE | P12: R$ UNIT.
B13: =RESUMO!C13 -> B.1 | C13: =IF($B$13="","",VLOOKUP($B$13,RESUMO!$C:$F,2,FALSE)) -> Terraplenagem | G13: =RESUMO!C14 -> B.1.1 | H13: =IF($G$13="","",VLOOKUP($G$13,RESUMO!$C:$F,2,FALSE)) -> Escavação, carga e transporte de material de 1ª categoria - DMT de 800 a 1.000 m - caminho de serviço pavimentado - com escavadeira e caminhão basculante de 14 m³ | O13: =IF($G$13="","",VLOOKUP($G$13,RESUMO!$C:$F,3,FALSE)) -> m³ | P13: =IF($G$13="","",VLOOKUP($G$13,RESUMO!$C:$F,4,FALSE)) -> 0
B15: LOCAL | C15: EIXO | D15: ESTACA/KM INICIAL | F15: ESTACA/KM FINAL | H15: LADO | I15: SENTIDO | J15: COMP. | K15: LARGURA | L15: QUANTIDADE | M15: QUANTIDADE ACUMULADA | N15: OBSERVAÇÃO | Q15: MEDIÇÃO | S15: ITEM REFERÊNCIA
D16: INTEIRA | E16: FRAÇÃO | F16: INTEIRA | G16: FRAÇÃO | J16: (m) | K16: (m) | S16: CÓDIGO | T16: DESCRIÇÃO
S17: B.1.1 | T17: =IF($S17="","",VLOOKUP($S17,RESUMO!$C:$D,2,FALSE)) -> Escavação, carga e transporte de material de 1ª categoria - DMT de 800 a 1.000 m - caminho de serviço pavimentado - com escavadeira e caminhão basculante de 14 m³ | V17: =HYPERLINK("#"&"'"&S17&"'"&"!A1","LINK") -> LINK
S18: B.1.2 | T18: =IF($S18="","",VLOOKUP($S18,RESUMO!$C:$D,2,FALSE)) -> Escavação e carga de material de 1ª categoria - DMT acima de 3.000 m | V18: =HYPERLINK("#"&"'"&S18&"'"&"!A1","LINK") -> LINK
L19: =IF(J19="","",J19*K19) | M19: =IF(B19="","",IF(OR(M18="",Q19=""),M18,SUM(L19,M18))) | S19: B.1.3 | T19: =IF($S19="","",VLOOKUP($S19,RESUMO!$C:$D,2,FALSE)) -> Transporte com caminhão basculante de 10 m³ - rodovia pavimentada (DMT 5 Km) | V19: =HYPERLINK("#"&"'"&S19&"'"&"!A1","LINK") -> LINK
L20: =IF(J20="","",J20*K20) | M20: =IF(B20="","",IF(OR(M19="",Q20=""),M19,SUM(L20,M19))) | S20: B.1.4 | T20: =IF($S20="","",VLOOKUP($S20,RESUMO!$C:$D,2,FALSE)) -> Regularização de bota-fora com espalhamento e execução de hidrossemeadura | V20: =HYPERLINK("#"&"'"&S20&"'"&"!A1","LINK") -> LINK
L21: =IF(J21="","",J21*K21) | M21: =IF(B21="","",IF(OR(M20="",Q21=""),M20,SUM(L21,M20))) | S21: B.1.5 | T21: =IF($S21="","",VLOOKUP($S21,RESUMO!$C:$D,2,FALSE)) -> Royaltie de bota-fora | V21: =HYPERLINK("#"&"'"&S21&"'"&"!A1","LINK") -> LINK
L22: =IF(J22="","",J22*K22) | M22: =IF(B22="","",IF(OR(M21="",Q22=""),M21,SUM(L22,M21)))
L23: =IF(J23="","",J23*K23) | M23: =IF(B23="","",IF(OR(M22="",Q23=""),M22,SUM(L23,M22)))
L24: =IF(J24="","",J24*K24) | M24: =IF(B24="","",IF(OR(M23="",Q24=""),M23,SUM(L24,M23)))
L25: =IF(J25="","",J25*K25) | M25: =IF(B25="","",IF(OR(M24="",Q25=""),M24,SUM(L25,M24)))
L26: =IF(J26="","",J26*K26) | M26: =IF(B26="","",IF(OR(M25="",Q26=""),M25,SUM(L26,M25)))
L27: =IF(J27="","",J27*K27) | M27: =IF(B27="","",IF(OR(M26="",Q27=""),M26,SUM(L27,M26)))
L28: =IF(J28="","",J28*K28) | M28: =IF(B28="","",IF(OR(M27="",Q28=""),M27,SUM(L28,M27)))
L29: =IF(J29="","",J29*K29) | M29: =IF(B29="","",IF(OR(M28="",Q29=""),M28,SUM(L29,M28)))
L30: =IF(J30="","",J30*K30) | M30: =IF(B30="","",IF(OR(M29="",Q30=""),M29,SUM(L30,M29)))
L31: =IF(J31="","",J31*K31) | M31: =IF(B31="","",IF(OR(M30="",Q31=""),M30,SUM(L31,M30)))
L32: =IF(J32="","",J32*K32) | M32: =IF(B32="","",IF(OR(M31="",Q32=""),M31,SUM(L32,M31)))
L33: =IF(J33="","",J33*K33) | M33: =IF(B33="","",IF(OR(M32="",Q33=""),M32,SUM(L33,M32)))
... L36: =IF(J36="","",J36*K36) | M36: =IF(B36="","",IF(OR(M35="",Q36=""),M35,SUM(L36,M35)))

Sheet B.1.2
B2: QUADRO RESUMO | E2: CONTRATO | J2: HISTÓRICO DE MEDIÇÃO: | T2: NAVEGAÇÃO
E3: QUANTIDADES | G3: R$ FINANCEIRO
B4: QUANTIDADE DE PROJETO: | E4: =IF($G$13="","",VLOOKUP($G$13,RESUMO!$C:$G,5,FALSE)) -> 72616.71 | G4: =E4*$Q$13 -> 1151937.7
B5: QUANTIDADE ACUMULADA: | E5: =SUMIFS(M:M,R:R,"<>") -> 68762.526 | G5: =E5*$Q$13 -> 1090797.8
B6: QUANTIDADE ACUM. ANTERIOR: | E6: =E5-E9 -> 62616.71 | G6: =E6*$Q$13 -> 993305.14
B7: SALDO CONTRATUAL: | E7: =E4-E5 -> 3854.184 | G7: =E7*$Q$13 -> 61139.922
B8: NÃO MEDIDO: | E8: =SUM(M:M)-E5 -> 0 | G8: =E8*$Q$13 -> 0
B9: MEDIÇÃO ATUAL: | E9: =SUMIF(R:R,CAPA!$I$2,M:M) -> 6145.816 | G9: =E9*$Q$13 -> 97492.676
B11: GRUPO | G11: ITEM
B12: CÓDIGO | C12: DESCRIÇÃO | G12: CÓDIGO | H12: DESCRIÇÃO | P12: UNIDADE | Q12: R$ UNIT.
B13: =RESUMO!C13 -> B.1 | C13: =IF($B$13="","",VLOOKUP($B$13,RESUMO!$C:$F,2,FALSE)) -> Terraplenagem | G13: =RESUMO!C15 -> B.1.2 | H13: =IF($G$13="","",VLOOKUP($G$13,RESUMO!$C:$F,2,FALSE)) -> Escavação e carga de material de 1ª categoria - DMT acima de 3.000 m | P13: =IF($G$13="","",VLOOKUP($G$13,RESUMO!$C:$F,3,FALSE)) -> m³ | Q13: =IF($G$13="","",VLOOKUP($G$13,RESUMO!$C:$F,4,FALSE)) -> 15.86326
B15: LOCAL | C15: EIXO | D15: ESTACA/KM INICIAL | F15: ESTACA/KM FINAL | H15: LADO | I15: SENTIDO | J15: COMP. | K15: LARGURA | L15: ALTURA | M15: QUANTIDADE | N15: QUANTIDADE ACUMULADA | O15: OBSERVAÇÃO | R15: MEDIÇÃO | T15: ITEM REFERÊNCIA
D16: INTEIRA | E16: FRAÇÃO | F16: INTEIRA | G16: FRAÇÃO | J16: (m) | K16: (m) | L16: (m) | T16: CÓDIGO | U16: DESCRIÇÃO
B17: BR381 | C17: EIXO | D17: 297 | E17: 500 | H17: ESQUERDO | I17: CRESCENTE | M17: 62616.71 | N17: =IF(OR(B17="",M17=""),"",IF(AND(N16="",R17=""),N16,SUM(M17,N16))) -> 62616.71 | O17: CONFORME PLANTA (AUTOCAD) | R17: 2 | T17: B.1.1 | U17: =IF($T17="","",VLOOKUP($T17,RESUMO!$C:$D,2,FALSE)) -> Escavação, carga e transporte de material de 1ª categoria - DMT de 800 a 1.000 m - caminho de serviço pavimentado - com escavadeira e caminhão basculante de 14 m³ | W17: =HYPERLINK("#"&"'"&T17&"'"&"!A1","LINK") -> LINK
B18: BR381 | C18: EIXO | D18: 297 | E18: 500 | H18: ESQUERDO | I18: CRESCENTE | M18: =68762.526-M17 -> 6145.816 | N18: =N17+M18 -> 68762.526 | O18: CONFORME PLANTA (AUTOCAD) | R18: 3 | T18: B.1.2 | U18: =IF($T18="","",VLOOKUP($T18,RESUMO!$C:$D,2,FALSE)) -> Escavação e carga de material de 1ª categoria - DMT acima de 3.000 m | W18: =HYPERLINK("#"&"'"&T18&"'"&"!A1","LINK") -> LINK
T19: B.1.3 | U19: =IF($T19="","",VLOOKUP($T19,RESUMO!$C:$D,2,FALSE)) -> Transporte com caminhão basculante de 10 m³ - rodovia pavimentada (DMT 5 Km) | W19: =HYPERLINK("#"&"'"&T19&"'"&"!A1","LINK") -> LINK
T20: B.1.4 | U20: =IF($T20="","",VLOOKUP($T20,RESUMO!$C:$D,2,FALSE)) -> Regularização de bota-fora com espalhamento e execução de hidrossemeadura | W20: =HYPERLINK("#"&"'"&T20&"'"&"!A1","LINK") -> LINK
T21: B.1.5 | U21: =IF($T21="","",VLOOKUP($T21,RESUMO!$C:$D,2,FALSE)) -> Royaltie de bota-fora | W21: =HYPERLINK("#"&"'"&T21&"'"&"!A1","LINK") -> LINK
M23: =IF(J23="","",J23*K23*L23) | N23: =IF(B23="","",IF(OR(N22="",R23=""),N22,SUM(M23,N22)))
